Workbook

Sheet GALLASTEGUI
D1: AC109RC | E1: Y | F1: AE754XE
A2: DIA | B2: SALE DE | C2: LLEGA A | D2: KM REC | E2: TN COM 29 | F2: TN ESC 35 | G2: TN ESC 37,5 | H2: REMITO Nº | I2: MATERIAL | J2: KM VACIOS | K2: $
A3: 46143 | B3: BAJO DEL TORO | C3: L. NEGRA | D3: 1070 | H3: VACIO
A4: 46146 | B4: L. NEGRA | C4: SAN FERNANDO | D4: 420 | H4: 769486
A5: 46147 | B5: SAN FERNANDO | C5: IBICUY | D5: 150 | H5: VACIO
A6: 46147 | B6: IBICUY | C6: AÑELO | D6: 1430 | H6: 125232 | I6: YPF
A7: 46150 | B7: AÑELO | C7: L. NEGRA | D7: 940 | H7: VACIO
A8: 46153 | B8: L. NEGRA | C8: J. C. PAZ | D8: 390 | H8: 771149
A9: 46154 | B9: J. C. PAZ | C9: IBICUY | D9: 170 | H9: VACIO
A10: 46154 | B10: IBICUY | C10: BANDUR | D10: 1470 | H10: 12583 | I10: YPF BANDUR
A11: 46157 | B11: BANDUR | C11: L. NEGRA | D11: 950 | H11: VACIO
A12: 46158 | B12: L. NEGRA | C12: CAMPANA | D12: 420 | G12: 36.49 | H12: 621736 | I12: CLINKER
A13: 46160
A28: 46116 | B28: L. NEGRA | C28: CAMPANA | D28: 420 | G28: 36.42 | H28: 619012 | I28: CLINKER
A29: 46118 | B29: CAMPANA | C29: SIDERCA | D29: 10 | H29: VACIO
A30: 46119 | B30: SIDERCA | C30: CATAMARCA | D30: 990 | G30: 36.04 | H30: 153050 | I30: SIDERCA | K30: 1766494.1
A31: 46120 | B31: CATAMARCA | C31: CORDOBA | D31: 380 | H31: 503424 | K31: 1119388.3
A32: 46121 | B32: CORDOBA | C32: MALAGUEÑO | D32: 50 | H32: VACIO
A33: 46121 | B33: MALAGUEÑO | C33: ROSARIO | D33: 430 | H33: 303243 | I33: PIEDRA
A34: 46122 | B34: ROSARIO | C34: RAMALLO | D34: 80 | H34: VACIO
A35: 46123 | B35: RAMALLO | C35: L. NEGRA | D35: 500 | G35: 36.18 | H35: 1064632 | I35: LODO
A36: 46125 | B36: L. NEGRA | C36: DOLORES | D36: 370 | H36: 766061
A37: 46125 | B37: DOLORES | C37: L. NEGRA | D37: 370 | H37: VACIO
A38: 46126 | B38: L. NEGRA | C38: SAN EFRNANDO | D38: 420 | H38: 766275
A39: 46127 | B39: SAN FERNANDO | C39: IBICUY | D39: 150 | H39: VACIO
A40: 46127 | B40: IBICUY | C40: BAJO DEL TORO | D40: 1560 | H40: 121254 | I40: YPF TORO
A41: 46130 | B41: BAJO DEL TORO | C41: ALLEN | D41: 270 | H41: VACIO
A42: 46132 | B42: ALLEN | C42: L. NEGRA | D42: 820 | G42: 35.5 | H42: 189570 | I42: YESO LOMA
A43: 46134 | B43: L. NEGRA | C43: ZAPALA | D43: 1010 | G43: 35.29 | H43: 620124 | I43: CLINKER
A44: 46135 | B44: ZAPALA | C44: ALLEN | D44: 240 | H44: VACIO
A45: 46136 | B45: ALLEN | C45: L. NEGRA | D45: 820 | G45: 35.1 | H45: 189848 | I45: YESO LOMA
A46: 46137 | B46: L. NEGRA | C46: SAN EFRNANDO | D46: 420 | G46: 35.34 | H46: 249561 | I46: FENOMIX
A47: 46139 | B47: SAN FERNANDO | C47: IBICUY | D47: 150 | H47: VACIO
A48: 46140 | B48: IBICUY | C48: BAJO DEL TORO | D48: 1560 | H48: 121254 | I48: YPF TORO
D49: 1 A LAS 8
D51: =SUM(D21:D50) -> 11020 | G51: =AVERAGE(G21:G49) -> 35.695714 | J51: =SUM(J21:J50) -> 0 | K51: =SUM(K21:K49) -> 2885882.4
B53: -1768.41 | C53: ,
B54: -300 | C54: ADELANTO | D54: 44083
B55: 140 | C55: PEAJES
B56: 490 | C56: PEAJES
B57: -500 | C57: ADELANTO | D57: 44104
B58: 795 | C58: PEAJES | D58: 44123
B59: -900 | C59: ADELANTO | D59: 44123
B60: 480 | C60: PEAJES
B61: -500 | C61: ADELANTO
B62: 490 | C62: PEAJES | D62: 44224
B63: -500 | C63: ADELANTO | D63: 44224
B64: 300 | C64: PESADA | D64: 44250
B65: -300 | C65: ADELANTO
B66: 300 | C66: BALANZA | D66: 44257
B67: -300 | C67: ADELANTO
B68: 260 | C68: PEAJES | D68: 44292
B69: -200 | C69: ADELANTO | D69: 44292
B70: 315 | C70: PEAJES | D70: 44321
B71: -400 | C71: ADELANTO
B72: 995 | C72: PEAJES
B73: -1000 | C73: ADELANTO | D73: 44373
B74: 520 | C74: PEAJES | D74: 44394
B75: -500 | C75: ADELANTO
B76: 880 | C76: PEAJES | D76: 44580
B77: -800 | C77: ADELANTO
B78: 360 | C78: peajes | D78: 44582
B79: -400 | C79: adelanto
B80: 400 | C80: PEAJES
B81: -400 | C81: ADELANTO
B82: 360 | C82: PEAJES | D82: 44596
B83: -400 | C83: ADELANTO | D83: 44596
B84: 600 | C84: PEAJES | D84: 44600
B85: -600 | C85: ADELANTO | D85: 44600
B86: 1130 | C86: PEAJES | D86: 44609
B87: -1100 | C87: ADELANTO
B88: 680 | C88: PEAJES | D88: 44692
B89: -700 | C89: ADELANTO
B90: 280 | C90: PEAJES
B91: -300 | C91: ADELANTO
B92: -560 | C92: ANTEC PENAL | D92: 44714
B93: 720 | C93: PEAJES | D93: 44757
B94: 720 | C94: PEAJES | D94: 44770
B95: -800 | C95: ADELANTO | D95: 44770
B96: -1000 | C96: ADELANTO | D96: 44795
B97: 2720 | C97: PEAJES | D97: 44797
B98: -2800 | C98: ADELANTO | D98: 44797
B99: 920 | C99: PEAJES
B100: -920 | C100: ADELANTO
B101: 400 | C101: PEAJES | D101: 44861
B102: 400 | C102: PEAJES | D102: 44863
B103: -400 | C103: ADELANTO
B104: 400 | C104: PEAJES | D104: 44876
B105: -500 | C105: ADELANTO
B106: 800 | C106: PEAJES
B107: -800 | C107: ADELANTO
B108: 1600 | C108: PEAJES
B109: -900 | C109: ADELANTO
B110: 400 | C110: PEAJES
B111: -400 | C111: ADELANTO
B112: 800 | C112: PEAJES
B113: -800 | C113: ADELANTO
B114: -300 | C114: ANTEC PENAL
B115: 1200 | C115: PEAJES | D115: 45065
B116: -1200 | C116: ADELANTO
...

Sheet SCHWINDT
A2: DIA | B2: SALE DE | C2: LLEGA A | D2: KM REC | E2: TN COM 29 | F2: TN ESC 35 | G2: TN ESC 37,5 | H2: REMITO Nº | I2: MATERIAL | J2: KM VACIOS | K2: $
A3: 46142 | B3: L. NEGRA | C3: RAMALLO | D3: 500 | H3: 620592
A4: 46144 | B4: RAMALLO | C4: L. NEGRA | D4: 500 | F4: 34.33 | H4: 1068078 | I4: ESCORIA
A5: 46146 | B5: L. NEGRA | C5: ZAPALA | D5: 1010 | H5: 620763 | I5: CLINKER
A6: 46148 | B6: ZAPALA | C6: ALLEN | D6: 240 | H6: VACIO
A7: 46148 | B7: ALLEN | C7: L. NEGRA | D7: 820 | F7: 34.1 | H7: 190230 | I7: YESO LOMA
A8: 46151 | B8: L. NEGRA | C8: ZAPALA | D8: 1010 | H8: 621109 | I8: CLINKER
A9: 46153 | B9: ZAPALA | C9: ALLEN | D9: 240 | H9: VACIO
A10: 46154 | B10: ALLEN | C10: L. NEGRA | D10: 820 | F10: 34.3 | H10: 190426 | I10: YESO LOMA
A11: 46155 | B11: L. NEGRA | C11: BAHIA BLANCA | D11: 320 | F11: 35.1 | H11: 295923 | I11: PIEDRA
A12: 46157 | B12: BAHIA BLANCA | C12: BARKER | D12: 350 | H12: VACIO
A25: 46116 | B25: L. NEGRA | C25: CAMPANA | D25: 420 | F25: 35.42 | H25: 618968 | I25: CLINKER
A26: 46118 | B26: CAMPANA | C26: SIDERCA | D26: 10 | H26: VACIO
A27: 46119 | B27: CAMPANA | C27: CATAMARCA | D27: 990 | F27: 34.72 | H27: 153029 | I27: SIDERCA | K27: 1701794.6
A28: 46120 | B28: CATAMARCA | C28: CORDOBA | D28: 380 | H28: 503419 | K28: 1057200.1
A29: 46121 | B29: CORDOBA | C29: MALAGUEÑO | D29: 50 | H29: VACIO
A30: 46121 | B30: MALAGUEÑO | C30: ROSARIO | D30: 430 | F30: 34.64 | H30: 303245 | I30: PIEDRA
A31: 46122 | B31: ROSARIO | C31: RAMALLO | D31: 80 | H31: VACIO
A32: 46123 | B32: RAMALLO | C32: L. NEGRA | D32: 500 | F32: 34.28 | H32: 1064638 | I32: LODO
A33: 46095 | B33: L. NEGRA | C33: ZAPALA | D33: 1010 | F33: 34.49 | H33: 619623 | I33: CLINKER
A34: 46127 | B34: ZAPALA | C34: ALLEN | D34: 240 | H34: VACIO
A35: 46128 | B35: ALLEN | C35: L. NEGRA | D35: 820 | F35: 34 | H35: 189594 | I35: YESO LOMA
A36: 46129 | B36: L. NEGRA | C36: C. FEDERAL | D36: 380 | H36: 294009 | I36: PIEDRA
A37: 46132 | B37: C. FEDERAL | C37: IBICUY | D37: 170 | H37: VACIO
A38: 46133 | B38: IBICUY | C38: RAMALLO | D38: 230 | H38: VACIO
A39: 46133 | B39: RAMALLO | C39: L. NEGRA | D39: 500 | F39: 34.67 | H39: 1066227 | I39: ESCORIA
A40: 46134 | B40: L. NEGRA | C40: ZAPALA | D40: 1010 | F40: 35.26 | H40: 620105 | I40: CLINKER
A41: 46135 | B41: ZAPALA | C41: ALLEN | D41: 240 | H41: VACIO
A42: 46136 | B42: ALLEN | C42: L. NEGRA | D42: 820 | F42: 33.7 | H42: 189877 | I42: YESO LOMA
A43: 46140 | B43: L. NEGRA | C43: CAMPANA | D43: 420 | F43: 34.24 | H43: 620423 | I43: CLINKER
A44: 46140 | B44: CAMPANA | C44: SIDERAR | D44: 150 | H44: VACIO
A45: 46141 | B45: SIDERAR | C45: RAMALLO | D45: 10 | H45: 1067612 | I45: CORTO
A46: 46141 | B46: RAMALLO | C46: SIDERAR | D46: 10 | H46: VACIO
A47: 46141 | B47: SIDERAR | C47: RAMALLO | D47: 10 | H47: 1067646 | I47: CORTO
A48: 46141 | B48: RAMALLO | C48: SIDERAR | D48: 10 | H48: VACIO
A49: 46141 | B49: SIDERAR | C49: L. NEGRA | D49: 500 | F49: 34.21 | H49: 1067677 | I49: ESCORIA
D50: 30 A LAS 11
D52: =SUM(D3:D51) -> 15200 | F52: =AVERAGE(F3:F50) -> 34.497333 | J52: =SUM(J3:J51) -> 0 | K52: =SUM(K3:K51) -> 2758994.6
B54: -2131.06
B55: 200 | C55: PEAJES | D55: 43756
B56: 1500 | C56: PEAJES | D56: 43760
B57: -1600 | C57: ADELANTO
B58: 200 | C58: PEAJES | D58: 43763
B59: -400 | C59: ADELANTO | D59: 43763
B60: 1965 | C60: PEAJES | D60: 43768
B61: -1800 | C61: ADELANTO
B62: 2305 | C62: PEAJES | D62: 43775
B63: -2500 | C63: ADELANTO
B64: 700 | C64: PEAJES | D64: 43782
B65: -700 | C65: ADELANTO | D65: 43796
B66: 200 | C66: PEAJES
B67: 200 | C67: PEAJES | D67: 43797
B68: 200 | C68: PEAJES | D68: 43813
B69: -600 | C69: ADELANTO
B70: 200 | C70: PEAJES
B71: 500 | C71: 2 CAMBIO GOMA | D71: 43866
B72: 350 | C72: PEAJES
B73: -1000 | C73: ADELANTO
B74: 250 | C74: BALANZA
B75: 250 | C75: BALANZA | D75: 43893
B76: 250 | C76: BALANZA | D76: 43908
B77: -600 | C77: ADELANTO
B78: 200 | C78: PEAJES
B79: -200 | C79: ADELANTO
B80: 480 | C80: PEAJES
B81: -500 | C81: ADELANTO
B82: 2610 | C82: PEAJES | D82: 44212
B83: -2600 | C83: ADELANTO
B84: 300 | C84: BALANZA
B85: -300 | C85: ADELANTO
B86: 630 | C86: PEAJES
B87: -630 | C87: ADELANTO
B88: 300 | C88: PEAJES
B89: -300 | C89: ADELANTO
B90: 220 | C90: PEAJES
B91: -200 | C91: ADELANTO
B92: 620 | C92: peajes
B93: -600 | C93: ADELANTO
B94: 520 | C94: PEAJES
B95: -500 | C95: ADELANTO
B96: 600 | C96: GOMERIA | D96: 44525
B97: -600 | C97: ADELANTO | D97: 44531
B98: 1100 | C98: GOMERIA | D98: 44575
B99: -1100 | C99: ADEALNTO
B100: 880 | C100: PEAJES | D100: 44579
B101: -900 | C101: ADELANTO | D101: 44579
B102: 1420 | C102: PEAJES | D102: 44583
B103: -1420 | C103: ADELANTO | D103: 44583
B104: 1600 | C104: PEAJES | D104: 44590
B105: -1600 | C105: ADELANTO | D105: 44590
B106: 420 | C106: PEAJES | D106: 44600
B107: -400 | C107: ADELANTO | D107: 44600
B108: 640 | C108: PEAJES Y BALANZA | D108: 44607
B109: -700 | C109: ADELANTO
B110: 420 | C110: PEAJES | D110: 44622
B111: -400 | C111: ADELANTO | D111: 44622
B112: 880 | C112: PEAJE | D112: 44686
B113: -900 | C113: ADELANTO
B114: 280 | C114: PEAJE | D114: 44720
B115: -300 | C115: ADELANTO
...

Sheet SAENZ BURUAGA
D1: AE169ZO
A2: DIA | B2: SALE DE | C2: LLEGA A | D2: KM REC | E2: TN COM 29 | F2: TN ESC 35 | G2: TN ESC 37,5 | H2: REMITO Nº | I2: MATERIAL | J2: KM VACIOS | K2: $
A3: 46142 | B3: DARSENA | C3: L. NEGRA | D3: 380 | H3: VACIO
A4: 46146 | B4: L. NEGRA | C4: M. DEL PLATA | D4: 320 | F4: 34.56 | H4: 769524
A5: 46147 | B5: M. DEL PLATA | C5: L. NEGRA | D5: 320 | H5: VACIO
A6: 46147 | B6: L. NEGRA | C6: OLAVARRIA | D6: 40 | F6: 34.76 | H6: 769718
A7: 46148 | B7: OLAVARRIA | C7: L. NEGRA | D7: 40 | H7: VACIO
A8: 46148 | B8: L. NEGRA | C8: SOLA | D8: 360 | F8: 35.02 | H8: 769876
A9: 46149 | B9: SOLA | C9: LOMASER | D9: 70 | H9: VACIO
A10: 46149 | B10: LOMASER | C10: RAMALLO | D10: 300 | H10: 899959
A11: 46150 | B11: RAMALLO | C11: SOLA | D11: 240 | F11: 33.18 | H11: 279964 | I11: ESCORIA
A12: 46150 | B12: SOLA | C12: LOMASER | D12: 70 | H12: VACIO
A13: 46150 | B13: LOMASER | C13: CAMPANA | D13: 125 | F13: 35.18 | H13: 900184
A14: 46151 | B14: CAMPANA | C14: RAMALLO | D14: 150 | H14: VACIO
A15: 46151 | B15: RAMALLO | C15: LOMASER | D15: 300 | H15: 280116 | I15: ESCORIA
A16: 46152 | B16: LOMASER | C16: L. NEGRA | D16: 300 | H16: VACIO
A17: 46153 | B17: L. NEGRA | C17: B. DE ESCOBAR | D17: 430 | F17: 35.02 | H17: 771155
A18: 46154 | B18: B. ESCOBAR | C18: LOMASER | D18: 140 | H18: VACIO
A19: 46154 | B19: LOMASER | C19: URIBURU | D19: 340 | F19: 34.75 | H19: 900750
A20: 46155 | B20: URIBURU | C20: RAMALLO | D20: 80 | H20: VACIO
A21: 46155 | B21: RAMALLO | C21: LOMASER | D21: 300 | H21: 280329 | I21: ESCORIA
A22: 46156 | B22: LOMASER | C22: L. NEGRA | D22: 300 | H22: VACIO
A23: 46156 | B23: L. NEGRA | C23: B. DE ESCOBAR | D23: 430 | F23: 35.04 | H23: 771956
A24: 46157
A32: 46113 | B32: L. NEGRA | C32: PEHUAJO | D32: 230 | F32: 34.96 | H32: 764525 | K32: 1196752.1
A33: 46118 | B33: PEHUAJO | C33: SALAZAR | D33: 100 | H33: DERIVACION
A34: 46119 | B34: SALAZAR | C34: L. NEGRA | D34: 170 | H34: VACIO
A35: 46120 | B35: L. NEGRA | C35: OLAVARRIA | D35: 40 | F35: 35.28 | H35: 765177 | K35: 306705.97
A36: 46120 | B36: OLAVARRIA | C36: L. NEGRA | D36: 40 | H36: VACIO
A37: 46121 | B37: L. NEGRA | C37: COLON | D37: 440 | F37: 34.68 | H37: 765424
A38: 46122 | B38: COLON | C38: RAMALLO | D38: 140 | H38: VACIO
A39: 46122 | B39: RAMALLO | C39: LOMASER | D39: 300 | H39: 178847 | I39: ESCORIA
A40: 46123 | B40: LOMASER | C40: L. NEGRA | D40: 300 | H40: VACIO
A41: 46125 | B41: L. NEGRA | C41: OLAVARRIA | D41: 25 | F41: 34.98 | H41: 766071
A42: 46125 | B42: OLAVARRIA | C42: L. NEGRA | D42: 25 | H42: VACIO
A43: 46125 | B43: L. NEGRA | C43: NEUQUEN | D43: 830 | F43: 34.96 | H43: 766166 | K43: 3323016.9
A44: 46126 | B44: NEUQUEN | C44: L. NEGRA | D44: 830 | H44: VACIO
A45: 46127 | B45: L. NEGRA | C45: M. DEL PLATA | D45: 320 | F45: 35.24 | H45: 766440
A46: 46128 | B46: M. DEL PLATA | C46: L. NEGRA | D46: 320 | H46: VACIO
A47: 46128 | B47: L. NEGRA | C47: M. DEL PLATA | D47: 320 | F47: 34.7 | H47: 766670
A48: 46129 | B48: M. DEL PLATA | C48: L. NEGRA | D48: 320 | H48: VACIO
A49: 46132 | B49: L. NEGRA | C49: BOLIVAR | D49: 150 | F49: 35.04 | H49: 767232
A50: 46133 | B50: BOLIVAR | C50: L. NEGRA | D50: 150 | H50: VACIO
A51: 46135 | B51: L. NEGRA | C51: V. GESSEL | D51: 400 | F51: 34.76 | H51: 767730
A52: 46136 | B52: V. GESSEL | C52: L. NEGRA | D52: 400 | H52: VACIO
A53: 46136 | B53: L. NEGRA | C53: G. PACHECO | D53: 430 | F53: 34.72 | H53: 767972
A54: 46139 | B54: G. PACHECO | C54: LOMASER | D54: 120 | H54: VACIO
A55: 46140 | B55: LOMASER | C55: DARSENA | D55: 80 | F55: 34.61 | H55: 898280
A56: 46140 | B56: DARSENA | C56: LOMASER | D56: 80 | H56: VACIO
A57: 46140 | B57: LOMASER | C57: RAMALLO | D57: 300 | H57: 898409
A58: 46141 | B58: RAMALLO | C58: SOLA | D58: 240 | F58: 35.32 | H58: 279549
A59: 46142 | B59: SOLA | C59: LOMASER | D59: 70 | H59: VACIO
A60: 46142 | B60: LOMASER | C60: DARSENA | D60: 80 | H60: 898804
D61: 30 A LAS 19
J62: =SUM(J3:J61) -> 0 | N62: C. PIEDRA BUENA | O62: L. NEGRA | P62: 2075 | T62: VACIO
D63: =SUM(D3:D62) -> 12285 | F63: =AVERAGE(F3:F61) -> 34.838 | K63: =SUM(K3:K61) -> 4826475
B65: -2189.98
B66: 315 | C66: PEAJES
B67: 400 | C67: gomeria | D67: 44094
B68: 490 | C68: PEAJES | D68: 44104
B69: -1100 | C69: adelanto | D69: 44104
B70: 315 | C70: PEAJES | D70: 44117
B71: 620 | C71: PEAJES | D71: 44123
B72: 315 | C72: PEAJES | D72: 44137
B73: -1200 | C73: PEAJES | D73: 44137
B74: 290 | C74: PEAJES
B75: 290 | C75: PEAJES | D75: 44182
B76: -600 | C76: adelanto
B77: 480 | C77: PEAJES
B78: -500 | C78: ADELANTO
B79: 630 | C79: PEAJES | D79: 44195
B80: 130 | C80: PEAJES
B81: -500 | C81: ADELANTO
B82: 790 | C82: PEAJES
B83: -1000 | C83: ADELANO
B84: 300 | C84: PEAJES
B85: 630 | C85: PEAJES | D85: 44294
B86: -1000 | C86: ADELANTO | D86: 44294
B87: 1035 | C87: PEAJES | D87: 44307
B88: -1000 | C88: ADELANTO | D88: 44307
B89: 775 | C89: PEAJES | D89: 44313
B90: -800 | C90: adelanto | D90: 44313
B91: 915 | C91: PEAJES | D91: 44319
B92: 490 | C92: PEAJES | D92: 44350
B93: -1400 | C93: adelanto | D93: 44350
B94: 300 | C94: BALANZA | D94: 44399
B95: 1000 | C95: GOMERIA
B96: -1300 | C96: ADELANTO
B97: 300 | C97: BALANZA
B98: 220 | C98: PEAJES | D98: 44501
B99: 530 | C99: PEAJES | D99: 44568
B100: -1000 | C100: ADELANTO | D100: 44568
B101: 1950 | C101: GOMERIA800 BALANZA420 PEAJE730 | D101: 44607
B102: -2000 | C102: ADELANTO
B103: 800 | C103: balanza | D103: 44618
B104: -560 | C104: ANT. PENALES | D104: 44623
B105: 1040 | C105: PEAJES | D105: 44637
B106: -1300 | C106: ADELANTO | D106: 44637
B107: 730 | C107: PEAJES | D107: 44686
B108: 680 | C108: PEAJES
...

Sheet SCHMIDT
A2: DIA | B2: SALE DE | C2: LLEGA A | D2: KM REC | E2: TN COM 29 | F2: TN ESC 35 | G2: TN ESC 37,5 | H2: REMITO Nº | I2: MATERIAL | J2: KM VACIOS | K2: $
A3: 46142 | B3: IBICUY | C3: AÑELO | D3: 1430 | H3: 125232 | I3: YPF
A4: 46145 | B4: AÑELO | C4: ALLEN | D4: 180 | H4: VACIO
A5: 46146 | B5: ALLEN | C5: L. NEGRA | D5: 820 | F5: 33.8 | H5: 189863 | I5: YESO LOMA
A6: 46147 | B6: L. NEGRA | C6: BERISSO | D6: 360 | F6: 34.94 | H6: 2950.. | I6: PIEDRA
A7: 46148 | B7: BERISSO | C7: IBICUY | D7: 280 | H7: VACIO
A8: 46148 | B8: IBICUY | C8: AÑELO | D8: 1430 | H8: 125350 | I8: YPF
A9: 46149 | B9: AÑELO | C9: L. NEGRA | D9: 940 | H9: VACIO
A10: 46151 | B10: L. NEGRA | C10: ZAPALA | D10: 1010 | H10: 621174 | I10: CLINKER
A11: 46153 | B11: ZAPALA | C11: ALLEN | D11: 240 | H11: VACIO
A12: 46154 | B12: ALLEN | C12: L. NEGRA | D12: 820 | F12: 33.7 | H12: 190274 | I12: YESO LOMA
A13: 46155 | B13: L. NEGRA | C13: CAMPANA | D13: 430 | F13: 35 | H13: 295892 | I13: PIEDRA
A14: 46156 | B14: CAMPANA | C14: IBICUY | D14: 100 | H14: VACIO
A15: 46156 | B15: IBICUY | C15: BANDUR | D15: 1470 | H15: 126926 | I15: YPF BANDUR
A16: 46158 | B16: BANDUR | C16: L. NEGRA | D16: 950 | H16: VACIO
A31: 46113 | B31: IBICUY | C31: AÑELO | D31: 1430 | H31: 80712 | I31: YPF
A32: 46116 | B32: AÑELO | C32: L. NEGRA | D32: 1040 | H32: VACIO
A33: 46119 | B33: L. NEGRA | C33: CAMPANA | D33: 420 | F33: 34.42 | H33: 619133 | I33: CLINKER
A34: 46119 | B34: CAMPANA | C34: SIDERAR | D34: 150 | H34: VACIO
A35: 46120 | B35: SIDERAR | C35: RAMALLO | D35: 10 | H35: 1063950 | I35: CORTO
A36: 46120 | B36: RAMALLO | C36: SIDERAR | D36: 10 | H36: VACIO
A37: 46120 | B37: SIDERAR | C37: RAMALLO | D37: 10 | H37: 1063968 | I37: CORTO
A38: 46120 | B38: RAMALLO | C38: SIDERAR | D38: 10 | H38: VACIO
A39: 46120 | B39: SIDERAR | C39: RAMALLO | D39: 10 | H39: 1063995 | I39: CORTO
A40: 46120 | B40: RAMALLO | C40: SIDERAR | D40: 10 | H40: VACIO
A41: 46120 | B41: SIDERAR | C41: RAMALLO | D41: 10 | H41: 1064015 | I41: CORTO
A42: 46120 | B42: RAMALLO | C42: SIDERAR | D42: 10 | H42: VACIO
A43: 46120 | B43: SIDERAR | C43: RAMALLO | D43: 10 | H43: 1064044 | I43: CORTO
A44: 46121 | B44: RAMALLO | C44: SIDERAR | D44: 10 | H44: VACIO
A45: 46121 | B45: SIDERAR | C45: RAMALLO | D45: 10 | H45: 1064147 | I45: CORTO
A46: 46121 | B46: RAMALLO | C46: L. NEGRA | D46: 500 | H46: ???? | I46: PALLETS
A47: 46122 | B47: L. NEGRA | C47: BARKER | D47: 180 | H47: 765624
A48: 46125 | B48: BARKER | C48: L. NEGRA | D48: 200 | H48: 182596 | I48: M. ROJO
A49: 46126 | B49: L. NEGRA | C49: ZAPALA | D49: 1010 | F49: 34.58 | H49: 619622 | I49: CLINKER
A50: 46127 | B50: ZAPALA | C50: ALLEN | D50: 240 | H50: VACIO
A51: 46128 | B51: ALLEN | C51: L. NEGRA | D51: 820 | F51: 33.8 | H51: 189592 | I51: YESO LOMA
A52: 46129 | B52: L. NEGRA | C52: ZAPALA | D52: 1010 | F52: 34.57 | H52: 619908 | I52: CLINKER
A53: 46133 | B53: ZAPALA | C53: ALLEN | D53: 240 | H53: VACIO
A54: 46134 | B54: ALLEN | C54: L. NEGRA | D54: 820 | F54: 34.1 | H54: 189810 | I54: YESO LOMA
A55: 46135 | B55: L. NEGRA | C55: CAMPANA | D55: 430 | F55: 34.52 | H55: 294444 | I55: PIEDRA
A56: 46136 | B56: CAMPANA | C56: RAMALLO | D56: 150 | H56: VACIO
A57: 46136 | B57: RAMALLO | C57: ZAPALA | D57: 1470 | F57: 32.48 | H57: 1066902 | I57: LODO
A58: 46140 | B58: ZAPALA | C58: L. NEGRA | D58: 1060 | H58: 16440 | I58: TANDILIA
A59: 46141 | B59: L. NEGRA | C59: TORCUATO | D59: 400 | H59: 294739
A60: 46142 | B60: TORCUATO | C60: IBICUY | D60: 150 | H60: VACIO
D61: 30 A LAS 11
D63: =SUM(D3:D62) -> 22290 | F63: =AVERAGE(F3:F61) -> 34.173636 | J63: =SUM(J3:J61) -> 0 | K63: =SUM(K3:K62) -> 0
B65: -2060.32
B66: 200 | C66: ADELANTO | D66: 43760
B67: 1500 | C67: PEAJES | D67: 43761
B68: -1900 | C68: ADELANTO
B69: -1000 | C69: ADELANTO | D69: 43769
B70: 2140 | C70: PEAJES | D70: 43774
B71: -900 | C71: ADELANTO
B72: 2320 | C72: PEAJES | D72: 43775
B73: -2500 | C73: ADELANTO
B74: 2140 | C74: PEAJES | D74: 43781
B75: -2200 | C75: ADELANTO
B76: 200 | C76: PEAJES | D76: 43784
B77: -200 | C77: ADELANTO
B78: 200 | C78: PEAJES | D78: 43791
B79: -200 | C79: ADELANTO
B80: 470 | C80: peajes | D80: 43813
B81: 200 | C81: BALANZA | D81: 43816
B82: -500 | C82: ADELANTO
B83: 400 | C83: PEAJES | D83: 43818
B84: -500 | C84: ADELANTO | D84: 43818
B85: 640 | C85: PEAJES | D85: 43820
B86: -600 | C86: ADELANTO
B87: 250 | C87: PEAJES | D87: 43867
B88: 250 | C88: PEAJES | D88: 43872
B89: -600 | C89: ADELANTO
B90: 200 | C90: PEAJES | D90: 43875
B91: 900 | C91: PEAJEWS Y BALANZA | D91: 43901
B92: -1000 | C92: ADELANTO
B93: 400 | C93: PEAJES | D93: 44113
B94: -400 | C94: ADELANTO | D94: 44113
B95: 890 | C95: PEAJES | D95: 44127
B96: -900 | C96: ADELANTO | D96: 44127
B97: 680 | C97: peaje | D97: 44132
B98: -700 | C98: ADELANTO | D98: 44132
B99: 400 | C99: PEAJES
B100: 200 | C100: PEAJES
B101: -500 | C101: ADELANTO | D101: 44139
B102: 810 | C102: peajes
B103: -800 | C103: adelanto
B104: 480 | C104: PEAJE | D104: 44155
B105: -500 | C105: ADELANTO
B106: 810 | C106: PEAJES
B107: -810 | C107: ADELANTO
B108: 400 | C108: PEAJES
B109: -400 | C109: ADELANTO
B110: 2610 | C110: PEAJES | D110: 44212
B111: -2600 | C111: ADELANTO
B112: 300 | C112: PEAJES | D112: 44221
B113: -300 | C113: ADELANTO | D113: 44221
B114: 630 | C114: PEAJES
B115: -600 | C115: ADELANTO | D115: 44226
B116: 200 | C116: peaje
B117: 500 | C117: BALANZA Y PEAJE | D117: 44268
...

Sheet CEJAS
D1: JTN564
A2: DIA | B2: SALE DE | C2: LLEGA A | D2: KM REC | E2: TN COM 29 | F2: TN ESC 35 | G2: TN ESC 37,5 | H2: REMITO Nº | I2: MATERIAL | J2: KM VACIOS | K2: $
A3: 46142 | B3: ALLEN | C3: L. NEGRA | D3: 820 | F3: 33.5 | H3: 190073 | I3: YESO LOMA
A4: 46144 | B4: L. NEGRA | C4: ZAPALA | D4: 1010 | F4: 34.25 | H4: 620680 | I4: CLINKER
A5: 46147 | B5: ZAPALA | C5: ALLEN | D5: 240 | H5: VACIO
A6: 46147 | B6: ALLEN | C6: L. NEGRA | D6: 820 | F6: 33.5 | H6: 190095 | I6: YESO LOMA
A7: 46148 | B7: L. NEGRA | C7: PUNTA ALTA | D7: 370 | H7: 295169
A8: 46149 | B8: PUNTA ALTA | C8: L. NEGRA | D8: 370 | H8: VACIO
A9: 46151 | B9: L. NEGRA | C9: ZAPALA | D9: 1010 | H9: 621107 | I9: CLINKER
A10: 46153 | B10: ZAPALA | C10: V. REGINA | D10: 280 | H10: VACIO
A11: 46153 | B11: V. REGINA | C11: ALLEN | D11: 90 | H11: 163166
A12: 46154 | B12: ALLEN | C12: L. NEGRA | D12: 820 | F12: 34 | H12: 190432 | I12: YESO LOMA
A13: 46155 | B13: L. NEGRA | C13: TANDIL | D13: 150 | H13: 621453
A14: 46156 | B14: TANDIL | C14: L. NEGRA | D14: 150 | H14: VACIO
A15: 46156 | B15: L. NEGRA | C15: M. DEL PLATA | D15: 320 | H15: 771914
A16: 46157 | B16: M. DEL PLATA | C16: L. NEGRA | D16: 320 | H16: PALLETS | I16: 1 CLIENTE
A29: 46113 | B29: ADELA 6 | C29: L. NEGRA | D29: 970 | H29: VACIO
A30: 46116 | B30: L. NEGRA | C30: CAMPANA | D30: 420 | F30: 34.94 | H30: 619007 | I30: CLINKER
A31: 46118 | B31: CAMPANA | C31: SIDERAR | D31: 150 | H31: VACIO
A32: 46118 | B32: SIDERAR | C32: RAMALLO | D32: 10 | H32: 1063483 | I32: CORTO
A33: 46119 | B33: RAMALLO | C33: SIDERAR | D33: 10 | H33: VACIO
A34: 46119 | B34: SIDERAR | C34: RAMALLO | D34: 10 | H34: 1063606 | I34: CORTO
A35: 46119 | B35: RAMALLO | C35: L. NEGRA | D35: 500 | F35: 34.01 | H35: 1063679 | I35: LODO
A36: 46120 | B36: L. NEGRA | C36: CAMPANA | D36: 420 | F36: 34.68 | H36: 619233 | I36: CLINKER
A37: 46121 | B37: CAMPANA | C37: SIDERAR | D37: 150 | H37: VACIO
A38: 46121 | B38: SIDERAR | C38: RAMALLO | D38: 10 | H38: 1064286 | I38: CORTO
A39: 46122 | B39: RAMALLO | C39: SIDERAR | D39: 10 | H39: VACIO
A40: 46122 | B40: SIDERAR | C40: RAMALLO | D40: 10 | H40: 1064365 | I40: CORTO
A41: 46122 | B41: RAMALLO | C41: L. NEGRA | D41: 500 | H41: 1064490 | I41: LODO
A42: 46126 | B42: L. NEGRA | C42: CAMPANA | D42: 420 | F42: 34.66 | H42: 619581 | I42: CLINKER
A43: 46127 | B43: CAMPANA | C43: SIDERCA | D43: 10 | H43: VACIO
A44: 46127 | B44: CAMPANA | C44: CATAMARCA | D44: 990 | F44: 33.8 | H44: 153208 | I44: SIDERCA
A45: 46128 | B45: CATAMARCA | C45: FERREYRA | D45: 390 | H45: 504061
A46: 46129 | B46: FERREYRA | C46: PAMPAYASTA | D46: 120 | H46: VACIO
A47: 46129 | B47: PAMPAYASTA | C47: ROSARIO | D47: 340 | F47: 33.1 | H47: TKT 21650
A48: 46130 | B48: ROSARIO | C48: RAMALLO | D48: 80 | H48: VACIO
A49: 46130 | B49: RAMALLO | C49: L. NEGRA | D49: 500 | F49: 34.24 | H49: 1065841 | I49: LODO
A50: 46135 | B50: L. NEGRA | C50: CAMPANA | D50: 430 | H50: 292,,, | I50: PIEDRA
A51: 46136 | B51: CAMPANA | C51: RAMALLO | D51: 150 | H51: VACIO
A52: 46136 | B52: RAMALLO | C52: ZAPALA | D52: 1470 | F52: 33.92 | H52: 1066905 | I52: LODO
A53: 46140 | B53: ZAPALA | C53: L. NEGRA | D53: 1060 | H53: 16441 | I53: TANDILIA
A54: 46141 | B54: L. NEGRA | C54: ZAPALA | D54: 1010 | H54: ???? | I54: CLINKER
A55: 46142 | B55: ZAPALA | C55: ALLEN | D55: 240 | H55: VACIO
D56: 30 A LAS 21
D58: =SUM(D3:D57) -> 17150 | F58: =AVERAGE(F3:F56) -> 34.05 | J58: =SUM(J3:J57) -> 0 | K58: =SUM(K3:K57) -> 0
B60: -1796.21
B61: 200 | C61: PEAJES
B62: -500 | C62: ADELANTO
B63: 480 | C63: PEAJES | D63: 44123
B64: -500 | C64: ADELANTO | D64: 72
B65: 480 | C65: PEAJES
B66: -500 | C66: ADELANTO
B67: 1400 | C67: PEAJES | D67: 44196
B68: -1300 | C68: ADELANTO
B69: 260 | C69: PEAJES
B70: 300 | C70: PEAJES | D70: 44270
B71: 800 | C71: GOMERIA | D71: 44270
B72: -1400 | C72: ADELANTO | D72: 44270
B73: 1400 | C73: PEAJES | D73: 44309
B74: -1400 | C74: ADELANTO | D74: 44309
B75: 600 | C75: PEAJES | D75: 44347
B76: 300 | C76: PEAJES | D76: 44352
B77: -900 | C77: PEAJES | D77: 44352
B78: 150 | C78: PEAJES | D78: 44410
B79: -200 | C79: ADELANTO | D79: 44410
B80: 520 | C80: PEAJES | D80: 44421
B81: -500 | C81: ADELANTO | D81: 44421
... B84: 280 | C84: PEAJES | D84: 44445
B85: -300 | C85: ADELANTO
B86: 520 | C86: PEAJES | D86: 44457
B87: -500 | C87: ADELANTO
B88: 280 | C88: PEAJES | D88: 44534
B89: -300 | C89: ADELANTO | D89: 44534
B90: 1000 | C90: GOMERIA
B91: -1000 | C91: ADELANTO
B92: 800 | C92: balanzabk | D92: 44597
B93: -800 | C93: ADELANTO
B94: 420 | C94: peajes | D94: 44614
B95: -400 | C95: ADELANTO | D95: 44614
B96: 800 | C96: GOMERIA
B97: -800 | C97: ADELANTO
B98: 280 | C98: PEAJE | D98: 44681
B99: 1500 | C99: LAVADO ZARATE
B100: -1700 | C100: ADELANTO
B101: 440 | C101: PEAJES | D101: 44692
B102: -500 | C102: ADELANTO
B103: 680 | C103: PEAJES | D103: 44709
B104: -700 | C104: ADELANTO | D104: 44709
B105: 1120 | C105: PEAJES | D105: 44723
B106: -1100 | C106: ADELANTO | D106: 44723
B107: 1500 | C107: GOMERIA | D107: 44748
B108: 680 | C108: PEAJES
B109: -2200 | C109: ADELANTO
B110: 700 | C110: peajes
B111: -700 | C111: ADELANTO
B112: 880 | C112: PEAJES | D112: 44765
B113: -900 | C113: ADELANTO
B114: 640 | C114: PEAJES | D114: 44814
B115: -640 | C115: ADELANTO
B116: 1840 | C116: peajes | D116: 44837
...

Sheet VALERGA
A2: DIA | B2: SALE DE | C2: LLEGA A | D2: KM REC | E2: TN COM 29 | F2: TN ESC 35 | G2: TN ESC 37,5 | H2: REMITO Nº | I2: MATERIAL | J2: KM VACIOS | K2: $
A3: 46143 | B3: IBICUY | C3: BAJO DEL TORO | D3: 1560 | H3: 124223 | I3: YPF TORO
A4: 46146 | B4: BAJO DEL TORO | C4: ALLEN | D4: 270 | H4: VACIO
A5: 46147 | B5: ALLEN | C5: L. NEGRA | D5: 820 | F5: 35.5 | H5: 189873 | I5: YESO LOMA
A6: 46148 | B6: L. NEGRA | C6: M. DEL PLATA | D6: 320 | H6: 769862
A7: 46149 | B7: M. DEL PLATA | C7: L. NEGRA | D7: 320 | H7: VACIO
A8: 46150 | B8: L. NEGRA | C8: CAMPANA | D8: 420 | F8: 36.66 | H8: 621039 | I8: CLINKER
A9: 46151 | B9: CAMPANA | C9: IBICUY | D9: 85 | H9: VACIO
A10: 46151 | B10: IBICUY | C10: BANDUR | D10: 1470 | H10: 125942 | I10: YPF BANDUR
A11: 46154 | B11: BANDUR | C11: L. NEGRA | D11: 950 | H11: VACIO
A28: 46113 | B28: ADELA 6 | C28: L. NEGRA | D28: 1070 | H28: VACIO
A29: 46116 | B29: L. NEGRA | C29: CAMPANA | D29: 420 | G29: 36.91 | H29: 618977 | I29: CLINKER
A30: 46118 | B30: CAMPANA | C30: IBICUY | D30: 85 | H30: VACIO
A31: 46119 | B31: IBICUY | C31: BAJO DEL TORO | D31: 1560 | H31: 119681 | I31: YPF TORO
A32: 46122 | B32: BAJO DEL TORO | C32: L. NEGRA | D32: 1070 | H32: VACIO
A33: 46123 | B33: L. NEGRA | C33: ZAPALA | D33: 1010 | G33: 36.36 | H33: 619511 | I33: CLINKER
A34: 46126 | B34: ZAPALA | C34: ALLEN | D34: 240 | H34: VACIO
A35: 46126 | B35: ALLEN | C35: L. NEGRA | D35: 820 | G35: 34.7 | H35: 189472 | I35: YESO LOMA | K35: 949499.51
A36: 46128 | B36: L. NEGRA | C36: ZAPALA | D36: 1010 | G36: 36.51 | H36: 619789 | I36: CLINKER
A37: 46129 | B37: ZAPALA | C37: L. NEGRA | D37: 1060 | H37: 16418 | I37: TANDILIA
A38: 46135 | B38: L. NEGRA | C38: CAMPANA | D38: 430 | H38: 292… | I38: PIEDRA
A39: 46136 | B39: CAMPANA | C39: IBICUY | D39: 85 | H39: VACIO
A40: 46136 | B40: IBICUY | C40: BAJO DEL TORO | D40: 1560 | H40: 122785 | I40: YPF TORO
A41: 46139 | B41: BAJO DEL TORO | C41: ALLEN | D41: 270 | H41: VACIO
A42: 46140 | B42: ALLEN | C42: L. NEGRA | D42: 820 | G42: 36.1 | H42: 189990 | I42: YESO LOMA
A43: 46142 | B43: L. NEGRA | C43: C. FEDERAL | D43: 390 | G43: 35.84 | H43: 294831 | I43: PIEDRA
A44: 46142 | B44: C. FEDERAL | C44: IBICUY | D44: 170 | H44: VACIO
D45: 30 A LAS 22
D47: =SUM(D3:D46) -> 18285 | F47: =AVERAGE(#REF!) -> #REF! | G47: =AVERAGE(G3:G45) -> 36.07 | J47: =SUM(J3:J46) -> 0 | K47: =SUM(K3:K46) -> 949499.51 | L47: =K47/D47 -> 51.927783
B49: -1968.2
B50: 630 | C50: PEAJES | K50: 267km
B51: -700 | C51: ADELANTO
B52: 630 | C52: PEAJES
B53: -600 | C53: ADELANTO
B54: 1110 | C54: PEAJES
B55: -1200 | C55: ADELANTO
B56: 680 | C56: PEAJES | D56: 44131
B57: -600 | C57: ADELANTO
B58: 400 | C58: PEAJES
B59: -400 | C59: ADELANTO
B60: 2855 | C60: PEAJES | D60: 44182
B61: -2900 | C61: ADELANTO
B62: 315 | C62: PEAJES | D62: 44195
B63: -300 | C63: ADELANTO
B64: 1990 | C64: PEAJES | D64: 44216
B65: -2000 | C65: ADELANTO | D65: 44216
B66: 950 | C66: PEAJES | D66: 44226
B67: 450 | C67: GOMERIA
B68: -1400 | C68: ADELANTO
B69: 1700 | C69: LAVADO | D69: 44316
B70: 1290 | C70: PEAJES | D70: 44321
B71: -3000 | C71: ADELANTO
B72: 1250 | C72: peajes | D72: 44369
B73: -1200 | C73: ADELANTO | D73: 44369
B74: 200 | C74: PEAJES | D74: 44434
B75: -200 | C75: ADELANTO | D75: 44434
B76: 300 | C76: BALANZA | D76: 44457
B77: -300 | C77: ADELANTO
B78: 220 | C78: peajes | D78: 44543
B79: -300 | C79: ADELANTO | D79: 44543
B80: 1170 | C80: PEAJES Y BALANZA | D80: 44574
B81: -1100 | C81: ADELANTO
B82: 420 | C82: BALANZA | D82: 44576
B83: -400 | C83: ADELANTO
B84: 3250 | C84: PEAJES
B85: -3300 | C85: ADELANTO | D85: 44600
B86: 420 | C86: BALANZA
B87: -400 | C87: delanto | D87: 44611
B88: 1260 | C88: peaje | D88: 44628
B89: -1300 | C89: ADELANTO | D89: 44628
B90: 1160 | C90: PEAJES
B91: -1100 | C91: ADELANTO
B92: 880 | C92: PEAJES | D92: 44671
B93: -900 | C93: ADELANTO
B94: 680 | C94: PEAJES | D94: 44679
B95: -700 | C95: ADELANTO | D95: 44679
B96: 4110 | C96: peajes | D96: 44690
B97: -4100 | C97: ADELANTO | D97: 44690
B98: 880 | C98: PEAJES | D98: 44693
B99: -900 | C99: ADELANTO
B100: 960 | C100: PEAJES | D100: 44727
B101: -1000 | C101: ADELANTO | D101: 44727
B102: -980 | C102: ANTEC PENAL | D102: 44735
B103: 920 | C103: PEAJES | D103: 44775
B104: -900 | C104: ADELANTO | D104: 44775
B105: 480 | C105: peajes | D105: 44783
B106: -500 | C106: ADELANTO | D106: 44783
B107: 480 | C107: PEAJES | D107: 44793
B108: 5010 | C108: PEAJES | D108: 44827
B109: -5000 | C109: ADELANTO | D109: 44827
B110: -20000 | C110: ADELANTO | D110: 44835 | E110: PABLO | F110: NO ESTABA ANOTADO
B111: =12320+6884.34+13047.19 -> 32251.53 | C111: GAS | D111: 44841 | E111: PABLO
B112: -12300 | C112: PAGO GAS | D112: 44841 | E112: PABLO
B113: -30000 | C113: ADELANTO | D113: 44841 | E113: PABLO
B114: 9940 | C114: GAS | D114: 44847
B115: -9950 | C115: ADELANTO | D115: 44847
B116: 92739.82 | C116: COMBUSTIBLE | D116: 44858
B117: -70000 | C117: ADELANTO | D117: 44858
B118: 1200 | C118: peajes | D118: 45094
B119: -1200 | C119: adelanto | D119: 45094
...

Sheet PUCHETA
D1: LSN 102
A2: DIA | B2: SALE DE | C2: LLEGA A | D2: KM REC | E2: TN COM 29 | F2: TN ESC 35 | G2: TN ESC 37,5 | H2: REMITO Nº | I2: MATERIAL | J2: KM VACIOS | K2: $
A3: 46142 | B3: L. NEGRA | C3: CAMPANA | D3: 420 | F3: 34.46 | H3: 620612 | I3: CLINKER
A4: 46144 | B4: CAMPANA | C4: IBICUY | D4: 85 | H4: VACIO
A5: 46144 | B5: IBICUY | C5: BAJO DEL TORO | D5: 1560 | H5: 124501 | I5: YPF TORO
A6: 46148 | B6: BAJO DEL TORO | C6: ALLEN | D6: 270 | H6: VACIO
A7: 46150 | B7: ALLEN | C7: L. NEGRA | D7: 820 | F7: 34.7 | H7: 190217 | I7: YESO LOMA
A8: 46153 | B8: L. NEGRA | C8: ZAPALA | D8: 1010 | H8: 621266 | I8: CLINKER
A9: 46154 | B9: ZAPALA | C9: ALLEN | D9: 240 | H9: VACIO
A10: 46155 | B10: ALLEN | C10: L. NEGRA | D10: 820 | F10: 34.8 | H10: 190447 | I10: YESO LOMA
A11: 46157 | B11: L. NEGRA | C11: CAMPANA | D11: 420 | F11: 34.79 | H11: 621578 | I11: CLINKER
A12: 46157 | B12: CAMPANA | C12: IBICUY | D12: 85 | H12: VACIO
A26: 46112 | B26: IBICUY | C26: ADELA 6 | D26: 1450 | H26: 118504 | I26: ADELA YPF
A27: 46114 | B27: ADELA 6 | C27: L. NEGRA | D27: 1070 | H27: VACIO
A28: 46119 | B28: L. NEGRA | C28: CAMPANA | D28: 420 | F28: 35.12 | H28: 619142 | I28: CLINKER
A29: 46120 | B29: CAMPANA | C29: IBICUY | D29: 85 | H29: VACIO
A30: 46120 | B30: IBICUY | C30: BAJO DEL TORO | D30: 1560 | H30: 119914 | I30: YPF TORO
A31: 46123 | B31: BAJO DEL TORO | C31: L. NEGRA | D31: 1070 | H31: VACIO
A32: 46126 | B32: L. NEGRA | C32: RIO CUARTO | D32: 730 | H32: 766240
A33: 46127 | B33: RIO CUARTO | C33: PAMPAYASTA | D33: 140 | H33: VACIO
A34: 46127 | B34: PAMPAYASTA | C34: ROSARIO | D34: 340 | F34: 36.1 | H34: TKT 21557
A35: 46128 | B35: ROSARIO | C35: RAMALLO | D35: 80 | H35: VACIO
A36: 46128 | B36: RAMALLO | C36: L. NEGRA | D36: 500 | F36: 35.59 | H36: 1065369 | I36: LODO
A37: 46129 | B37: L. NEGRA | C37: ZAPALA | D37: 1010 | F37: 35.21 | H37: 619896 | I37: CLINKER
A38: 46132 | B38: ZAPALA | C38: ALLEN | D38: 240 | H38: VACIO
A39: 46133 | B39: ALLEN | C39: L. NEGRA | D39: 820 | F39: 34 | H39: 189785 | I39: YESO LOMA
A40: 46135 | B40: L. NEGRA | C40: ZAPALA | D40: 1010 | F40: 34.5 | H40: 620187 | I40: CLINKER
A41: 46136 | B41: ZAPALA | C41: ALLEN | D41: 240 | H41: VACIO
A42: 46136 | B42: ALLEN | C42: L. NEGRA | D42: 820 | F42: 34.2 | H42: 189919 | I42: YESO LOMA
A43: 46139 | B43: L. NEGRA | C43: TORCUATO | D43: 400 | F43: 34.74 | H43: 294655 | I43: PIEDRA
A44: 46140 | B44: TORCUATO | C44: LOMASER | D44: 140 | H44: VACIO
A45: 46140 | B45: LOMASER | C45: RAMALLO | D45: 300 | H45: 5302 | I45: PALLET
A46: 46141 | B46: RAMALLO | C46: L. NEGRA | D46: 500 | F46: 35.55 | H46: 1067730 | I46: ESCORIA
D47: 30 A LAS 11
D49: =SUM(D3:D48) -> 18655 | F49: =AVERAGE(F3:F47) -> 34.904615 | J49: =SUM(J3:J48) -> 0 | K49: =SUM(K3:K48) -> 0
B51: -2222.5
B52: 200 | C52: PEAJES
B53: 2800 | C53: PEAJES
B54: -2800 | C54: ADELANTO | D54: 44055
B55: 200 | C55: PEAJES
B56: 130 | C56: PEAJES | D56: 44179
B57: -400 | C57: ADELANTO | D57: 44179
B58: 300 | C58: BALANZASP
B59: -300 | C59: ADELANTO
B60: 300 | C60: PEAJES
B61: -300 | C61: adelanto
B62: 130 | C62: PEAJES | D62: 44282
B63: 300 | C63: BALANZA | D63: 44285
B64: -400 | C64: ADELANTO
B65: 400 | C65: peajes | D65: 44299
B66: 500 | C66: gomeria | D66: 44299
B67: -900 | C67: ADELANTO | D67: 44299
B68: 200 | C68: PEAJES | D68: 44361
B69: -200 | C69: ADELANTO | D69: 44361
B70: 620 | C70: PEAJES | D70: 44455
B71: -600 | C71: ADELANTO | D71: 44455
B72: 840 | C72: REPUESTO
B73: -840 | C73: ADELANTO
B74: 1560 | C74: peajes gomeria
B75: -1600 | C75: ADELANTO | D75: 44699
B76: 480 | C76: peajes | D76: 44767
B77: -500 | C77: ADELANTO | D77: 44767
B78: -300 | C78: ANT. PENALES | D78: 44774
B79: 1000 | C79: Balanza | D79: 44775
B80: -1000
B81: 840 | C81: peajes | D81: 44783
B82: -500 | C82: ADELANTO | D82: 44783
B83: 280 | C83: peajes | D83: 44790
B84: -300 | C84: ADELANTO | D84: 44790
B85: 480 | C85: PEAJES | D85: 44814
B86: -400 | C86: ADELANTO
B87: 480 | C87: PEAJES | D87: 44828
B88: -500 | C88: ADELANTO
B89: 480 | C89: PEAJES
B90: -400 | C90: ADELANTO
B91: 480 | C91: PEAJES
B92: -500 | C92: ADELANTO
B93: 800 | C93: PEAJES
B94: -800 | C94: ADELANTO | D94: 44877
B95: 2000 | C95: PEAJES | D95: 44884
B96: -2000 | C96: ADELANTO
B97: 800 | C97: PEAJES | D97: 44925
B98: -900 | C98: ADELANTO
B99: 800 | C99: PEAJES | D99: 44940
B100: -800 | C100: ADELANTO
B101: 400 | C101: PEAJES | D101: 44951
B102: -400 | C102: ADELANTO
B103: 800 | C103: peaje | D103: 45002
B104: -800 | C104: ADELANTO | D104: 45002
B105: 800 | C105: PEAJES | D105: 45044
B106: -800 | C106: ADELANTO | D106: 45044
B107: 800 | C107: PEAJES | D107: 45052
B108: -800 | C108: ADELANTO | D108: 45052
B109: 1200 | C109: PEAJES | D109: 45086
B110: -1200 | C110: ADELANTO
B111: 6000 | C111: gomeria | D111: 45428
B112: -14000 | C112: ADELANTO | D112: 45428
B113: -1000 | C113: ANT. PENALES | D113: 45504
B114: -1000 | C114: ANT. PENALES | D114: 45842
B116: =SUM(B51:B114) -> -12062.5 | C116: 45842 | XFD116: =SUM(A116:XFC116) -> 33779.5

Sheet CALIGIURI
D1: AE 601 GF
A2: DIA | B2: SALE DE | C2: LLEGA A | D2: KM REC | E2: TN COM 29 | F2: TN ESC 35 | G2: TN ESC 37,5 | H2: REMITO Nº | I2: MATERIAL | J2: KM VACIOS | K2: $
A30: 46112 | B30: ALLEN | C30: L. NEGRA | D30: 820 | G30: 35.8 | H30: 189341 | I30: YESO LOMA
A31: 46118 | B31: L. NEGRA | C31: CAMPANA | D31: 420 | G31: 36.19 | H31: 619080 | I31: CLINKER
A32: 46119 | B32: CAMPANA | C32: SIDERAR | D32: 150 | H32: VACIO
A33: 46119 | B33: SIDERAR | C33: RAMALLO | D33: 10 | H33: 1063787 | I33: CORTO
A34: 46119 | B34: RAMALLO | C34: SIDERAR | D34: 10 | H34: VACIO
A35: 46119 | B35: SIDERAR | C35: RAMALLO | D35: 10 | H35: 1063710 | I35: CORTO
A36: 46119 | B36: RAMALLO | C36: L. NEGRA | D36: 500 | H36: 1063826 | I36: ESCORIA
A37: 46120 | B37: L. NEGRA | C37: M. DEL PLATA | D37: 320 | H37: 765296 | K37: 907612.2
A38: 46121 | B38: M. DEL PLATA | C38: BARKER | D38: 230 | H38: VACIO
A39: 46122 | B39: BARKER | C39: L. NEGRA | D39: 200 | H39: 182570 | I39: M. ROJO
A40: 46139 | B40: L. NEGRA | C40: CAMPANA | D40: 430 | G40: 35.34 | H40: 294654 | I40: PIEDRA
A41: 46140 | B41: CAMPANA | C41: SIDERCA | D41: 10 | H41: VACIO
A42: 46140 | B42: SIDERCA | C42: CATAMARCA | D42: 990 | G42: 35.9 | H42: 153462 | I42: SIDERCA
A43: 46141 | B43: CATAMARCA | C43: CORDOBA | D43: 380 | H43: 504954
A44: 46141 | B44: CORDOBA | C44: SAN AGUSTIN | D44: 150 | H44: VACIO
A45: 46141 | B45: SAN AGUSTIN | C45: ROSARIO | D45: 450 | H45: PIEDRA | I45: LA ELENA
A46: 46142 | B46: ROSARIO | C46: IBICUY | D46: 300 | H46: VACIO
D47: 30 A LAS 20
J48: =SUM(J3:J47) -> 0
D49: =SUM(D3:D48) -> 5380 | G49: =AVERAGE(G3:G47) -> 35.8075 | K49: =SUM(K3:K48) -> 907612.2
B51: -2064.02
B52: 600 | C52: PEAJES
B53: -600 | C53: ADELANTO
B54: 795 | C54: PEAJES
B55: -800 | C55: ADELANTO
B56: 400 | C56: PEAJES
B57: -400 | C57: ADELANTO
B58: 795 | C58: PEAJES
B59: -800 | C59: ADELANTO
B60: 200 | C60: PEAJES
B61: -200 | C61: ADELANTO
B62: 760 | C62: PEAJES | D62: 44123
B63: -700 | C63: ADELANTO | D63: 44123
B64: 310 | C64: peajes | D64: 44125
B65: -300 | C65: ADELANTO | D65: 44125
B66: 200 | C66: PEAJES
B67: -200 | C67: ADELANTO
B68: 200 | C68: PEAJES | D68: 44139
B69: 930 | C69: PEAJES
B70: -1200 | C70: ADELANTO
B71: 680 | C71: PEAJES
B72: -700 | C72: ADELANTO | D72: 44166
B73: 695 | C73: PEAJES | D73: 44182
B74: -700 | C74: ADELANTO
B75: 200 | C75: PEAJES
B76: -200 | C76: ADELANTO
B77: 500 | C77: PEAJES
B78: -500 | C78: ADELANTO
B79: 500 | C79: PEAJES | D79: 44214
B80: -500 | C80: ADELANTO
B81: 500 | C81: peajes | D81: 44219
B82: -500 | C82: ADELANTO
B83: 500 | C83: PEAJES
B84: -500 | C84: ADELANTO
B85: 300 | C85: PESADA
B86: 200 | C86: PEAJES
B87: -500
B88: 500 | C88: PEAJES | D88: 44257
B89: -500 | C89: adelanto | D89: 44257
B90: 200 | C90: PEAJES | D90: 44285
B91: -200 | C91: ADELANTO
B92: 300 | C92: BALANZA | D92: 44295
B93: -300 | C93: ADELANTO
B94: 1200 | C94: peajes | D94: 44307
B95: -1200 | C95: ADELANTO | D95: 44307
B96: 200 | C96: PEAJES | D96: 44312
B97: -200 | C97: ADELANTO | D97: 44312
B98: 915 | C98: PEAJES | D98: 44320
B99: -900 | C99: ADELANTO
B100: 200 | C100: PEAJES | D100: 44327
B101: -200 | C101: ADELANTO | D101: 44327
B102: 200 | C102: PEAJES | D102: 44333
B103: -200 | C103: ADELANTO | D103: 44333
B104: 200 | C104: PEAJES | D104: 44338
B105: -200 | C105: ADELANTO | D105: 44338
B106: 200 | C106: PEAJES | D106: 44354
B107: -200 | C107: ADELANTO | D107: 44354
B108: 400 | C108: PEAJES | D108: 44364
B109: -400 | C109: ADELANTO | D109: 44364
B110: 500 | C110: PEAJES | D110: 44369
B111: -500 | C111: ADELANTO | D111: 44369
B112: 390 | C112: PEAJES | D112: 44386
B113: -400 | C113: ADELANTO
B114: 1860 | C114: PEAJES | D114: 44396
B115: -1800 | C115: ADELANTO
B116: 820 | C116: PEAJES
B117: -800 | C117: ADELANTO | D117: 44404
B118: 800 | C118: PEAJES | D118: 44419
B119: -800 | C119: ADELANTO | D119: 44419
B120: 620 | C120: PEAJES | D120: 44428
B121: -600 | C121: ADELANTO | D121: 44428
B122: 200 | C122: PEAJES
B123: 220 | C123: PEAJES | D123: 44453
B124: -500 | C124: ADELANTO | D124: 44453
B125: 220 | C125: PEAJES | D125: 44460
B126: 220 | C126: PEAJES | D126: 44467
B127: -400 | C127: ADELANTO | D127: 44467
B128: 220 | C128: PEAJES | D128: 44478
...

Sheet ASTEAZARAN
C1: AA244ZI
A2: DIA | B2: SALE DE | C2: LLEGA A | D2: KM REC | E2: TN COM 29 | F2: TN ESC 35 | G2: TN ESC 37,5 | H2: REMITO Nº | I2: MATERIAL | J2: KM VACIOS | K2: $
A3: 46142 | B3: L. NEGRA | C3: CAMPANA | D3: 430 | F3: 34.46 | H3: 620612 | I3: PIEDRA
A4: 46114 | B4: CAMPANA | C4: IBICUY | D4: 100 | H4: VACIO
A25: 46112 | B25: IBICUY | C25: ADELA 6 | D25: 1490 | H25: 118338 | I25: ADELA YPF
A26: 46114 | B26: ADELA 6 | C26: L. NEGRA | D26: 970 | H26: VACIO
A27: 46118 | B27: L. NEGRA | C27: CAMPANA | D27: 420 | F27: 34.84 | H27: 619082 | I27: CLINKER
A28: 46119 | B28: CAMPANA | C28: SIDERAR | D28: 150 | H28: VACIO
A29: 46119 | B29: SIDERAR | C29: RAMALLO | D29: 10 | H29: 1063714 | I29: CORTO
A30: 46119 | B30: RAMALLO | C30: SIDERAR | D30: 10 | H30: VACIO
A31: 46119 | B31: SIDERAR | C31: RAMALLO | D31: 10 | H31: 1063788 | I31: CORTO
A32: 46119 | B32: RAMALLO | C32: L. NEGRA | D32: 500 | F32: 33.91 | H32: 1063821 | I32: ESCORIA
A33: 46121 | B33: L. NEGRA | C33: VICTORIA | D33: 430 | H33: 293566 | I33: PIEDRA
A34: 46122 | B34: VICTORIA | C34: IBICUY | D34: 150 | H34: VACIO
A35: 46122 | B35: IBICUY | C35: BAJO DEL TORO | D35: 1560 | H35: 120342 | I35: YPF TORO
A36: 46125 | B36: BAJO DEL TORO | C36: ALLEN | D36: 270 | H36: VACIO
A37: 46126 | B37: ALLEN | C37: L. NEGRA | D37: 820 | F37: 35 | H37: 189439 | I37: YESO LOMA
A38: 46127 | B38: L. NEGRA | C38: CAMPANA | D38: 420 | F38: 34.59 | H38: 619722 | I38: CLINKER
A39: 46128 | B39: CAMPANA | C39: RAMALLO | D39: 150 | H39: VACIO
A40: 46128 | B40: RAMALLO | C40: L. NEGRA | D40: 500 | F40: 35.27 | H40: 1065460 | I40: ESCORIA
A41: 46129 | B41: L. NEGRA | C41: ZAPALA | D41: 1010 | F41: 34.53 | H41: 619899 | I41: CLINKER
A42: 46132 | B42: ZAPALA | C42: ALLEN | D42: 240 | H42: VACIO
A43: 46132 | B43: ALLEN | C43: ZAPALA | D43: 240 | F43: 33.8 | H43: 189748 | I43: CORTO YESO
A44: 46133 | B44: ZAPALA | C44: ALLEN | D44: 240 | H44: VACIO
A45: 46133 | B45: ALLEN | C45: L. NEGRA | D45: 820 | F45: 33.8 | H45: 189790 | I45: YESO LOMA
A46: 46135 | B46: L. NEGRA | C46: CAMPANA | D46: 430 | H46: 294373 | I46: PIEDRA
A47: 46136 | B47: CAMPANA | C47: IBICUY | D47: 100 | H47: VACIO
A48: 46136 | B48: IBICUY | C48: AÑELO | D48: 1430 | H48: 112803 | I48: YPF
A49: 46140 | B49: AÑELO | C49: ALLEN | D49: 180 | H49: VACIO
A50: 46140 | B50: ALLEN | C50: L. NEGRA | D50: 820 | F50: 34.3 | H50: 189998 | I50: YESO LOMA
A51: 46141 | B51: L. NEGRA | C51: TORCUATO | D51: 400 | H51: ????
A52: 46142 | B52: TORCUATO | C52: IBICUY | D52: 150 | H52: VACIO
D53: 30 A LAS 16
J54: =SUM(J3:J53) -> 0
D55: =SUM(D3:D54) -> 14450 | F55: =AVERAGE(F3:F53) -> 34.45 | K55: =SUM(K3:K53) -> 0
B57: -2015
B58: 1390 | C58: PEAJES | D58: 44069
B59: 600 | C59: LAVADO
B60: -2000 | C60: ADELANTO
B61: 630 | C61: PEAJES | D61: 44103
B62: -700 | C62: ADELANTO | D62: 44103
B63: 680 | C63: PEAJES | D63: 44179
B64: 2025 | C64: PEAJES | D64: 44216
B65: -2610 | C65: ADELANTO | D65: 44216
B66: 200 | C66: GOMERIA | D66: 44219
B67: -200 | C67: ADELANTO | D67: 44219
B68: 450 | C68: GOMERIA
B69: 300 | C69: PEAJES | D69: 44265
B70: -800 | C70: ADELANTO | D70: 44265
B71: 1000 | C71: ARREGLO GOMA | D71: 44301
B72: 300 | C72: PEAJES
B73: -1300 | C73: ADELANTO
B74: 1400 | C74: PEAJES | D74: 44302
B75: -1400 | C75: ADELANTO
B76: 300 | C76: PEAJES | D76: 44307
B77: -300 | C77: ADELANTO | D77: 44307
B78: 200 | C78: PEAJES | D78: 44366
B79: -200 | C79: ADELANTO | D79: 44366
B80: 340 | C80: PEAJES
B81: 600 | C81: LAVADO CAJA
B82: -900 | C82: ADELANTO | D82: 44415
B83: 300 | C83: peajes | D83: 44482
B84: -300 | C84: ADELANTO | D84: 44482
B85: 140 | C85: PEAJES | D85: 44511
B86: -200 | C86: PEAJES | D86: 44511
B87: 1400 | C87: GOMERIA | D87: 44533
B88: -1400 | C88: ADELANTO
B89: 1920 | C89: PEAJES | D89: 44649
B90: -1900 | C90: ADELANTO | D90: 44649
B91: 280 | C91: PEAJES | D91: 44725
B92: -300 | C92: ADELANTO | D92: 44725
B93: 280 | C93: PEAJES | D93: 44741
B94: 1000 | C94: Balanza Juarez | D94: 44751
B95: 480 | C95: Peajes | D95: 44751
B96: 360 | C96: PEAJES | D96: 44786
B97: -400 | C97: ADELANTO | D97: 44786
B98: 280 | C98: PEAJES | D98: 44798
B99: 880 | C99: PEAJES
B100: -900 | C100: ADELANTO
B101: 400 | C101: PEAJES | D101: 44881
B102: -500 | C102: ADELANTO | D102: 44881
B103: -1800 | C103: ADELANTO | D103: 44881
B104: 800 | C104: peajes | D104: 44884
B105: -800 | C105: adelanto
B106: 1600 | C106: peajes | D106: 44902
B107: -1600 | C107: ADELANTO | D107: 44902
B108: 800 | C108: PEAJES | D108: 44911
B109: -800 | C109: ADELANTO
B110: 800 | C110: PEAJES | D110: 44925
B111: -800 | C111: ADELANTO | D111: 44925
B112: 400 | C112: PEAJES | D112: 44931
B113: 800 | C113: PEAJES | D113: 44938
B114: -1300 | C114: ADELANTO | D114: 44938
B115: 800 | C115: PEAJES | D115: 44963
B116: 400 | C116: peajes | D116: 44964
B117: -1200 | C117: ADELANTO | D117: 44964
B118: 1200 | C118: peajes | D118: 45089
B119: -1200 | C119: adelanto | D119: 45089
B120: 1200 | C120: PEAJES | D120: 45093
B121: -330 | C121: ANTEC PENAL | D121: 45138
...

Sheet GARMENDIA
F1: PFN894
A2: DIA | B2: SALE DE | C2: LLEGA A | D2: KM REC | E2: TN COM 29 | F2: TN ESC 35 | G2: TN ESC 37,5 | H2: REMITO Nº | I2: MATERIAL | J2: KM VACIOS | K2: $
A26: 46111 | B26: L. NEGRA | C26: VICTORIA | D26: 430 | H26: 292957 | I26: PIEDRA
A27: 46113 | B27: VICTORIA | C27: IBICUY | D27: 150 | H27: VACIO
A28: 46114 | B28: IBICUY | C28: AÑELO | D28: 1430 | H28: 118786 | I28: YPF
A29: 46115 | B29: AÑELO | C29: L. NEGRA | D29: 1040 | H29: VACIO
A30: 46120 | B30: L. NEGRA | C30: BAHIA BLANCA | D30: 320
A31: 46121 | B31: BAHIA BLANCA | C31: L. NEGRA | D31: 320
A32: 46122 | B32: L. NEGRA | C32: S. FERNANDO | D32: 420 | F32: 35.02 | H32: 293676 | I32: FENOMIX
A33: 46125 | B33: S. FERNANDO | C33: IBICUY | D33: 150 | H33: VACIO
A34: 46125 | B34: IBICUY | C34: BAJO DEL TORO | D34: 1560 | H34: 120901 | I34: YPF TORO
A35: 46127 | B35: BAJO DEL TORO | C35: ALLEN | D35: 270 | H35: VACIO
A36: 46128 | B36: ALLEN | C36: L. NEGRA | D36: 820 | F36: 34.2 | H36: 189557 | I36: YESO LOMA
A37: 46129 | B37: L. NEGRA | C37: CASEROS | D37: 380 | H37: ???? | I37: TRAMONTANA
A38: 46132 | B38: CASEROS | C38: IBICUY | D38: 180 | H38: VACIO
A39: 46132 | B39: IBICUY | C39: BAJO DEL TORO | D39: 1560 | H39: 121979 | I39: YPF TORO
A40: 46135 | B40: BAJO DEL TORO | C40: ALLEN | D40: 270 | H40: VACIO
A41: 46136 | B41: ALLEN | C41: L. NEGRA | D41: 820 | F41: 34.1 | H41: 189878 | I41: YESO LOMA
A42: 46137 | B42: L. NEGRA | C42: SAN EFRNANDO | D42: 420 | H42: 294580
A43: 46139 | B43: SAN FERNANDO | C43: IBICUY | D43: 150 | H43: VACIO
A44: 46139 | B44: IBICUY | C44: AÑELO | D44: 1430 | H44: ???? | I44: YPF
D45: 30 A LAS 23
D47: =SUM(D3:D46) -> 12120 | F47: =AVERAGE(F3:F45) -> 34.44 | J47: =SUM(J3:J46) -> 0 | K47: =SUM(K3:K46) -> 0
B49: -2017
B50: 455 | C50: PEAJES
B51: -500 | C51: ADELANTO
B52: 140 | C52: PEAJES
B53: -200 | C53: ADELANTO
B54: 515 | C54: PEAJES
B55: -500 | C55: ADELANTO
B56: 280 | C56: PEAJES
B57: -200 | C57: ADELANTO
B58: 220 | C58: PEAJES | D58: 44149
B59: 200 | C59: PEAJES | D59: 44167
B60: -400 | C60: ADELANTO
B61: 220 | C61: PEAJES | D61: 44186
B62: -200 | C62: ADELANTO | D62: 44186
B63: 200 | C63: PEAJES | D63: 44188
B64: -200 | C64: ADELANTO | D64: 44188
B65: 465 | C65: PEAJES
B66: -500 | C66: ADELANTO
B67: 300 | C67: BALANZA SPEDRO | D67: 44203
B68: -300 | C68: ADELANTO | D68: 44203
B69: 300 | C69: BALANZA SPEDRO
B70: -300 | C70: ADELANTO
B71: 490 | C71: PEAJES
B72: -500 | C72: ADELANTO
B73: 490 | C73: PEAJES | D73: 44268
B74: -500 | C74: ADELANTO
B75: 300 | C75: PEAJES | D75: 44277
B76: -300 | C76: ADELANTO | D76: 44277
B77: 300 | C77: PEAJES | D77: 44282
B78: -300 | D78: 27/63
B79: 715 | C79: peajes | D79: 44310
B80: -700 | C80: ADELANTO | D80: 247/4
B81: 890 | C81: PEAJES | D81: 44315
B82: -900 | C82: ADELANTO
B83: 500 | C83: GOMERIA
B84: -500 | C84: ADELANTO
B85: 630 | C85: PEAJES | D85: 44343
B86: -600 | C86: ADELANTO
B87: 300 | C87: BALANZA SPEDRO | E87: 44567
B88: -300 | C88: ADELANTO
B89: 420 | C89: PEAJES
B90: -500 | C90: ADELANTO | D90: 44614
B91: 420 | C91: PEAJES | D91: 44623
B92: -400 | C92: ADELANTO | D92: 44623
B93: 680 | C93: PEAJES | D93: 44676
B94: -700 | C94: ADELANTO | D94: 44676
B95: 800 | C95: PEAJES | D95: 44695
B96: -800 | C96: ADELANTO | D96: 44695
B97: 5640 | C97: PEAJES | D97: 44700
B98: -5640 | C98: ADELANTO | D98: 44700
B99: -1500 | C99: ADELANTO | D99: 44700
B100: 2080 | C100: PEAJES | D100: 44707
B101: -2100 | C101: ADELANTO | D101: 44707
... B103: -4320 | C103: ADELANTO | D103: 44714
B104: 2960 | C104: PEAJES
B105: -2900 | C105: ADELANTO
B106: 960 | C106: PEAJES | D106: 44726
B107: -1000 | C107: ADELANTO | D107: 44726
B108: 2507.5 | C108: UREA | D108: 44749
B109: 300 | C109: PEAJES
B110: -1300 | C110: ADELANTO
B111: 480 | C111: PEAJES | D111: 44827
B112: -500 | C112: ADELANTO
B113: -300 | C113: ANT. PENALES | D113: 44832
B114: 480 | C114: PEAJES
B115: -480 | C115: ADELANTO
B116: 480 | C116: PEAJES | D116: 44849
B117: -400 | C117: ADELANTO | D117: 44849
B118: 800 | C118: peajes | D118: 44869
B119: -500 | C119: ADELANTO | D119: 44869
B120: 800 | C120: PEAJES | D120: 44875
B121: -800 | C121: ADELANTO
B122: 800 | C122: PEAJES | D122: 44881
B123: -800 | C123: ADELANTO | D123: 44881
B124: 800 | C124: PEAJES | D124: 44893
B125: -800 | C125: ADELANTO | D125: 44893
B126: 800 | C126: PEAJES | D126: 44897
...

Sheet SALTO
D1: AD242JZ
A2: DIA | B2: SALE DE | C2: LLEGA A | D2: KM REC | E2: TN COM 29 | F2: TN ESC 35 | G2: TN ESC 37,5 | H2: REMITO Nº | I2: MATERIAL | J2: KM VACIOS | K2: $
A26: 46111 | B26: DOCK SUD | C26: T. SUAREZ | D26: 70 | G26: TALLER | H26: VOLVO
A27: 46084 | B27: T. SUAREZ | C27: IBICUY | D27: 220 | H27: VACIO
A28: 46115 | B28: IBICUY | C28: BAJO DEL TORO | D28: 1560 | H28: 80746 | I28: YPF TORO
A29: 46119 | B29: BAJO DEL TORO | C29: L. NEGRA | D29: 1070 | H29: VACIO
A30: 46122 | B30: L. NEGRA | C30: SPEGAZZINI | D30: 350 | G30: 35.14 | H30: 293670 | I30: PIEDRA
A31: 46094 | B31: SPEGAZZINI | C31: LOMASER | D31: 20 | H31: VACIO
A32: 46125 | B32: LOMASER | C32: J. C. PAZ | D32: 120 | H32: 895883
A33: 46125 | B33: J. C. PAZ | C33: CAÑUELAS | D33: 120 | H33: VACIO
A34: 46125 | B34: CAÑUELAS | C34: RAMALLO | D34: 300 | H34: 5258 | I34: PALLETS | K34: 329603.71
A35: 46125 | B35: RAMALLO | C35: L. NEGRA | D35: 500 | H35: 1064909 | I35: LODO
A36: 46127 | B36: L. NEGRA | C36: ZAPALA | D36: 1010 | G36: 36.25 | H36: 619692 | I36: CLINKER
A37: 46128 | B37: ZAPALA | C37: ALLEN | D37: 240 | H37: VACIO
A38: 46128 | B38: ALLEN | C38: L. NEGRA | D38: 850 | G38: 33 | H38: 189632 | I38: YESO LOMA
A39: 46130 | B39: L. NEGRA | C39: ZAPALA | D39: 1010 | H39: 619973 | I39: CLINKER
A40: 46132 | B40: ZAPALA | C40: ALLEN | D40: 240 | H40: VACIO
A41: 46132 | B41: ALLEN | C41: L. NEGRA | D41: 850 | G41: 36 | H41: 189730 | I41: YESO LOMA
A42: 46134 | B42: L. NEGRA | C42: ZAPALA | D42: 1010 | G42: 36.64 | H42: 620156 | I42: CLINKER
A43: 46135 | B43: ZAPALA | C43: ALLEN | D43: 240 | H43: VACIO
A44: 46136 | B44: ALLEN | C44: L. NEGRA | D44: 850 | G44: 35.5 | H44: 189849 | I44: YESO LOMA
D45: 25 A LAS 8 | E45: LF
D47: =SUM(D3:D46) -> 10630 | G47: =AVERAGE(G3:G45) -> 35.421667 | J47: =SUM(J3:J46) -> 0 | K47: =SUM(K3:K46) -> 329603.71 | L47: =K47/D47 -> 31.006934
B49: -2106 | C49: ADELANTO
B50: 630 | C50: PEAJES
B51: -600 | C51: ADELANTO
B52: 630 | C52: PEAJES
B53: -600 | C53: ADELANTO | D53: 44111
B54: 1065 | C54: PEAJES Y GOMERIA
B55: -1100 | C55: ADELANTO | D55: 44118
B56: 600 | C56: EMPARCHE GOMERIA | D56: 44123
B57: 140 | C57: PEAJES
B58: -700 | C58: ADELANTO
B59: 800 | C59: ARREGLO DE LONA | D59: 44130
B60: -800 | C60: ADELANTO
B61: 220 | C61: PEAJES | D61: 44140
B62: 220 | C62: PEAJES | D62: 44148
B63: 800 | C63: gomeria | D63: 44161
B64: -1200 | C64: ADELANTO | D64: 44161
B65: 340 | C65: PEAJES
B66: -400 | C66: ADELANTO
B67: 315 | C67: PEAJES | D67: 44180
B68: -300 | C68: ADELANTO
B69: 490 | C69: PEAJES
B70: -500 | C70: ADELANTO
B71: 315 | C71: PEAJES | D71: 44203
B72: -300 | C72: ADELANTO | D72: 44203
B73: 1225 | C73: PEAJE | D73: 44214
B74: -1200 | C74: ADELANTO | D74: 44214
B75: 490 | C75: PEAJES | D75: 44216
B76: -500 | C76: ADELANTO
B77: 315 | C77: PEAJES | D77: 44216
B78: -300 | C78: ADELANTO
B79: 630 | C79: PEAJES | D79: 44222
B80: -600 | C80: ADELANTO | D80: 44222
B81: 300 | C81: PEAJE | D81: 44278
B82: -300 | C82: ADELANTO | D82: 44278
B83: 300 | C83: BALANZA
B84: -300 | C84: ADELANTO | D84: 44289
B85: 300 | C85: PEAJE | D85: 44294
B86: -400 | C86: ADELANTO | D86: 44294
B87: 315 | C87: PEAJES | D87: 44305
B88: -300 | C88: ADELANTO | D88: 44305
B89: 490 | C89: PEAJE | D89: 44320
B90: -500 | C90: ADELANTO | D90: 44320
B91: 420 | C91: BALANZA | D91: 44575
B92: -400 | C92: ADEALNTO
B93: 420 | C93: PEAJES | D93: 44635
B94: -400 | C94: ADELANTO | D94: 44635
B95: 880 | C95: PEAJES | D95: 44642
B96: -900 | C96: ADELANTO | D96: 44642
B97: 440 | C97: peajes | D97: 44686
B98: -400 | C98: adelanto
B99: 440 | C99: PEAJE | D99: 44699
B100: -500 | C100: ADELANTO
B101: 440 | C101: peajes | D101: 44744
B102: -400 | C102: adelanto | D102: 44744
B103: 400 | C103: PEAJES | D103: 44757
B104: -400 | C104: ADELANTO | D104: 44757
B105: 300 | C105: PEAJES | D105: 44786
B106: -300
B107: 300 | C107: PEAJES | D107: 44793
B108: -300 | C108: ADELANTO
B109: 480 | C109: PEAJES | D109: 44799
B110: -500 | C110: ADELANTO | D110: 44799
B111: 480 | C111: peakes
B112: -500 | C112: adelanto
B113: -300 | C113: ant. Penales | D113: 44826
B114: 1180 | C114: PEAJES | D114: 44828
B115: -1000 | C115: ADELANTO | D115: 44828
B116: 480 | C116: PEAJES | D116: 44834
B117: -500 | C117: ADELANTO | D117: 44834
B118: 800 | C118: peajes | D118: 44863
B119: -800 | C119: adelanto
B120: 800 | C120: peajes | D120: 44868
B121: -600 | C121: adelanto
B122: 800 | C122: PEAJES | D122: 44876
B123: -800 | C123: ADELANTO | D123: 44876
B124: 1600 | C124: PEAJES | D124: 44883
B125: 3000 | C125: GOMERIA
...

Sheet BAZAN
D1: JKQ716
A2: DIA | B2: SALE DE | C2: LLEGA A | D2: KM REC | E2: TN COM 29 | F2: TN ESC 35 | G2: TN ESC 37,5 | H2: REMITO Nº | I2: MATERIAL | J2: KM VACIOS | K2: $
A23: 46113 | B23: L. NEGRA | C23: CASEROS | D23: 380 | F23: 34.44 | H23: 293227 | I23: TRAMONTANA | K23: 619920
A24: 46118 | B24: CASEROS | C24: IBICUY | D24: 180 | H24: VACIO
A25: 46118 | B25: IBICUY | C25: AÑELO | D25: 1430 | H25: 119477 | I25: YPF
A26: 46121 | B26: AÑELO | C26: L. NEGRA | D26: 1000 | H26: VACIO
A27: 46123 | B27: L. NEGRA | C27: ZAPALA | D27: 1010 | F27: 33.91 | H27: 619460 | I27: CLINKER | K27: 2227070.5
A28: 46125 | B28: ZAPALA | C28: ALLEN | D28: 240 | H28: VACIO
A29: 46125 | B29: ALLEN | C29: L. NEGRA | D29: 820 | F29: 34.7 | H29: 189454 | I29: YESO LOMA | K29: 972132.93
A30: 46126 | B30: L. NEGRA | C30: CAMPANA | D30: 420 | F30: 34.25 | H30: 619657 | I30: CLINKER
A31: 46127 | B31: CAMPANA | C31: SIDERAR | D31: 150 | H31: VACIO
A32: 46127 | B32: SIDERAR | C32: L. NEGRA | D32: 500 | F32: 34.03 | H32: 1065172 | I32: ESCORIA
A33: 46129 | B33: L. NEGRA | C33: ZAPALA | D33: 1010 | F33: 34.26 | H33: 619847 | I33: CLINKER
A34: 46132 | B34: ZAPALA | C34: ALLEN | D34: 240 | H34: VACIO
A35: 46132 | B35: ALLEN | C35: ZAPALA | D35: 240 | F35: 33.6 | H35: 189745 | I35: YESO LOMA
A36: 46133 | B36: ZAPALA | C36: ALLEN | D36: 240 | H36: VACIO
A37: 46133 | B37: ALLEN | C37: L. NEGRA | D37: 820 | F37: 33.8 | H37: 189791 | I37: YESO LOMA
A38: 46135 | B38: L. NEGRA | C38: CAMPANA | D38: 430 | H38: ???? | I38: PIEDRA
A39: 46136 | B39: CAMPANA | C39: IBICUY | D39: 100 | H39: VACIO
A40: 46136 | B40: IBICUY | C40: BAJO DEL TORO | D40: 1470 | H40: 122776 | I40: YPF TORO 5
A41: 46141 | B41: BAJO DEL TORO | C41: L. NEGRA | D41: 1070 | H41: VACIO
D42: 30 A LAS 13
D44: =SUM(D3:D43) -> 11750 | F44: =AVERAGE(F3:F42) -> 34.12375 | J44: =SUM(J3:J43) -> 0 | K44: =SUM(K3:K43) -> 3819123.4
B46: -2130
B47: 200 | C47: PEAJES
B48: -200 | C48: ADELANTO
B49: 200 | C49: PEAJES
B50: -200 | C50: ADELANTO
B51: 215 | C51: PEAJES | D51: 44105 | I51: 10000
B52: -200 | C52: ADELANTO | I52: 7000
B53: 130 | C53: PEAJES | I53: 10000
B54: 200 | C54: PEAJES | I54: 10000
B55: -300 | C55: ADELANTO | I55: 10000
B56: 480 | C56: PEAJES | I56: 7000
B57: -400 | C57: ADELANTO | D57: 44123 | I57: 10000
B58: 1000 | C58: PARCHE GOMA | D58: 44127 | I58: 10000
B59: -1000 | C59: ADELANTO | I59: 7000
B60: 630 | C60: PEAJES | D60: 44127 | I60: 10000
B61: -700 | C61: ADELANTO | I61: 10000
B62: 400 | C62: PEAJES | D62: 44140 | I62: 10000
B63: 400 | C63: PEAJES | D63: 44140 | I63: 10000
B64: -800 | C64: ADELANTO | D64: 44144 | I64: 10000
B65: 960 | C65: PEAJES | D65: 44161
B66: 1500 | C66: AUXILIO EN RESISTENCIA
B67: -2500 | C67: ADELANTO
B68: 680 | C68: PEAJES | D68: 44165
B69: -600 | C69: ADELANTO | D69: 44165
B70: 480 | C70: PEAJES | D70: 44169
B71: -500 | C71: ADELANTO | D71: 44169 | I71: EL EMPORIO | J71: 1374657.7
B72: 200 | C72: PEAJES | D72: 44182 | I72: CABRERA | J72: 359963.1
B73: -200 | C73: ADELANTO | I73: LEMOS | J73: 45738
B74: 200 | C74: PEAJES | D74: 44188 | I74: RODAMIENTO | J74: 298125
B75: -200 | C75: ADELANTO | I75: PUBLICIDAD | J75: 100000
B76: 200 | C76: PEAJES | J76: =SUM(J71:J75) -> 2178483.8
B77: -200 | C77: ADELANTO
B78: 480 | C78: PEAJES
B79: -500 | C79: ADELANTO
B80: 480 | C80: PEAJES
B81: -500 | C81: ADELANTO
B82: 500 | C82: GOMERIA
B83: -500 | C83: ADELANTO | D83: 44217
B84: 1200 | C84: PEAJES
B85: -1200 | C85: ADELANTO | D85: 44223
B86: 200 | C86: PEAJES | D86: 44230
B87: -200 | C87: ADELANTO
B88: 200 | C88: PEAJES | D88: 44238
B89: 200 | C89: PEAJES | D89: 44252
B90: -200 | C90: ADELANTO | D90: 44252
B91: 3300 | C91: ARREGLO GOMAS | D91: 44258
B92: 800 | C92: PEAJES
B93: -4200 | C93: ADELANTO | XFD93: =SUM(A93:XFC93) -> -4200
B94: 600 | C94: PEAJES
B95: -700 | C95: ADELANTO
B96: 600 | C96: PEAJES | D96: 44279
B97: 300 | C97: BALANZA
B98: -900 | C98: ADELANTO
B99: 300 | C99: PEAJES | D99: 44282
B100: 200 | C100: PEAJES | D100: 44295
B101: 800 | C101: ARREGLO GOMAS
B102: -1300 | C102: ADELANTO
B103: 200 | C103: PEAJES | D103: 44299
B104: -200 | C104: ADELANTO
B105: 800 | C105: PEAJES | D105: 44313
B106: -800 | C106: ADELANTO
B107: 1200 | C107: PEAJES | D107: 44316
B108: -1200 | C108: ADELANTO | D108: 44316
B109: 400 | C109: PEAJES | D109: 44320
B110: -400 | C110: ADELANTO
B111: 600 | C111: PEAJES
B112: -600 | C112: ADELANTO | D112: 44330
B113: 300 | C113: PEAJES
B114: -300 | C114: ADELANTO | D114: 44370
B115: 1000 | C115: PEAJES | D115: 44378
B116: -1000 | C116: ADELANTO | D116: 44378
B117: 220 | C117: PEAJES | D117: 44383
B118: -300 | C118: ADELANTO
B119: 840 | C119: PEAJES | D119: 44396
B120: -700 | C120: ADELANTO | D120: 44396
B121: 280 | C121: PEAJES | D121: 44401
B122: -300 | C122: ADELANTO
...

Sheet BORDIGNON
D1: AB742XZ
A2: DIA | B2: SALE DE | C2: LLEGA A | D2: KM REC | E2: TN COM 29 | F2: TN ESC 35 | G2: TN ESC 37,5 | H2: REMITO Nº | I2: MATERIAL | J2: KM VACIOS | K2: $
A29: 46112 | B29: L. NEGRA | C29: RAMALLO | D29: 500 | H29: 618865
A30: 46113 | B30: RAMALLO | C30: SIDERAR | D30: 10 | H30: VACIO
A31: 46113 | B31: SIDERAR | C31: RAMALLO | D31: 10 | H31: 1062968 | I31: CORTO
A32: 46113 | B32: RAMALLO | C32: L. NEGRA | D32: 500 | F32: 34.45 | H32: 1063032 | I32: ESCORIA
A33: 46118 | B33: L. NEGRA | C33: M. DEL PLATA | D33: 320 | H33: 764963 | K33: 857189.3
A34: 46119 | B34: M. DEL PLATA | C34: L. NEGRA | D34: 320 | H34: VACIO
A35: 46120 | B35: L. NEGRA | C35: BARKER | D35: 180 | H35: 765168
A36: 46120 | B36: BARKER | C36: L. NEGRA | D36: 220 | H36: 33294 | I36: ARCAMIN
A37: 46120 | B37: L. NEGRA | C37: JUNIN | D37: 325 | H37: 619282 | K37: 1017282.2
A38: 46121 | B38: JUNIN | C38: L. NEGRA | D38: 325 | H38: VACIO
A39: 46121 | B39: L. NEGRA | C39: BARKER | D39: 180 | H39: 765468
A40: 46122 | B40: BARKER | C40: L. NEGRA | D40: 200 | H40: 182565 | I40: M. ROJO
A41: 46123 | B41: L. NEGRA | C41: ZAPALA | D41: 1010 | F41: 35.21 | H41: 619507 | I41: CLINKER | K41: 2312449.1
A42: 46125 | B42: ZAPALA | C42: ALLEN | D42: 240 | H42: VACIO
A43: 46125 | B43: ALLEN | C43: L. NEGRA | D43: 820 | F43: 35 | H43: 189456 | I43: YESO LOMA | K43: 970476.83
A44: 46126 | B44: L. NEGRA | C44: CAMPANA | D44: 430 | H44: 293868 | I44: PIEDRA
A45: 46127 | B45: CAMPANA | C45: SIDERCA | D45: 10 | H45: VACIO
A46: 46127 | B46: SIDERCA | C46: CATAMARCA | D46: 990 | F46: 34.44 | H46: 153207 | I46: SIDERCA
A47: 46128 | B47: CATAMARCA | C47: ALTA GRACIA | D47: 430 | H47: 504060
A48: 46129 | B48: ALTA GRACIA | C48: PAMPAYASTA | D48: 150 | H48: VACIO
A49: 46130 | B49: PAMPAYASTA | C49: ROSARIO | D49: 370 | F49: 35.7 | H49: TKT 21648
A50: 46130 | B50: ROSARIO | C50: RAMALLO | D50: 80 | H50: VACIO
A51: 46130 | B51: RAMALLO | C51: L. NEGRA | D51: 500 | F51: 34.67 | H51: 1065812 | I51: LODO
A52: 46134 | B52: L. NEGRA | C52: CAMPANA | D52: 430 | F52: 34.68 | H52: 294340 | I52: PIEDRA
A53: 46135 | B53: CAMPANA | C53: IBICUY | D53: 100 | H53: VACIO
A54: 46136 | B54: IBICUY | C54: BAJO DEL TORO | D54: 1560 | H54: 122669 | I54: YPF TORO
A55: 46138 | B55: BAJO DEL TORO | C55: ALLEN | D55: 270 | H55: VACIO
A56: 46139 | B56: ALLEN | C56: L. NEGRA | D56: 820 | F56: 34.2 | H56: 189965 | I56: YESO LOMA
A57: 46140 | B57: L. NEGRA | C57: CHACABUCO | D57: 360 | H57: 620478
A58: 46141 | B58: CHACABUCO | C58: RAMALLO | D58: 180 | H58: VACIO
A59: 46141 | B59: RAMALLO | C59: L. NEGRA | D59: 500 | F59: 34.86 | H59: 1067745 | I59: ESCORIA
D60: 30 A LAS 11
D62: =SUM(D3:D61) -> 12340 | F62: =AVERAGE(F3:F60) -> 34.801111 | J62: =SUM(J3:J61) -> 0 | K62: =SUM(K3:K61) -> 5157397.4
B64: -2020
B65: 520 | C65: PEAJES | D65: 44098
B66: -500 | C66: ADELANTO | D66: 44098
B67: 480 | C67: PEAJES
B68: -500 | C68: ADELANTO
B69: 200 | C69: PEAJES | D69: 44109
B70: -200 | C70: ADELANTO | D70: 44109
B71: 260 | C71: PEAJES | D71: 44114
B72: -300 | C72: ADELANTO
B73: 480 | C73: PEAJES | D73: 44123
B74: -500 | C74: ADELANTO | D74: 44123
B75: 400 | C75: PEAJES | D75: 44132
B76: -400 | C76: ADELANTO
B77: 200 | C77: PEAJES | D77: 44139
B78: 680 | C78: PEAJES
B79: -700 | C79: ADELANTO
B80: 200 | C80: PEAJES
B81: -300 | C81: ADELANTO
B82: 200 | C82: PEAJES | D82: 44166
B83: -200 | C83: ADELANTO | D83: 44166
B84: 960 | C84: PEAJES | D84: 44179
B85: -1000 | C85: ADELANTO | D85: 44179
B86: 480 | C86: PEAJES | D86: 44182
B87: -500 | C87: ADELANTO
B88: 400 | C88: PEAJES | D88: 44191
B89: -400 | C89: ADELANTO
B90: 695 | C90: PEAJES
B91: -700 | C91: ADELANTO
B92: 200 | C92: PEAJES
B93: -200 | C93: ADELANTO
B94: 480 | C94: PEAJES
B95: -500 | C95: ADELANTO
B96: 200 | C96: PEAJES | D96: 44211
B97: -630 | C97: MULTA ESTACIONAMIENTO
B98: 200 | C98: PEAJES | D98: 44221
B99: 300 | C99: BALANZA
B100: 500 | C100: PEAJES
B101: -500 | C101: ADELANTO | D101: 44229
B102: 300 | C102: BALANZA | D102: 44235
B103: -300 | C103: ADELANTO
B104: 300 | C104: BALANZA | D104: 44240
B105: -300 | C105: PEAJES | D105: 44240
B106: 200 | C106: PEAJES | D106: 44257
B107: -200 | C107: ADELANTO
B108: 500 | C108: PEAJES
B109: -500 | C109: ADELANTO
B110: 200 | C110: PEAJES | D110: 44272
B111: -200 | C111: ADELANTO
B112: 300 | C112: BALANZA
B113: 200 | C113: PEAJES
B114: -500 | C114: ADELANTO
B115: 915 | C115: PEAJES | D115: 44320
B116: -900 | C116: ADELANTO
B117: 400 | C117: peajes | D117: 44333
B118: -400 | C118: adelanto | D118: 44333
B119: 200 | C119: PEAJES | D119: 44351
B120: 300 | C120: BALANZA
B121: -500 | C121: ADELANTO
B122: 200 | C122: PEAJES
B123: -200 | C123: ADELANTO
B124: 440 | C124: PEAJES
B125: 220 | C125: PEAJES | D125: 44387
B126: -700 | C126: ADELANTO
B127: 520 | C127: PEAJES | D127: 44394
B128: -500 | C128: ADELANTO
...

Sheet LAGANO D
D1: NYU 938
A2: DIA | B2: SALE DE | C2: LLEGA A | D2: KM REC | E2: TN COM 29 | F2: TN ESC 35 | G2: TN ESC 37,5 | H2: REMITO Nº | I2: MATERIAL | J2: KM VACIOS | K2: $
A29: 46112 | B29: SIDERAR | C29: L. NEGRA | D29: 500 | F29: 34.93 | H29: 1062780 | I29: ESCORIA
A30: 46118 | B30: L. NEGRA | C30: CAMPANA | D30: 420 | F30: 34.78 | H30: 619079 | I30: CLINKER
A31: 46119 | B31: CAMPANA | C31: SIDERAR | D31: 150 | H31: VACIO
A32: 46119 | B32: SIDERAR | C32: RAMALLO | D32: 10 | H32: 1063740 | I32: CORTO
A33: 46119 | B33: RAMALLO | C33: SIDERAR | D33: 10 | H33: VACIO
A34: 46119 | B34: SIDERAR | C34: RAMALLO | D34: 10 | H34: 1063806 | I34: CORTO
A35: 46119 | B35: RAMALLO | C35: SIDERAR | D35: 10 | H35: VACIO
A36: 46120 | B36: SIDERAR | C36: RAMALLO | D36: 10 | H36: 1063946 | I36: CORTO
A37: 46120 | B37: RAMALLO | C37: SIDERAR | D37: 10 | H37: VACIO
A38: 46120 | B38: SIDERAR | C38: RAMALLO | D38: 10 | H38: 1063984 | I38: CORTO
A39: 46120 | B39: RAMALLO | C39: SIDERAR | D39: 10 | H39: VACIO
A40: 46120 | B40: SIDERAR | C40: RAMALLO | D40: 10 | H40: 1064021 | I40: CORTO
A41: 46121 | B41: RAMALLO | C41: SIDERAR | D41: 10 | H41: VACIO
A42: 46121 | B42: SIDERAR | C42: RAMALLO | D42: 10 | H42: 1064167 | I42: CORTO
A43: 46121 | B43: RAMALLO | C43: ZAPALA | D43: 1470 | F43: 34.74 | H43: 1064266 | I43: LODO | K43: 2179217.6
A44: 46125 | B44: ZAPALA | C44: L. NEGRA | D44: 1060 | H44: 16405 | I44: TANDILIA | K44: 1528749.1
A45: 46127 | B45: L. NEGRA | C45: ZAPALA | D45: 1010 | F45: 34.85 | H45: 619688 | I45: CLINKER
A46: 46128 | B46: ZAPALA | C46: ALLEN | D46: 240 | H46: VACIO
A47: 46128 | B47: ALLEN | C47: L. NEGRA | D47: 820 | F47: 34 | H47: 189643 | I47: YESO LOMA
A48: 46134 | B48: L. NEGRA | C48: ZAPALA | D48: 1010 | F48: 34.78 | H48: 620092 | I48: CLINKER
A49: 46135 | B49: ZAPALA | C49: ALLEN | D49: 240 | H49: VACIO
A50: 46135 | B50: ALLEN | C50: L. NEGRA | D50: 820 | F50: 34.9 | H50: 189844 | I50: YESO LOMA
A51: 46137 | B51: L. NEGRA | C51: SAN EFRNANDO | D51: 420 | F51: 34.96 | H51: 294560 | I51: FENOMIX
A52: 46139 | B52: SAN FERNANDO | C52: IBICUY | D52: 150 | H52: VACIO
A53: 46139 | B53: IBICUY | C53: BAJO DEL TORO | D53: 1560 | H53: 123493 | I53: YPF TORO
D54: 30 A LAS 23
D56: =SUM(D3:D55) -> 9980 | F56: =AVERAGE(F3:F54) -> 34.7425 | J56: =SUM(J3:J55) -> 0 | K56: =SUM(K3:K55) -> 3707966.7
B58: -2000
B59: 315 | C59: peajes | D59: 44095
B60: -400 | C60: adelanto
B61: 160 | C61: peajes
B62: -200 | C62: ADELANTO
B63: 160 | C63: peajes
B64: 200 | C64: adelanto
B65: -200 | C65: adelanto
B66: 200 | C66: PEAJES | D66: 44137
B67: -300 | C67: adelanto | D67: 44151
B68: 515 | C68: peajes | D68: 44163
B69: -500 | C69: adelanto
B70: 1910 | C70: PEAJES | D70: 44168
B71: -1900 | C71: ADELANTO
B72: 315 | C72: PEAJES | D72: 44182
B73: -300 | C73: ADELAQNTO
B74: 1660 | C74: peajes
B75: -1700
B76: 1955 | C76: PEAJES
B77: -1900 | C77: ADELANTO
B78: 315 | C78: peajes
B79: -400 | C79: ADELANTO
B80: 300 | C80: peajes
B81: -300 | C81: ADELANTO
B82: 490 | C82: PEAJES | D82: 44223
B83: -400 | C83: ADELANTO | D83: 44223
B84: 600 | C84: BALANZA | D84: 44299
B85: 315 | C85: PEAJES
B86: -1000 | C86: ADELANTO
B87: 915 | C87: peajes | D87: 44307
B88: -900 | C88: ADELANTO | D88: 44307
B89: 600 | C89: peajes | D89: 44310
B90: -600 | C90: ADELANTO | D90: 44310
B91: 915 | C91: peajes | D91: 44319
B92: -900 | C92: adelanto | D92: 44319
B93: 500 | C93: PEAJES | D93: 44356
B94: 1000 | C94: GOMERIA | D94: 44356
B95: -1500 | C95: ADELANTO | D95: 44356
B96: 600 | C96: peajes | D96: 44378
B97: -600 | C97: adelanto | D97: 44378
B98: 220 | C98: peajes
B99: -500 | C99: ADELANTO | D99: 44387
B100: 620 | C100: PEAJES | D100: 44421
B101: -600 | C101: ADELANTO | D101: 44421
B102: 300 | C102: peajes | D102: 44434
B103: 1900 | C103: peajes | D103: 44504
B104: -1900 | C104: adelanto
B105: 1900 | C105: peajes
B106: -1900 | C106: ADELANTO | D106: 44529
B107: -400 | C107: ANTEC PENAL | D107: 44531
B108: 520 | C108: PEAJES | D108: 44534
B109: 300 | C109: PESADA
B110: -500 | C110: ADELANTO
B111: 280 | C111: peajes
B112: -300 | C112: ADELANTO
B113: 800 | C113: peajes
B114: -800 | C114: adelanto
B115: 800 | C115: PEAJES | D115: 44652
B116: -800 | C116: ADELANTO | D116: 44652
B117: 680 | C117: PEAJES | D117: 44671
B118: 1800 | C118: LAVADO
B119: -2400 | C119: ADELANTO
B120: 280 | C120: PEAJES | D120: 44677
B121: -300 | C121: ADELANTO | D121: 44677
B122: 680 | C122: PEAJES | D122: 44687
B123: -700 | C123: ADERLANTO
B124: 560
B125: -600
B126: 440 | C126: PEAJES | D126: 44700
B127: -400 | C127: ADELANTO | D127: 44700
B128: 880 | C128: peajes | D128: 44713
...

Sheet NOVILLO
D1: AC860OW
A2: DIA | B2: SALE DE | C2: LLEGA A | D2: KM REC | E2: TN COM 29 | F2: TN ESC 35 | G2: TN ESC 37,5 | H2: REMITO Nº | I2: MATERIAL | J2: KM VACIOS | K2: $
A25: 46113 | B25: ROSARIO | C25: IBICUY | D25: 300 | H25: VACIO
A26: 46113 | B26: IBICUY | C26: ADELA 6 | D26: 1450 | H26: 118679 | I26: ADELA YPF
A27: 46115 | B27: ADELA 6 | C27: L. NEGRA | D27: 970 | H27: VACIO
A28: 46119 | B28: L. NEGRA | C28: CAMPANA | D28: 420 | F28: 34.59 | H28: 619143 | I28: HOLCIM
A29: 46120 | B29: CAMPANA | C29: IBICUY | D29: 85 | H29: VACIO
A30: 46120 | B30: IBICUY | C30: AÑELO | D30: 1430 | H30: 119935 | I30: YPF
A31: 46122 | B31: AÑELO | C31: L. NEGRA | D31: 940 | H31: VACIO
A32: 46126 | B32: L. NEGRA | C32: ZAPALA | D32: 1010 | F32: 34.19 | H32: 619649 | I32: CLINKER
A33: 46127 | B33: ZAPALA | C33: ALLEN | D33: 230 | H33: VACIO
A34: 46128 | B34: ALLEN | C34: L. NEGRA | D34: 820 | F34: 34.8 | H34: 189593 | I34: YESO LOMA
A35: 46130 | B35: L. NEGRA | C35: ZAPALA | D35: 1010 | F35: 34.58 | H35: 619979 | I35: CLINKER
A36: 46133 | B36: ZAPALA | C36: ALLEN | D36: 240 | H36: VACIO
A37: 46134 | B37: ALLEN | C37: L. NEGRA | D37: 820 | F37: 34.1 | H37: 189808 | I37: YESO LOMA
A38: 46135 | B38: L. NEGRA | C38: SALTO | D38: 380 | H38: 767727
A39: 46136 | B39: SALTO | C39: LOMASER | D39: 200 | H39: VACIO
A40: 46136 | B40: LOMASER | C40: RAMALLO | D40: 300 | H40: 5292 | I40: PALLETS
A41: 46137 | B41: RAMALLO | C41: L. NEGRA | D41: 500 | F41: 34.88 | H41: 1067076 | I41: ESCORIA
A42: 46140 | B42: L. NEGRA | C42: RAMALLO | D42: 500 | H42: 620414
A43: 46140 | B43: RAMALLO | C43: SIDERAR | D43: 10 | H43: VACIO
A44: 46140 | B44: SIDERAR | C44: RAMALLO | D44: 10 | H44: 1067559 | I44: CORTO
A45: 46141 | B45: RAMALLO | C45: SIDERAR | D45: 10 | H45: VACIO
A46: 46141 | B46: SIDERAR | C46: RAMALLO | D46: 10 | H46: 1067641 | I46: CORTO
A47: 46141 | B47: RAMALLO | C47: L. NEGRA | D47: 500 | H47: 1067674 | I47: ESCORIA
A48: 46142 | B48: L. NEGRA | C48: CACHARI | D48: 130 | F48: ENGANCHO | G48: ACOPLADO | H48: ALBORNOZ
A49: 46142 | B49: CACHARI | C49: HINOJO | D49: 130 | H49: VACIO
D50: 30 A LAS 20
D52: =SUM(D3:D51) -> 12405 | F52: =AVERAGE(F3:F50) -> 34.523333 | J52: =SUM(J3:J51) -> 0 | K52: =SUM(K3:K51) -> 0 | L52: =+K52/D52 -> 0
B54: -2000
B55: 480
B56: -500
B57: 480 | C57: PEAJES | D57: 44105
B58: -500 | C58: ADELANTO | D58: 44105
B59: 480 | C59: PEAJES | D59: 44128
B60: -500 | C60: ADELANTO | D60: 44128
B61: 740 | C61: peajes | D61: 44184
B62: -700 | C62: ADELANTO | D62: 44184
B63: 1000 | C63: ARREGLO DE GOMA | D63: 44188
B64: -1000 | C64: ADELANTO
B65: 790 | C65: PEAJES
B66: -800 | C66: ADELANTO
B67: 315 | C67: PEAJES
B68: -300 | C68: ADELANTO
B69: 260 | C69: PEAJES | D69: 44218
B70: -300 | C70: ADELANTO
B71: 400 | C71: PEAJES
B72: -400 | C72: ADELANTO
B73: 375 | C73: peajes
B74: -400 | C74: ADELANTO
B75: 500 | C75: PEAJES | D75: 44268
B76: -500 | C76: ADELANTO | D76: 44268
B77: 600 | C77: PEAJES | D77: 44284
B78: -600 | C78: ADELANTO | D78: 44284
B79: 670 | C79: PEAJES | D79: 44310
B80: -600 | C80: ADELANTO | D80: 44310
B81: 1325 | C81: PEAJES
B82: -2000 | C82: ADELANTO
B83: 3025 | C83: PEAJES | D83: 44351
B84: -3340 | C84: ADELANTO | D84: 44351
B85: 2550 | C85: peajes
B86: -2600 | C86: adelanto | D86: 44358
B87: 1900 | C87: PEAJES | D87: 44370
B88: -1900 | C88: ADELANTO
B89: 750 | C89: PEAJES | D89: 44380
B90: 684 | C90: PEAJES | D90: 44410
B91: -700 | C91: ADELANTO | D91: 44410
B92: 620 | C92: PEAJES | D92: 44417
B93: -400 | C93: ADELANTO | D93: 44417
B94: 220 | C94: PEAJES | D94: 44473
B95: -200 | C95: ADELANTO | D95: 44473
B96: 1260 | C96: PEAJES | D96: 44475
B97: -1300 | C97: ADELANTO | D97: 44475
B98: 1700 | C98: PEAJES | D98: 44477
B99: -1700 | C99: ADELANTO
B100: 1420 | C100: PEAJES | D100: 44491
B101: -1420 | C101: ADELANTO | D101: 44491
B102: 3050 | C102: PEAJES
B103: -4000
B104: 380 | C104: PEAJES | D104: 44517
B105: 300 | C105: BALANZA | D105: 44534
B106: 300 | C106: BALANZA
B107: -300 | C107: ADELANTO
B108: 360 | C108: PEAJES | D108: 44639
B109: 440 | C109: PEAJES
B110: -400 | C110: ADELANTO
B111: 1680 | C111: PEAJES
B112: -1600 | C112: ADELANTO
B113: 940 | C113: PEAJES | D113: 44658
B114: -1100 | C114: ADELANTO | D114: 44658
B115: 2200 | C115: PEAJES
B116: -2200 | C116: ADELANTO
B117: 680 | C117: PEAJES | D117: 44753
B118: -700 | C118: ADELANTO | D118: 44753
B119: 580 | C119: PEAJES
B120: -600 | C120: ADELANTO
B121: 560 | C121: PEAJES | D121: 44774
B122: -500 | C122: ADELANTO | D122: 44774
B123: 560 | C123: peajes | D123: 44789
B124: 1040 | C124: PEAJES | D124: 44804
...

Sheet ARIAS
D1: AA244ZJ
A2: DIA | B2: SALE DE | C2: LLEGA A | D2: KM REC | E2: TN COM 29 | F2: TN ESC 35 | G2: TN ESC 37,5 | H2: REMITO Nº | I2: MATERIAL | J2: KM VACIOS | K2: $
A33: 46113 | B33: SOLA | C33: LOMASER | D33: 70 | H33: VACIO
A34: 46113 | B34: LOMASER | C34: PUNTA ALTA | D34: 610 | H34: 894728 | K34: 1076388.4
A35: 46118 | B35: PUNTA ALTA | C35: L. NEGRA | D35: 310 | H35: VACIO
A36: 46119 | B36: L. NEGRA | C36: SOLA | D36: 360 | F36: 35.05 | H36: 765047 | K36: 1174368.6
A37: 46120 | B37: SOLA | C37: ESCOBAR | D37: 70 | H37: DERIVACION
A38: 46121 | B38: ESCOBAR | C38: LOMASER | D38: 130 | H38: VACIO
A39: 46121 | B39: LOMASER | C39: RAMALLO | D39: 300 | H39: 895495
A40: 46122 | B40: RAMALLO | C40: ESCOBAR | D40: 185 | F40: 35.24 | H40: 278830 | I40: ESCORIA
A41: 46122 | B41: ESCOBAR | C41: LOMASER | D41: 130 | H41: VACIO
A42: 46122 | B42: LOMASER | C42: PUNTA ALTA | D42: 610 | H42: 895692 | K42: 1076388.4
A43: 46125 | B43: PUNTA ALTA | C43: L. NEGRA | D43: 310 | H43: VACIO
A44: 46125 | B44: L. NEGRA | C44: SOLA | D44: 360 | F44: 34.98 | H44: 766068 | K44: 1171020.9
A45: 46127 | B45: SOLA | C45: LOMASER | D45: 70 | H45: VACIO
A46: 46128 | B46: LOMASER | C46: RAMALLO | D46: 300 | F46: 35 | H46: 896493
A47: 46128 | B47: RAMALLO | C47: LOMASER | D47: 300 | F47: 35.02 | H47: 279076 | I47: ESCORIA
A48: 46139 | B48: LOMASER | C48: PUNTA ALTA | D48: 610 | H48: 896758
A49: 46131 | B49: PUNTA ALTA | C49: L. NEGRA | D49: 310 | H49: VACIO
A50: 46132 | B50: L. NEGRA | C50: SOLA | D50: 360 | F50: 34.9 | H50: 767180
A51: 46134 | B51: SOLA | C51: LOMASER | D51: 70 | H51: VACIO
A52: 46135 | B52: LOMASER | C52: RAMALLO | D52: 300 | H52: 897555
A53: 46135 | B53: RAMALLO | C53: LOMASER | D53: 300 | F53: 35.28 | H53: 279337 | I53: ESCORIA
A54: 46136 | B54: LOMASER | C54: PUNTA ALTA | D54: 610 | H54: 897821
A55: 46142 | B55: PUNTA ALTA | C55: L. NEGRA | D55: 310 | H55: VACIO
D56: LLEGO A PRINGLES
D58: =SUM(D3:D57) -> 6985 | F58: =AVERAGE(F3:F56) -> 35.067143 | J58: =SUM(J3:J57) -> 0 | K58: =SUM(K3:K57) -> 4498166.2
B60: -2000
B61: 300
B62: -300 | C62: ADELANTO | D62: 44229
B63: 300 | C63: PEAJE
B64: -300 | C64: ADELANTO
B65: 200 | C65: PEAJE | D65: 44279
B66: 300 | C66: BALANZA
B67: -500 | C67: ADELANTO
B68: 345 | C68: PEAJE | D68: 44300
B69: -400 | C69: ADELANTO
B70: 615 | C70: PEAJE | D70: 44324
B71: -600 | C71: ADELANTO
B72: 1000 | C72: gomeria | D72: 44329
B73: -1000 | C73: adelanto | D73: 44329
B74: 630 | C74: PEAJES | D74: 44350
B75: -600 | C75: ADELANTO
B76: 1750 | C76: PEAJES Y ARGOMA
B77: -1800 | C77: ADELANTO | D77: 44373
B78: 200 | C78: PEAJES | D78: 44389
B79: 300 | C79: PEAJES | D79: 44398
B80: -500 | C80: ADELANTO | D80: 44398
B81: 740 | C81: PEAJES
B82: -700 | C82: ADELANTO
B83: 1000 | C83: IMP MISIONES
B84: -1000 | C84: ADELANTO
B85: 300 | C85: PEAJES
B86: -300 | C86: ADELANTO
B87: 300 | C87: PEAJES | D87: 44422
B88: -300 | C88: ADELANTI | D88: 44422
B89: 520 | C89: peajes | D89: 44439
B90: -500 | C90: adelanto | D90: 44439
B91: 520 | C91: PEA/BALAN | D91: 44461
B92: -600 | C92: ADELANTO
B93: 520 | C93: peajes
B94: -500 | C94: adelanto
B95: 220 | C95: peajes | D95: 44474
B96: -200 | C96: adelanto | D96: 44474
B97: 300 | C97: PEAJE
B98: -300 | C98: ADELANTO
B99: 520 | C99: FITO SANITARIO | D99: 44498
B100: -520 | C100: ADELANTO
B101: 220 | C101: PEAJES | D101: 44516
B102: -220 | C102: ADELANTO | D102: 44516
B103: -500 | C103: ADELANTO
B104: 520 | C104: PEAJES
B105: 220 | C105: peajes
B106: -200 | C106: adelanto | D106: 44526
B107: 220 | C107: PEAJES | D107: 44534
B108: -300 | C108: ADELANTO
B109: 520 | C109: peajes | D109: 44545
B110: -520 | C110: adelanto | D110: 44545
B111: 1506 | C111: PEAJES | D111: 44567
B112: -1500 | C112: ADELANTO
B113: 190 | C113: PEAJES
B114: -200 | C114: ADELANTO
B115: 420 | C115: PEAJE
B116: -400 | C116: ADELANTO
B117: 220 | C117: PEAJES | D117: 44576
B118: -200 | C118: ADELANTO
B119: 220 | C119: peaje
B120: -220 | C120: adelanto | D120: 44583
B121: 220 | C121: peajes
B122: -200 | C122: adelanto
B123: 220 | C123: PEAJES | D123: 44597
B124: -200 | C124: ADELANTO
B125: 280 | C125: PEAJE | D125: 44610
B126: -300 | C126: ADELANTO
B127: 800 | C127: PEAJES | D127: 44636
B128: -800 | C128: ADELANTO | D128: 44636
B129: 800 | C129: PEAJES | D129: 44639
B130: -800 | C130: ADELANTO
B131: 800 | C131: BALANZA
B132: -800 | C132: ADELANTO | D132: 44644
...

Sheet JUAREZ
D1: NYU 936
A2: DIA | B2: SALE DE | C2: LLEGA A | D2: KM REC | E2: TN COM 29 | F2: TN ESC 35 | G2: TN ESC 37,5 | H2: REMITO Nº | I2: MATERIAL | J2: KM VACIOS | K2: $
A36: 46112 | B36: L. NEGRA | C36: SOLA | D36: 360 | G36: 37.36 | H36: 293159 | I36: PIEDRA | K36: 704281.13
A37: 46113 | B37: SOLA | C37: IBICUY | D37: 180 | H37: VACIO
A38: 46114 | B38: IBICUY | C38: AÑELO | D38: 1430 | H38: 118879 | I38: YPF
A39: 46118 | B39: AÑELO | C39: L. NEGRA | D39: 1000 | H39: VACIO
A40: 46120 | B40: L. NEGRA | C40: CAMPANA | D40: 420 | G40: 36.86 | H40: 619192 | I40: HOLCIM
A41: 46121 | B41: CAMPANA | C41: RAMALLO | D41: 170 | G41: FUE A TALLER | H41: VACIO | I41: BESTEN
A42: 46123 | B42: RAMALLO | C42: L. NEGRA | D42: 500 | G42: 35.62 | H42: 1064633 | I42: LODO
A43: 46125 | B43: L. NEGRA | C43: SANTA ROSA | D43: 450 | H43: 766112
A44: 46126 | B44: SANTA ROSA | C44: L. NEGRA | D44: 450 | H44: VACIO
A45: 46126 | B45: L. NEGRA | C45: S. FERNANDO | D45: 420 | H45: 766324
A46: 46127 | B46: S. FERNANDO | C46: IBICUY | D46: 150 | H46: VACIO
A47: 46128 | B47: IBICUY | C47: BAJO DEL TORO | D47: 1560 | H47: 121289 | I47: YPF TORO
A48: 46130 | B48: BAJO DEL TORO | C48: ALLEN | D48: 270 | H48: VACIO
A49: 46132 | B49: ALLEN | C49: L. NEGRA | D49: 820 | G49: 34.2 | H49: 189557 | I49: YESO LOMA
A50: 46134 | B50: L. NEGRA | C50: ZAPALA | D50: 1010 | G50: 36.19 | H50: 620169 | I50: CLINKER
A51: 46136 | B51: ZAPALA | C51: ALLEN | D51: 240 | H51: VACIO
A52: 46136 | B52: ALLEN | C52: L. NEGRA | D52: 820 | G52: 36.5 | H52: 189893 | I52: YESO LOMA
A53: 46139 | B53: L. NEGRA | C53: CAMPANA | D53: 420 | G53: 36.52 | H53: 620386 | I53: HOLCIM
A54: 46140 | B54: CAMPANA | C54: IBICUY | D54: 85 | H54: VACIO
A55: 46141 | B55: IBICUY | C55: BAJO DEL TORO | D55: 1520 | H55: 123675 | I55: YPF TORO
D56: 30 A LAS 21
D58: =SUM(D3:D57) -> 12275 | G58: =AVERAGE(G3:G56) -> 36.178571 | J58: =SUM(J3:J57) -> 0 | K58: =SUM(K3:K57) -> 704281.13
B60: -2000
B61: 300 | C61: 44419
B62: -300 | C62: 44419
B63: 300 | C63: PEAJES | D63: 44483
B64: -300 | C64: ADELANTO | D64: 44483
B65: -700 | C65: GOMERIA
B66: 700 | C66: ADELANTO
B67: 1000 | C67: PEAJES
B68: -1000 | C68: ADELANTO
B69: 420 | C69: BALANZA | D69: 44610
B70: -500 | C70: ADELANTO
B71: 440 | C71: peajes | D71: 44645
B72: -400 | C72: adelanto | D72: 44645
B73: 680 | C73: peajes | D73: 44676
B74: -700 | C74: ADELANTO | D74: 44676
B75: -300 | C75: ANTEC PENAL | D75: 44741
B76: 480 | C76: PEAJES | D76: 44751
B77: -200 | C77: ADELANTO
B78: 200 | C78: PEAJES
B79: -200 | C79: ADELANTO
B80: 480 | C80: PEAJES
B81: -500 | C81: ADELANTO
B82: 480 | C82: PEAJES
B83: -500 | C83: ADELANTO | D83: 44778
B84: 480 | C84: PEAJES | D84: 44807
B85: -500 | C85: ADELANTO | D85: 44807
B86: 480 | C86: PEAJES
B87: -500 | C87: ADELANTO | D87: 44834
B88: 480 | C88: PEAJES
B89: -400 | C89: ADELANTO
B90: 480 | C90: PEAJES | D90: 44849
B91: -500 | C91: ADELANTO | D91: 44849
B92: 800 | C92: PEAJES | D92: 44866
B93: -800 | C93: ADELANTO
B94: 800 | C94: PEAJES | D94: 44907
B95: -800 | C95: ADELANTO | D95: 44907
B96: 800 | C96: PEAJES | D96: 44912
B97: 800 | C97: PEAJES | D97: 44963
B98: -800 | C98: ADELANTO | D98: 44963
B99: 800 | C99: PEAJES | D99: 44970
B100: -800 | C100: ADELANTO
B101: 800 | C101: PEAJES | D101: 44988
B102: -1500 | C102: ADELANTO | D102: 44988
B103: 800 | C103: PEAJES
B104: -800 | C104: ADELANTO
B105: 800 | C105: PEAJES
B106: -800 | C106: ADELANTO | D106: 45023
B107: 1600 | C107: PEAJES
B108: 800 | C108: PEAJES
B109: -2400 | C109: ADELANTO
B110: 1200 | C110: PEAJES | D110: 45066
B111: -1200 | C111: ADELANTO | D111: 45066
B112: 1200 | C112: peajes | D112: 45071
B113: -1200 | C113: ADELANTO | D113: 45071
B114: 1200 | C114: PEAJES | D114: 45089
B115: -1200 | C115: ADELANTO | D115: 45089
B116: 1200 | C116: PEAJES | D116: 45093
B117: -1200 | C117: ADELANTO | D117: 45093
B118: 1200 | C118: PEAJES | D118: 45108
B119: -1200 | C119: ADELANTO | D119: 45108
B120: 1600 | C120: PEAJES | D120: 45209
B121: -1600 | C121: ADELANTO
B122: -1100 | C122: ANTEC PENAL | D122: 45436
B123: 1200 | C123: peajes | D123: 45439
B124: -8000 | C124: ADELANTO | D124: 45439
B125: 5050 | C125: PEAJES | D125: 45497
B126: -5000 | C126: ADELANTO
B127: 64500 | C127: PEAJES | D127: 45530
B128: -64500 | C128: ADELANTO | D128: 45530
B129: 31500 | C129: PEAJES
B130: -32000 | C130: ADELANTO | D130: 45565
B131: 13300 | C131: PEAJES | D131: 45769
B132: -13300 | C132: ADELANTO | D132: 45769
B133: 108200 | C133: PEAJES | D133: 45817
B134: -108000 | C134: ADELANTO
B135: 1800 | C135: PEAJES | D135: 45894
...

Sheet MEHRING
D1: NYU 936
A2: DIA | B2: SALE DE | C2: LLEGA A | D2: KM REC | E2: TN COM 29 | F2: TN ESC 35 | G2: TN ESC 37,5 | H2: REMITO Nº | I2: MATERIAL | J2: KM VACIOS | K2: $
A33: 46113 | B33: LOMASER | C33: L. NEGRA | D33: 300 | H33: VACIO
A34: 46113 | B34: L. NEGRA | C34: BAHIA BLANCA | D34: 310 | F34: 33.96 | H34: 764519
A35: 46118 | B35: BAHIA BLANCA | C35: L. NEGRA | D35: 310 | H35: VACIO
A36: 46118 | B36: L. NEGRA | C36: M. DEL PLATA | D36: 320 | F36: 33.96 | H36: 764969
A37: 46119 | B37: M. DEL PLATA | C37: L. NEGRA | D37: 320 | H37: VACIO
A38: 46120 | B38: L. NEGRA | C38: OLAVARRIA | D38: 40 | F38: 33.82 | H38: 765164 | K38: 294013.49
A39: 46120 | B39: OLAVARRIA | C39: L. NEGRA | D39: 40 | H39: VACIO
A40: 46121 | B40: L. NEGRA | C40: OLAVARRIA | D40: 40 | F40: 33.98 | H40: 765411 | K40: 295404.45
A41: 46122 | B41: OLAVARRIA | C41: L. NEGRA | D41: 40 | H41: VACIO
A42: 46122 | B42: L. NEGRA | C42: B. DE ESCOBAR | D42: 430 | F42: 34.12 | H42: 765699
A43: 46125 | B43: B. ESCOBAR | C43: LOMASER | D43: 140 | H43: VACIO
A44: 46126 | B44: LOMASER | C44: RAMALLO | D44: 300 | H44: 896108
A45: 46126 | B45: RAMALLO | C45: LOMASER | D45: 300 | H45: 278974 | I45: ESCORIA
A46: 46127 | B46: LOMASER | C46: RAMALLO | D46: 300 | H46: 896347
A47: 46127 | B47: RAMALLO | C47: LOMASER | D47: 300 | H47: 279034 | I47: ESCORIA
A48: 46127 | B48: LOMASER | C48: L. NEGRA | D48: 300 | H48: VACIO
A49: 46129 | B49: L. NEGRA | C49: B. DE ESCOBAR | D49: 430 | F49: 34.08 | H49: 766862
A50: 46132 | B50: B. ESCOBAR | C50: LOMASER | D50: 140 | H50: VACIO
A51: 46132 | B51: LOMASER | C51: DARSENA | D51: 80 | F51: 33.94 | H51: 897030
A52: 46133 | B52: DARSENA | C52: LOMASER | D52: 80 | H52: VACIO
A53: 46134 | B53: LOMASER | C53: RAMALLO | D53: 300 | H53: 897340
A54: 46134 | B54: RAMALLO | C54: LOMASER | D54: 300 | H54: 279303 | I54: ESCORIA
A55: 46136 | B55: LOMASER | C55: PUNTA ALTA | D55: 610 | F55: 35.97 | H55: 897808
A56: 46137 | B56: PUNTA ALTA | C56: L. NEGRA | D56: 310 | H56: VACIO
A57: 46137 | B57: L. NEGRA | C57: SOLA | D57: 360 | F57: 34 | H57: 768152
A58: 46139 | B58: SOLA | C58: LOMASER | D58: 70 | H58: VACIO
A59: 46140 | B59: LOMASER | C59: TORTUGUITAS | D59: 140 | F59: 33.86 | H59: 898328
A60: 46140 | B60: TORTUGUITAS | C60: LOMASER | D60: 140 | H60: VACIO
A61: 46141 | B61: LOMASER | C61: RAMALLO | D61: 300 | H61: 898631
A62: 46142 | B62: RAMALLO | C62: SOLA | D62: 240 | F62: 33.42 | H62: 279581 | I62: ESCORIA
D63: 30 A LAS 15
D65: =SUM(D3:D64) -> 7290 | F65: =AVERAGE(F3:F63) -> 34.100909 | J65: =SUM(J3:J64) -> 0 | K65: =SUM(K3:K64) -> 589417.94 | L65: =+K65/D65 -> 80.852941
B67: -2000
B68: 280 | C68: peajes | D68: 44523
B69: -300 | C69: adelanto | D69: 44523
B70: 300 | C70: BALANZA S.PEDRO | D70: 44566
B71: -300 | C71: adelanto | D71: 44566
B72: 1060 | C72: peajes | D72: 44581
B73: 800 | C73: gomeria | D73: 44581
B74: -1900 | C74: adelanto | D74: 44581
B75: 1600 | C75: peajes | D75: 44587
B76: -1600 | C76: adelanto | D76: 44587
B77: 1610 | C77: PEAJES
B78: -1610 | C78: adelanto
B79: 680 | C79: peajes | D79: 44643
B80: -700 | C80: adelanto | D80: 44643
B81: 1000 | C81: balanza bto juarez | D81: 44721
B82: 280 | C82: peajes
B83: -1200 | C83: adelanto
B84: 680 | C84: peajes | D84: 44741
B85: -700 | C85: adelanto | D85: 44741
B86: 1500 | C86: gomeria
B87: 660 | C87: peajes
B88: -2200 | C88: adelanto
B89: 480 | C89: PEAJES
B90: -600 | C90: ADELANTO | D90: 44786
B91: 300 | C91: peajes | D91: 44818
B92: -200 | C92: adelanto | D92: 44818
B93: 1160 | C93: peajes
B94: -1100 | C94: adelanto
B95: 480 | C95: PEAJES | D95: 44849
B96: -500 | C96: ADEALNTO
B97: 480 | C97: peajes | D97: 44860
B98: -500 | C98: ADELANTO | D98: 44860
B99: 1650 | C99: peajes
B100: -1600 | C100: adelanto
B101: 800 | C101: PEAJES | D101: 44883
B102: -800 | C102: ADELANTO
B103: 800 | C103: peajes | D103: 44914
B104: -800 | C104: ADELANTO | D104: 44914
B105: 2800 | C105: PEAJES | D105: 44933
B106: -2800 | C106: ADELANTO
B107: 1600 | C107: peajes | D107: 45022
B108: -1600 | C108: adelanto | D108: 45022
B109: 800 | C109: peajes | D109: 45030
B110: -800 | C110: adelanto
B111: 800 | C111: peajes
B112: -800 | C112: adelanto
B113: 1800 | C113: peajes | D113: 45121
B114: -1800 | C114: adelanto
B115: 3000 | C115: PEAJES | D115: 45122
B116: -3000 | C116: ADELANTO
B117: 600 | C117: PEAJES
B118: -600 | C118: ADELANTO | D118: 45136
B119: 2400 | C119: peajes | D119: 45166
B120: -2400 | C120: adelanto | D120: 45166
B121: 800 | C121: peajes | D121: 45234
B122: -800 | C122: adelanto | D122: 45234
B123: -300 | C123: ANT. PENALES | D123: 45258
B124: 17500 | C124: gomeria | D124: 45345
B125: -17500 | C125: gomeria
B126: 32800 | C126: peajes | D126: 45481
B127: -40000 | C127: ade | D127: 45481
B128: 72000
B129: -72000 | D129: 45503
B130: -50000 | C130: adelanto | D130: 45538
B131: 28000 | C131: PEAJES | D131: 45562
B132: 6400 | C132: peajers | D132: 45607
...

Sheet RAMOS
D1: NYU 936
A2: DIA | B2: SALE DE | C2: LLEGA A | D2: KM REC | E2: TN COM 29 | F2: TN ESC 35 | G2: TN ESC 37,5 | H2: REMITO Nº | I2: MATERIAL | J2: KM VACIOS | K2: $
A28: 46112 | B28: ALLEN | C28: L. NEGRA | D28: 820 | F28: 35.2 | H28: 189330 | I28: YESO LOMA
A29: 46118 | B29: L. NEGRA | C29: M. DEL PLATA | D29: 320 | H29: 764961 | K29: 857189.3
A30: 46119 | B30: M. DEL PLATA | C30: L. NEGRA | D30: 320 | H30: VACIO
A31: 46120 | B31: L. NEGRA | C31: CAMPANA | D31: 420 | F31: 34.62 | H31: 619200 | I31: HOLCIM
A32: 46120 | B32: CAMPANA | C32: IBICUY | D32: 85 | H32: VACIO
A33: 46121 | B33: IBICUY | C33: BAJO DEL TORO | D33: 1570 | H33: 120071 | I33: YPF TORO 5
A34: 46123 | B34: BAJO DEL TORO | C34: L. NEGRA | D34: 1070 | H34: VACIO
A35: 46126 | B35: L. NEGRA | C35: GRAL. PICO | D35: 450 | H35: 766231
A36: 46127 | B36: GRAL. PICO | C36: L. NEGRA | D36: 450 | H36: VACIO
A37: 46128 | B37: L. NEGRA | C37: ZAPALA | D37: 1010 | F37: 34.56 | H37: 619778 | I37: CLINKER
A38: 46129 | B38: ZAPALA | C38: L. NEGRA | D38: 1060 | H38: 16415 | I38: TANDILIA
A39: 46132 | B39: L. NEGRA | C39: BERISSO | D39: 360 | F39: 34.4 | H39: 294169 | I39: PIEDRA
A40: 46133 | B40: BERISSO | C40: LOMASER | D40: 110 | H40: VACIO
A41: 46133 | B41: LOMASER | C41: ZAPALA | D41: 1300 | H41: 5279 | I41: PALLETS
A42: 46135 | B42: ZAPALA | C42: L. NEGRA | D42: 1060 | H42: 16433 | I42: TANDILIA
A43: 46136 | B43: L. NEGRA | C43: M. DEL PLATA | D43: 320 | H43: 767985
A44: 46139 | B44: M. DEL PLATA | C44: L. NEGRA | D44: 320 | H44: VACIO
A45: 46139 | B45: L. NEGRA | C45: TORCUATO | D45: 400 | F45: 34.54 | H45: 294677 | I45: PIEDRA
A46: 46140 | B46: TORCUATO | C46: IBICUY | D46: 150 | H46: VACIO
A47: 46140 | B47: IBICUY | C47: BAJO DEL TORO | D47: 1560 | H47: ???? | I47: YPF TORO
D48: 1 A LAS 4 AM
D50: =SUM(D3:D49) -> 13155 | F50: =AVERAGE(F3:F48) -> 34.664 | J50: =SUM(J3:J49) -> 0 | K50: =SUM(K3:K49) -> 857189.3 | L50: =+K50/D50 -> 65.160722
B52: -2000
B53: 220 | C53: PEAJES | D53: 44517
B54: -300 | C54: ADELANTO | D54: 44517
B55: 620 | C55: PEAJES
B56: -600 | C56: ADELANTO | D56: 44530
B57: 220 | C57: PEAJES | D57: 44558
B58: -200 | C58: ADELANTO | D58: 44558
B59: 620 | C59: PEAJES | D59: 44560
B60: -600 | C60: ADELANTO | D60: 44560
B61: 220 | C61: PEAJES | D61: 44564
B62: -200 | C62: ADELANTO
B63: 220 | C63: PEAJES | D63: 44568
B64: -220 | C64: ADELANTO | D64: 44568
B65: 420 | C65: BALANZA | D65: 44571
B66: 500 | C66: ADELANTO
B67: 620 | C67: PEAJES | D67: 44576
B68: -1000 | C68: ADELANTO | D68: 44576
B69: -1000 | C69: GOMERIA | D69: 44576
B70: 840 | C70: PEAJES | D70: 44579
B71: -400 | C71: ADELANTO
B72: 220 | C72: PEAJES | D72: 44581
B73: -200 | C73: ADELANTO | D73: 44581
B74: 420 | C74: BALANZA | D74: 44589
B75: -500 | C75: ADELANTO
B76: 620 | C76: PEAJES | D76: 44596
B77: -600 | C77: ADELANTO
B78: 220 | C78: PEAJES | D78: 44599
B79: -200 | C79: ADELANTO
B80: 620 | C80: PEAJES | D80: 44601
B81: -600 | C81: ADELANTO | D81: 44601
B82: 640 | C82: PEAJES | D82: 44603
B83: -700 | C83: ADELANTO | D83: 44603
B84: 880 | C84: PEAJES
B85: -900 | C85: ADELANTO
B86: 560 | C86: PEAJES | D86: 44628
B87: -500 | C87: ADELANTO | D87: 44628
B88: 100 | C88: PEAJES | D88: 44628
B89: 840 | C89: PEAJES | D89: 44634
B90: -900 | C90: ADELANTO | D90: 44634
B91: 100 | C91: PEAJES | D91: 44636
B92: -100 | C92: ADELANTO
B93: 560 | C93: PEAJES | D93: 44645
B94: -600 | C94: ADELANTO | D94: 44645
B95: 280 | C95: PEAJES | D95: 44649
B96: -300 | C96: ADELANTO | D96: 44649
B97: 1320 | C97: PEAJES | D97: 44660
B98: -1300 | C98: ADELANTO | D98: 44660
B99: 280 | C99: PEAJES | D99: 44665
B100: -300 | C100: ADELANTO | D100: 44665
B101: 560 | C101: PEAJES | D101: 44670
B102: -600 | C102: ADELANTO | D102: 44670
B103: 280 | C103: PEAJES | D103: 44687
B104: -200 | C104: ADELANTO | D104: 44687
B105: 280 | C105: PEAJES | D105: 44691
B106: -300 | C106: ADELANTO
B107: 640 | C107: PEAJES | D107: 44694
B108: -600 | C108: ADELANTO | D108: 44694
B109: 1320 | C109: PEAJES | D109: 44698
B110: -1400 | C110: ADELANTO
B111: 280 | C111: PEAJES | D111: 44705
B112: -300 | D112: 44705
B113: 560 | C113: PEAJES | D113: 44712
B114: -500 | C114: ADELANTO | D114: 44712
B115: 1160 | C115: PEAJES
B116: -1200 | C116: ADELANTO | D116: 44714
B117: 560 | C117: PEAJES | D117: 44719
B118: -500 | C118: ADELANTO | D118: 44719
B119: 560 | C119: PEAJES | D119: 44726
B120: -600 | C120: ADELANTO
B121: 280 | C121: PEAJES | D121: 44728
B122: -1300 | C122: ADELANTO | D122: 44728
B123: 1560 | C123: PEAJES | D123: 44735
B124: -1500 | C124: ADELANTO | D124: 44735
B125: 280 | C125: peajes | D125: 44740
B126: -300 | C126: PEAJES | D126: 44740
B127: 1160 | C127: PEAJES | D127: 44742
...

Sheet GARCIA
D1: NYU 936
A2: DIA | B2: SALE DE | C2: LLEGA A | D2: KM REC | E2: TN COM 29 | F2: TN ESC 35 | G2: TN ESC 37,5 | H2: REMITO Nº | I2: MATERIAL | J2: KM VACIOS | K2: $
A28: 46111 | B28: IBICUY | C28: ADELA 6 | D28: 1490 | H28: 118241 | I28: ADELA YPF
A29: 46114 | B29: ADELA 6 | C29: L. NEGRA | D29: 1070 | H29: VACIO
A30: 46116 | B30: L. NEGRA | C30: CAMPANA | D30: 420 | F30: 35.12 | H30: 618963 | I30: HOLCIM
A31: 46118 | B31: CAMPANA | C31: IBICUY | D31: 85 | H31: VACIO
A32: 46119 | B32: IBICUY | C32: BAJO DEL TORO | D32: 1560 | H32: 119623 | I32: YPF TORO
A33: 46122 | B33: BAJO DEL TORO | C33: L. NEGRA | D33: 1070 | H33: VACIO
A34: 46125 | B34: L. NEGRA | C34: ZAPALA | D34: 1010 | F34: 35.47 | H34: 619576 | I34: CLINKER
A35: 46127 | B35: ZAPALA | C35: ALLEN | D35: 240 | H35: VACIO
A36: 46127 | B36: ALLEN | C36: L. NEGRA | D36: 820 | F36: 29.1 | H36: 189549 | I36: YESO LOMA
A37: 46129 | B37: L. NEGRA | C37: ZAPALA | D37: 1010 | H37: 619865 | I37: CLINKER
A38: 46132 | B38: ZAPALA | C38: ALLEN | D38: 240 | H38: VACIO
A39: 46132 | B39: ALLEN | C39: L. NEGRA | D39: 820 | F39: 27.8 | H39: 189728 | I39: YESO LOMA
A40: 46136 | B40: L. NEGRA | C40: TORCUATO | D40: 400 | H40: 294489 | I40: PIEDRA
A41: 46139 | B41: TORCUATO | C41: IBICUY | D41: 150 | H41: VACIO
A42: 46139 | B42: IBICUY | C42: AÑELO | D42: 1430 | H42: 123322 | I42: YPF
A43: 46141 | B43: AÑELO | C43: L. NEGRA | D43: 940 | H43: VACIO
D44: 30 A LAS 14
D46: =SUM(D3:D45) -> 12755 | F46: =AVERAGE(F3:F44) -> 31.8725 | J46: =SUM(J3:J45) -> 0 | K46: =SUM(K3:K45) -> 0
B48: -2000
B49: 280 | C49: peajes | D49: 44550
B50: 1220 | C50: peajes | D50: 44641
B51: -1500 | C51: adelanto | D51: 44641
B52: 600 | C52: PEAJES
B53: -600 | C53: ADELANTO
B54: 560 | C54: peajes | D54: 44809
B55: -600 | C55: adelanto | D55: 44809
B56: 1360 | C56: PEAJES | D56: 44814
B57: -1400 | C57: ADELANTO
B58: 840 | C58: PEAJES | D58: 44818
B59: -800 | C59: adelanto | D59: 44818
B60: 1660 | C60: peajes | D60: 44837
B61: -1700 | C61: adelanto | D61: 44837
B62: 400 | C62: peajes | D62: 44863
B63: -400 | C63: adelanto
B64: -300 | C64: ANT. PENALES | D64: 44867
B65: 400 | C65: peajes | D65: 44868
B66: -400 | C66: adelanto | D66: 44868
B67: 800 | C67: PEAJES | D67: 44877
B68: -800 | C68: adelanto | D68: 44877
B69: 400 | C69: peajes | D69: 44880
B70: 800 | C70: peajes | D70: 44890
B71: -900 | C71: adelanto
B72: 800 | C72: peajes
B73: -800 | C73: adelanto
B74: 800 | C74: PEAJES | D74: 44914
B75: -800 | C75: adelanto | D75: 44914
B76: 2400 | C76: peajes | D76: 44932
B77: -2400 | C77: adelanto
B78: 800 | C78: peajes
B79: -800 | C79: adelanto
B80: 800 | C80: peajes
B81: -800 | C81: adelanto
B82: 2000 | C82: PEAJES | D82: 44968
B83: -2000 | C83: ADELANTO | D83: 44968
B84: 800 | C84: peajes | D84: 44987
B85: -800 | C85: adelanto
B86: 800 | C86: PEAJES | D86: 45005
B87: -800 | C87: adelanto | D87: 45005
B88: 800 | C88: PEAJES | D88: 45016
B89: -800 | C89: adelanto | D89: 45016
B90: 800 | C90: peajes | D90: 45022
B91: -800 | C91: adelanto
B92: 800 | C92: peajes | D92: 45030
B93: -800 | C93: adelanto | D93: 45030
B94: 800 | C94: PEAJES | D94: 45038
B95: -800 | C95: adelanto
B96: 800 | C96: peajes | D96: 45050
B97: -800 | C97: adelanto | D97: 45050
B98: 800 | C98: peajes | D98: 45059
B99: -800 | C99: adelanto
B100: 1200 | C100: PEAJES | D100: 45070
B101: -1200 | C101: adelanto | D101: 45070
B102: 1200 | C102: peajes | D102: 45083
B103: -1200 | C103: adelanto | D103: 45083
B104: 1200 | C104: PEAJES | D104: 45093
B105: -1200 | C105: ADELANTO | D105: 45093
B106: 1200 | C106: PEAJES | D106: 45139
B107: -1200 | C107: adelanto | D107: 45139
B108: 1600 | C108: peajes | D108: 45153
B109: -1600 | C109: adelanto | D109: 45153
B110: 2400 | C110: peajes
B111: -2400 | C111: adelanto
B112: 800 | C112: peajes
B113: -800 | C113: adelanto | D113: 45190
B114: -300 | C114: ANTEC PENAL | D114: 45222
B115: 1600 | C115: PEAJES
B116: -1300 | C116: adelanto
B117: 1800 | C117: PEAJE | D117: 45299
B118: -1800 | C118: ADELANTO
B119: -1000 | C119: ANTEC PENAL | D119: 45568
B120: -1000 | C120: ANTEC PENAL | D120: 45931
B122: =SUM(B48:B120) -> -4080 | C122: 45931
E124: =800*3 -> 2400

Sheet BENITEZ
D1: NYU 936
A2: DIA | B2: SALE DE | C2: LLEGA A | D2: KM REC | E2: TN COM 29 | F2: TN ESC 35 | G2: TN ESC 37,5 | H2: REMITO Nº | I2: MATERIAL | J2: KM VACIOS | K2: $
A25: 46112 | B25: LOMASER | C25: RAMALLO | D25: 300 | H25: 894559
A26: 46113 | B26: RAMALLO | C26: LOMASER | D26: 300 | F26: 36.3 | H26: 278577 | I26: ESCORIA
A27: 46116 | B27: LOMASER | C27: RAMALLO | D27: 300 | H27: 894798
A28: 46116 | B28: RAMALLO | C28: SOLA | D28: 240 | F28: 36.46 | H28: 278627 | I28: ESCORIA
A29: 46120 | B29: SOLA | C29: LOMASER | D29: 80 | H29: VACIO
A30: 46120 | B30: LOMASER | C30: BOSQUES | D30: 105 | F30: 36.38 | H30: 895238 | K30: 405399.07
A31: 46121 | B31: BOSQUES | C31: LOMASER | D31: 105 | H31: VACIO
A32: 46121 | B32: LOMASER | C32: RAMALLO | D32: 300 | H32: 895461
A33: 46122 | B33: RAMALLO | C33: LOMASER | D33: 300 | F33: 36.54 | H33: 278822 | I33: ESCORIA
A34: 46125 | B34: LOMASER | C34: DARSENA F | D34: 80 | F34: 36.09 | H34: 895964
A35: 46126 | B35: DARSENA F | C35: BARADERO | D35: 150 | H35: TALLER
A36: 46127 | B36: BARADERO | C36: LOMASER | D36: 190 | H36: VACIO
A37: 46128 | B37: LOMASER | C37: RAMALLO | D37: 300 | H37: 896497
A38: 46128 | B38: RAMALLO | C38: LOMASER | D38: 300 | F38: 36 | H38: 279084 | I38: ESCORIA
A39: 46132 | B39: LOMASER | C39: RAMALLO | D39: 300 | H39: 896961
A40: 46132 | B40: RAMALLO | C40: LOMASER | D40: 300 | F40: 36.28 | H40: 279210 | I40: ESCORIA
A41: 46132 | B41: LOMASER | C41: L. NEGRA | D41: 300 | H41: VACIO
A42: 46135 | B42: L. NEGRA | C42: B. DE ESCOBAR | D42: 430 | F42: 36.78 | H42: 767731
A43: 46136 | B43: B. ESCOBAR | C43: LOMASER | D43: 140 | H43: VACIO
A44: 46139 | B44: LOMASER | C44: RAMALLO | D44: 300 | H44: 898075
A45: 46139 | B45: RAMALLO | C45: URIBURU | D45: 80 | F45: 36.38 | H45: 279455
A46: 46140 | B46: URIBURU | C46: RAMALLO | D46: 80 | H46: VACIO
A47: 46140 | B47: RAMALLO | C47: LOMASER | D47: 300 | F47: 36.52 | H47: 279492 | I47: ESCORIA
A48: 46141 | B48: LOMASER | C48: RAMALLO | D48: 300 | F48: 36.26 | H48: 898492
A49: 46141 | B49: RAMALLO | C49: LOMASER | D49: 300 | F49: 36.42 | H49: 279561 | I49: ESCORIA
A50: 46142 | B50: LOMASER | C50: TORCUATO | D50: 140 | F50: 36.2 | H50: 898784
A51: 46142 | B51: TORCUATO | C51: LOMASER | D51: 140 | H51: VACIO
D52: 30A LAS 20
D54: =SUM(D3:D53) -> 6160 | F54: =AVERAGE(F3:F52) -> 36.354615 | J54: =SUM(J3:J53) -> 0 | K54: =SUM(K3:K53) -> 405399.07
B56: -2000
B57: 680 | C57: peajes | D57: 44629
B58: -700 | C58: adelanto
B59: 420 | C59: peajes | D59: 44635
B60: -400 | C60: adelanto | D60: 44635
B61: 680 | C61: PEAJES | D61: 44643
B62: -700 | C62: ADELANTO
B63: 680 | C63: peajes | D63: 44699
B64: -700 | C64: adelanto
B65: 1040 | C65: peajes | D65: 44734
B66: -1100 | C66: adelanto | D66: 44734
B67: 480 | C67: PEAJES
B68: -400 | C68: adelanto
B69: 480 | C69: peajes | D69: 44854
B70: -500 | C70: adelanto
B71: 800 | C71: PEAJES | D71: 44868
B72: -800 | C72: adelanto | D72: 44868
B73: 800 | C73: peajes | D73: 44891
B74: -800 | C74: adelanto | D74: 44891
B75: 800 | C75: PEAJES | D75: 44897
B76: -800 | C76: adelanto | D76: 44897
B77: 800 | C77: PEAJES | D77: 44912
B78: -800 | C78: ADELANTO | D78: 44912
B79: 800 | C79: peajes | D79: 44960
B80: -800 | C80: adelanto
B81: 800 | C81: PEAJES | D81: 44965
B82: -800 | C82: ADELANTO
B83: 800 | C83: peajes | D83: 44970
B84: -800 | C84: adelanto
B85: 800 | C85: PEAJES | D85: 44975
B86: -800 | C86: adelanto | D86: 44975
B87: 800 | C87: peajes | D87: 44992
B88: -800 | C88: adelanto
B89: 2400 | C89: peajes | D89: 45019
B90: -2400 | C90: adelanto
B91: 800 | C91: peajes | D91: 45030
B92: -800 | C92: adelanto | D92: 45030
B93: 800 | C93: peajes
B94: -800 | C94: adelanto
B95: 800 | C95: peajes | D95: 45044
B96: -800 | C96: adelanto
B97: 800 | C97: peajes | D97: 45052
B98: -800 | C98: adelanto | D98: 45052
B99: 600 | C99: peajes | D99: 45079
B100: -600 | C100: adelanto
B101: 1200 | C101: peajes
B102: -1200 | C102: adelanto
B103: -330 | C103: ANTEC PENAL | D103: 45132
B104: 1200 | C104: peajes
B105: -900 | C105: adelanto | D105: 45136
B106: 1800 | C106: agua desmineralizada y copia llave | D106: 45146
B107: -1800 | C107: adelanto
B108: 800 | C108: peajes | D108: 45182
B109: -800 | C109: adelanto | D109: 45182
B110: 800 | C110: peajes | D110: 45196
B111: -800 | C111: adelanto
B112: 4500 | C112: PEAJES | D112: 45593
B113: -15000 | C113: adelanto | D113: 45593
B114: -1000 | C114: ANTEC PENAL | D114: 45831
B115: 15300 | C115: peajes | D115: 45840
B116: -15500 | C116: adelanto | D116: 45840
B117: =SUM(B56:B116) -> -13770 | C117: 45840

Sheet CANCELA
A2: DIA | B2: SALE DE | C2: LLEGA A | D2: KM REC | E2: TN COM 29 | F2: TN ESC 35 | G2: TN ESC 37,5 | H2: REMITO Nº | I2: MATERIAL | J2: KM VACIOS | K2: $
A30: 46112 | B30: IBICUY | C30: AÑELO | D30: 1430 | H30: 118339 | I30: YPF
A31: 46114 | B31: AÑELO | C31: L. NEGRA | D31: 940 | H31: VACIO
A32: 46116 | B32: L. NEGRA | C32: CAMPANA | D32: 420 | F32: 34.35 | H32: 618966 | I32: HOLCIM
A33: 46119 | B33: CAMPANA | C33: IBICUY | D33: 85 | H33: VACIO
A34: 46120 | B34: IBICUY | C34: BAJO DEL TORO | D34: 1560 | H34: 119854 | I34: YPF TORO
A35: 46122 | B35: BAJO DEL TORO | C35: L. NEGRA | D35: 1070 | H35: VACIO
A36: 46125 | B36: L. NEGRA | C36: CAMPANA | D36: 430 | H36: 293735 | I36: PIEDRA
A37: 46126 | B37: CAMPANA | C37: IBICUY | D37: 100 | H37: VACIO
A38: 46126 | B38: IBICUY | C38: BAJO DEL TORO | D38: 1470 | H38: 121071 | I38: YPF TORO 5
A39: 46128 | B39: BAJO DEL TORO | C39: L. NEGRA | D39: 1070 | H39: VACIO
A40: 46133 | B40: L. NEGRA | C40: J. C. PAZ | D40: 390 | H40: 767372
A41: 46134 | B41: J. C. PAZ | C41: IBICUY | D41: 170 | H41: VACIO
A42: 46135 | B42: IBICUY | C42: BAJO DEL TORO | D42: 1560 | H42: 122522 | I42: YPF TORO
A43: 46137 | B43: BAJO DEL TORO | C43: L. NEGRA | D43: 1070 | H43: VACIO
A44: 46139 | B44: L. NEGRA | C44: CAMPANA | D44: 430 | F44: 34.74 | H44: 294667 | I44: PIEDRA
A45: 46140 | B45: CAMPANA | C45: IBICUY | D45: 100 | H45: VACIO
A46: 46140 | B46: IBICUY | C46: AÑELO | D46: 1430 | H46: 123588 | I46: YPF
D47: 30 A LAS 23,59
D49: =SUM(D3:D48) -> 13725 | F49: =AVERAGE(F3:F47) -> 34.545 | J49: =SUM(J3:J48) -> 0 | K49: =SUM(K3:K48) -> 0
B51: -2000 | C51: 44634
B52: 1350 | C52: PEAJES | D52: 44643
B53: -1400 | C53: ADELANTO
B54: 800 | C54: peajes | D54: 44656
B55: -800 | C55: ADELANTO | D55: 44656
B56: 2400 | C56: GOMERIA
B57: -2400 | C57: ADELANTO
B58: 560 | C58: PEAJES | D58: 44714
B59: -600 | C59: ADELANTO
B60: 280 | C60: PEAJES | D60: 44716
B61: -200 | C61: ADELANTO
B62: 680 | C62: PEAJES | D62: 44735
B63: -700 | C63: ADELANTO
B64: 480 | C64: PEAJES | D64: 44750
B65: -500 | C65: ADELANTO | D65: 44750
B66: 3080 | C66: GOMERIA
B67: -3070 | C67: ADELANTO
B68: 480 | C68: PEAJES | D68: 44820
B69: -500 | C69: ADELANTO
B70: 1500 | C70: gomeria
B71: 960 | C71: PEAJES
B72: -2500 | C72: delanto
B73: 280 | C73: PEAJES | D73: 44848
B74: 1900 | C74: GOMERIA
B75: -2100 | C75: ADELANTO
B76: 480 | C76: PEAJES | D76: 44854
B77: -500 | C77: ADELANTO
B78: 800 | C78: PEAJES | D78: 44873
B79: 800 | C79: PEAJES | D79: 44879
B80: 1500 | C80: GOMERIA
B81: -3100 | C81: ADELANTO | D81: 44880
B82: 800 | C82: PEAJES | D82: 44889
B83: -800 | C83: ADELANTO | D83: 44889
B84: 800 | C84: PEAJES | D84: 44931
B85: -800 | C85: ADELANTO | D85: 44931
B86: 800 | C86: PEAJES | D86: 44939
B87: -800 | C87: ADELANTO
B88: 800 | C88: PEAJES | D88: 44994
B89: -800 | C89: ADELANTO | D89: 44994
B90: 3200 | C90: PEAJES
B91: -3200 | C91: ADELANTO
B92: 6400 | C92: PEAJES | D92: 45037
B93: -6400 | C93: ADELANTO | D93: 45037
B94: 800 | C94: PEAJERS
B95: -800 | C95: ADELANTO | D95: 45048
B96: 400 | C96: PEAJES | D96: 45057
B97: -400 | C97: ADELANTO | D97: 45057
B98: 1600 | C98: PEAJES | D98: 45150
B99: -1600 | C99: ADELANTO
B100: 2000 | C100: PEAJES
B101: -2000 | C101: ADELANTO
B102: 1600 | C102: PEAJES | D102: 45169
B103: -1600 | C103: ADELANTO
B104: -300 | C104: ANTEC PENAL | D104: 45260
B105: 1000 | C105: PEAJE | D105: 45321
B106: -1000 | C106: ADELANTO
B107: 1200 | C107: PEAJES | D107: 45412
B108: -9000 | C108: ADELANTO | D108: 45412
B109: -50000 | C109: ADELANTO | D109: 45513
B110: 4700 | C110: PEAJES
B111: -1000 | C111: ANTEC PENAL | D111: 45981
B112: =SUM(B51:B111) -> -56440 | C112: 45981

Sheet COSENTINO
D1: NYU 936
A2: DIA | B2: SALE DE | C2: LLEGA A | D2: KM REC | E2: TN COM 29 | F2: TN ESC 35 | G2: TN ESC 37,5 | H2: REMITO Nº | I2: MATERIAL | J2: KM VACIOS | K2: $
A27: 46116 | B27: L. NEGRA | C27: CAMPANA | D27: 420 | F27: 36.07 | H27: 618981 | I27: HOLCIM
A28: 46118 | B28: CAMPANA | C28: IBICUY | D28: 85 | H28: VACIO
A29: 46119 | B29: IBICUY | C29: AÑELO | D29: 1430 | H29: 119679 | I29: YPF
A30: 46121 | B30: AÑELO | C30: L. NEGRA | D30: 940 | H30: VACIO
A31: 46123 | B31: L. NEGRA | C31: CASEROS | D31: 380 | F31: 36 | H31: 2701178 | I31: TRAMONTANA | K31: 738000
A32: 46125 | B32: CASEROS | C32: LOMASER | D32: 130 | H32: VACIO
A33: 46125 | B33: LOMASER | C33: ROSARIO | D33: 340 | H33: 895970
A34: 46126 | B34: ROSARIO | C34: L. NEGRA | D34: 550 | H34: PALLETS | I34: LOS PAGARON | K34: 370454.21
A35: 46127 | B35: L. NEGRA | C35: ZAPALA | D35: 1010 | F35: 36.36 | H35: 619730 | I35: CLINKER
A36: 46128 | B36: ZAPALA | C36: ALLEN | D36: 240 | H36: VACIO
A37: 46128 | B37: ALLEN | C37: L. NEGRA | D37: 820 | F37: 32.7 | H37: 189647 | I37: YESO LOMA
A38: 46133 | B38: L. NEGRA | C38: ZAPALA | D38: 1010 | F38: 36.51 | H38: 620076 | I38: CLINKER
A39: 46134 | B39: ZAPALA | C39: ALLEN | D39: 240 | H39: VACIO
A40: 46135 | B40: ALLEN | C40: L. NEGRA | D40: 820 | F40: 35.7 | H40: 189829 | I40: YESO LOMA
A41: 46136 | B41: L. NEGRA | C41: CAMPANA | D41: 430 | H41: 293735 | I41: PIEDRA
A42: 46139 | B42: CAMPANA | C42: IBICUY | D42: 100 | H42: VACIO
A43: 46139 | B43: IBICUY | C43: BAJO DEL TORO | D43: 1560 | H43: ???? | I43: YPF TORO
D44: 30 A LAS 15
J45: =SUM(J3:J44) -> 0
D46: =SUM(D3:D45) -> 10505 | G46: =AVERAGE(G3:G44) -> #DIV/0! | K46: =SUM(K3:K45) -> 1108454.2
B49: -2000 | C49: ADELANTO
B50: 1080 | C50: PEAJES | D50: 44761
B51: -1100 | C51: ADELANTO
B52: 280 | C52: PEAJES | D52: 44768
B53: -300 | C53: ADELANTO | D53: 44768
B54: 400 | C54: PEAJES
B55: -400 | C55: ADELANTO
B56: 480 | C56: PEAJES | D56: 44803
B57: -510 | C57: ADELANTO
B58: 480 | C58: PEAJES | D58: 44828
B59: -500 | C59: ADELANTO | D59: 44828
B60: 800 | C60: PEAJES | D60: 44865
B61: -800 | C61: ADELANTO | D61: 44865
B62: 400 | C62: PEAJES | D62: 44867
B63: -400 | C63: ADELANTO | D63: 44867
B64: 900 | C64: PEAJES | D64: 44957
B65: -900 | C65: ADELANTO
B66: 400 | C66: PEAJES | D66: 44985
B67: -400 | C67: ADELANTO | D67: 44985
B68: 600 | C68: PEAJES | D68: 45082
B69: -600 | C69: ADELANTO | D69: 45082
B70: 600 | C70: PEAJES | D70: 45093
B71: -600 | C71: ADELANTO | D71: 45093
B72: 800 | C72: PEAJES | D72: 45182
B73: -800 | C73: ADELANTO | D73: 45182
B74: -300 | C74: ANTEC PENAL | D74: 45195
B75: 800 | C75: PEAJES | D75: 45206
B76: -800 | C76: ADELANTO
B77: -15000 | C77: ADELANTO | D77: transferencia
B78: 14200 | C78: peajes | D78: 45357
B79: -7000 | C79: ADELANTO | D79: 45357
B80: 10700 | C80: PEAJES | D80: 45533
B81: -10700 | C81: ADELANTO | D81: 45533
B82: 10700 | C82: PEAJES | D82: 45544
B83: -10700 | C83: adelanto
B84: 11100 | C84: PEAJES
B85: -11100 | C85: ADELANTO
B86: 11100 | C86: PEAJES | D86: 45610
B87: -11100
B88: 11100 | C88: PEAJES | D88: 45616
B89: -11100 | C89: ADELANTO
B90: 17900 | C90: PEAJES
B91: -18000 | C91: ADELANTO | D91: 45666
B92: 31200 | C92: PEAJES
B93: -31200 | C93: ADELANTO | D93: 45756
B94: 2000 | C94: PEAJE | D94: 45908
B95: -2000 | C95: ADELANTO
B96: -1000 | C96: ANTEC PENAL | D96: 45908
B97: =SUM(B48:B96) -> -11290 | C97: 45908

Sheet SALTO MAXIMILIANO
D1: NYU 936
A2: DIA | B2: SALE DE | C2: LLEGA A | D2: KM REC | E2: TN COM 29 | F2: TN ESC 35 | G2: TN ESC 37,5 | H2: REMITO Nº | I2: MATERIAL | J2: KM VACIOS | K2: $
A17: 46081 | B17: AÑELO | C17: L. NEGRA | D17: 980 | H17: VACIO
A18: 46084 | B18: L. NEGRA | C18: M. CENTRAL | D18: 340 | G18: 36.82 | H18: 291406 | I18: FENOMIX
A19: 46084 | B19: M. CENTRAL | C19: IBICUY | D19: 190 | H19: VACIO
A20: 46085 | B20: IBICUY | C20: AÑELO | D20: 1340 | H20: 112834 | I20: BANDUR YPF 5
A21: 46087 | B21: AÑELO | C21: ALLEN | D21: 180 | H21: VACIO
A22: 46087 | B22: ALLEN | C22: L. NEGRA | D22: 820 | H22: 187818 | I22: YESO LOMA
A23: 46088 | B23: L. NEGRA | C23: M. CENTRAL | D23: 340 | G23: 36.76 | H23: 291704 | I23: FENOMIX
A24: 46091 | B24: M. CENTRAL | C24: IBICUY | D24: 190 | H24: VACIO
A25: 46092 | B25: IBICUY | C25: ABBOT | D25: 230 | F25: SIGUIO | G25: COSENTINO | H25: COMISARIA | I25: YPF
D26: VER A | E26: PARTIR DEL 12
D28: =SUM(D3:D27) -> 4610 | G28: =AVERAGE(G3:G26) -> 36.79 | J28: =SUM(J3:J27) -> 0 | K28: =SUM(K3:K27) -> 0
B36: -2000 | C36: ADELANTO | XFD36: =SUM(A36:XFC36) -> -2000
B37: 1200 | C37: peajes
B38: -1200 | C38: adelanto
B39: 1200 | C39: PEAJES | D39: 45066
B40: -1200 | C40: ADELANTO | D40: 45066
B41: 1200 | C41: peajes
B42: -1200 | C42: adelanto | D42: 45098
B43: 1200 | C43: peajes | D43: 45108
B44: -1200 | C44: adelanto | D44: 45108
B45: 2400 | C45: PEAJES | D45: 45117
B46: -2400 | C46: adelanto | D46: 45117
B47: 1200 | C47: PEAJES | D47: 45122
B48: -1200 | C48: adelanto
B49: 1600 | C49: peajes
B50: 1600 | C50: PEAJES | D50: 45164
B51: -3200 | C51: adelanto | D51: 45164
B52: 800 | C52: PEAJES | D52: 45210
B53: -800 | C53: ADELANTO
B54: -30000 | C54: adelanto | D54: 45306
B55: 16500 | C55: PEAJES | D55: 45309
B56: 7000 | C56: gomeria | D56: 45366
B57: 4000 | C57: GOMERIA | D57: 45404
B58: -4000 | C58: adelanto | D58: 45404
B59: -1000 | C59: ANT. PENALES | D59: 45499
B60: 4700 | C60: peajes | D60: 45586
B61: -5000 | C61: adelanto | D61: 45586
B62: 65900 | C62: peajes
B63: -66000 | C63: adelanto
B64: 1800 | C64: PEAJE | D64: 45894
B65: -2000 | C65: ADELANTO | D65: 45894
B66: 4000 | C66: PEAJE | D66: 45922
B67: -4000 | C67: ADELANTO | D67: 45922
B69: =SUM(B36:B67) -> -10100 | C69: 45922

Sheet RANDAZZO
D1: NYU 936
A2: DIA | B2: SALE DE | C2: LLEGA A | D2: KM REC | E2: TN COM 29 | F2: TN ESC 35 | G2: TN ESC 37,5 | H2: REMITO Nº | I2: MATERIAL | J2: KM VACIOS | K2: $
A34: 46111 | B34: L. NEGRA | C34: CERRITO | D34: 900 | F34: 37.2 | H34: 764216
A35: 46116 | B35: CERRITO | C35: RAMALLO | D35: 330 | H35: VACIO
A36: 46117 | B36: RAMALLO | C36: LOMASER | D36: 300 | H36: 278637
A37: 46119 | B37: LOMASER | C37: RAMALLO | D37: 300 | H37: 895080
A38: 46119 | B38: RAMALLO | C38: LOMASER | D38: 300 | H38: 278702
A39: 46121 | B39: LOMASER | C39: PUNTA ALTA | D39: 610 | H39: 895444 | K39: 1076388.4
A40: 46122 | B40: PUNTA ALTA | C40: L. NEGRA | D40: 310 | F40: 25.99 | H40: VACIO
A41: 46122 | B41: L. NEGRA | C41: SOLA | D41: 360 | F41: 37.42 | H41: 765733 | K41: 1242661.4
A42: 46125 | B42: SOLA | C42: LOMASER | D42: 80 | H42: VACIO
A43: 46126 | B43: LOMASER | C43: P. TIROL | D43: 1000 | F43: 36.41 | H43: 896126
A44: 46128 | B44: P. TIROL | C44: RAMALLO | D44: 820 | H44: VACIO
A45: 46128 | B45: RAMALLO | C45: SOLA | D45: 240 | F45: 34.91 | H45: 279079 | I45: ESCORIA
A46: 46129 | B46: SOLA | C46: LOMASER | D46: 80 | H46: VACIO
A47: 46129 | B47: LOMASER | C47: PUNTA ALTA | D47: 610 | F47: 35.98 | H47: 89745
A48: 46130 | B48: PUNTA ALTA | C48: L. NEGRA | D48: 310 | H48: VACIO
A49: 46132 | B49: L. NEGRA | C49: SOLA | D49: 360 | F49: 36.36 | H49: 767151
A50: 46133 | B50: SOLA | C50: LOMASER | D50: 70 | H50: VACIO
A51: 46134 | B51: LOMASER | C51: RAMALLO | D51: 300 | H51: 897401
A52: 46135 | B52: RAMALLO | C52: SOLA | D52: 240 | F52: 35.52 | H52: 279313 | I52: ESCORIA
A53: 46136 | B53: SOLA | C53: LOMASER | D53: 80 | H53: VACIO
A54: 46139 | B54: LOMASER | C54: RAMALLO | D54: 300 | H54: 898094
A55: 46140 | B55: RAMALLO | C55: LOMASER | D55: 300 | H55: 279475 | I55: ESCORIA
A56: 46140 | B56: LOMASER | C56: L. NEGRA | D56: 300 | H56: VACIO
A57: 46141 | B57: L. NEGRA | C57: NAVARRO | D57: 300 | H57: ????
A58: 46142 | B58: NAVARRO | C58: LOMASER | D58: 90 | H58: VACIO
D59: 30 A LAS 14
D61: =SUM(D3:D60) -> 8890 | F61: =AVERAGE(F3:F59) -> 34.97375 | J61: =SUM(J3:J60) -> 0 | K61: =SUM(K3:K60) -> 2319049.8
B69: -2000 | C69: adelanto
B70: 2000 | C70: PEAJES | D70: 45152
B71: -2000 | C71: ADELANTO
B72: 2000 | C72: PEAJES | D72: 45197
B73: -2000 | C73: ADELANTO
B74: 1000 | C74: PEAJES | D74: 45304
B75: -1000 | C75: ADELANTO | D75: 45304
B76: 21000 | C76: PEAJES | D76: 45350
B77: -21000 | C77: ADELANTO
B78: 6800 | C78: peajes | D78: 45404
B79: -12000 | C79: adelanto | D79: 45404
B80: 18400 | C80: PEAJES
B81: -22000 | C81: adelanto | D81: 45434
B82: 7200 | C82: peajes | D82: 45472
B83: -8000 | C83: adelanto | D83: 45472
B84: 7400 | C84: peajes | D84: 45491
B85: -7400 | C85: adelanto
B86: 7400 | C86: PEAJES | D86: 45506
B87: -7000 | C87: adelanto | D87: 45506
B88: 10700 | C88: PEAJES
B89: -11000 | C89: adelanto
B90: 15400 | C90: PEAJES | D90: 45552
B91: -15400 | C91: adelanto
B92: 10900 | C92: PEAJES
B93: -11000 | C93: adelanto | D93: 45566
B94: 10900 | C94: PEAJES | D94: 45575
B95: -10900 | C95: adelanto
B96: 16000 | C96: PEAJES | D96: 45632
B97: -16000 | C97: adelanto | D97: 45632
B98: 11300 | C98: PEAJES
B99: -11300 | C99: adelanto | D99: 45644
B100: 16600 | C100: PEAJES | D100: 45702
B101: -16500 | C101: adelanto | D101: 45702
B102: 6400 | C102: PEAJES | D102: 45743
B103: 16000 | C103: GOMERIA
B104: -33000 | C104: adelanto
B105: 8000 | C105: PEAJES | D105: 45786
B106: -8000 | C106: ADELANTO
B107: 16000 | C107: PEAJES | D107: 45792
B108: -16000 | C108: ADELANTO
B109: 16000 | C109: PEAJES | D109: 45812
B110: -16000 | C110: ADELANTO
B111: 28400 | C111: PEAJES | D111: 45827
B112: -29000 | C112: ADELANTO
B113: 24000 | C113: PEAJES | D113: 45840
B114: -24000 | C114: adelanto | D114: 45840
B115: 24000 | C115: PEAJES | D115: 45862
B116: -24000 | C116: adelanto | D116: 45862
B117: 8000 | C117: PEAJE | D117: 45870
B118: -8000 | C118: ADELANTO | D118: 45870
B119: 9200 | C119: peaje | D119: 45891
B120: -9200 | C120: adelanto | D120: 45891
B121: 9200 | C121: PEAJE | D121: 45936
B122: -9200 | C122: ADELANTO
B123: 9200 | C123: PEAJE | D123: 45952
B124: -9200 | C124: ADELANTO
B125: 18400 | C125: PEAJES | D125: 45978
B126: -18400 | C126: ADELANTO
B127: 9200 | C127: PEAJE | D127: 45999
B128: -9200 | C128: ADELANTO
B129: =SUM(B69:B128) -> -22700 | C129: 45999

Sheet ACOSTA
D1: NYU 936
A2: DIA | B2: SALE DE | C2: LLEGA A | D2: KM REC | E2: TN COM 29 | F2: TN ESC 35 | G2: TN ESC 37,5 | H2: REMITO Nº | I2: MATERIAL | J2: KM VACIOS | K2: $
E3: AGREGAR 1 PERMANENCIA
A25: 46112 | B25: LOMASER | C25: RAMALLO | D25: 290 | H25: 894585
A26: 46113 | B26: RAMALLO | C26: LOMASER | D26: 290 | H26: 278583 | I26: ESCORIA
A27: 46118 | B27: LOMASER | C27: RAMALLO | D27: 290 | H27: 894946
A28: 46118 | B28: RAMALLO | C28: LOMASER | D28: 290 | H28: 278667 | I28: ESCORIA
A29: 46120 | B29: LOMASER | C29: RAMALLO | D29: 290 | H29: 895275
A30: 46121 | B30: RAMALLO | C30: LOMASER | D30: 290 | H30: 278758 | I30: ESCORIA
A31: 46125 | B31: LOMASER | C31: ESCOBAR | D31: 140 | F31: 35.35 | H31: 895827
A32: 46125 | B32: ESCOBAR | C32: RAMALLO | D32: 185 | H32: VACIO
A33: 46125 | B33: RAMALLO | C33: URIBURU | D33: 80 | H33: 278931
A34: 46126 | B34: URIBURU | C34: RAMALLO | D34: 80 | H34: VACIO
A35: 46127 | B35: RAMALLO | C35: LOMASER | D35: 290 | H35: 279016 | I35: ESCORIA | K35: 1229913
A36: 46129 | B36: LOMASER | C36: RAMALLO | D36: 290 | H36: 896695
A37: 46129 | B37: RAMALLO | C37: LOMASER | D37: 290 | H37: 279144 | I37: ESCORIA
A38: 46132 | B38: LOMASER | C38: RAMALLO | D38: 290 | H38: 896970
A39: 46132 | B39: RAMALLO | C39: LOMASER | D39: 290 | H39: 279212 | I39: ESCORIA
A40: 46134 | B40: LOMASER | C40: TORCUATO | D40: 140 | H40: 897403
A41: 46135 | B41: TORCUATO | C41: LOMASER | D41: 140 | H41: VACIO
A42: 46136 | B42: LOMASER | C42: RAMALLO | D42: 290 | H42: 897802
A43: 46136 | B43: RAMALLO | C43: LOMASER | D43: 290 | H43: 279392 | I43: ESCORIA
A44: 46140 | B44: LOMASER | C44: L. NEGRA | D44: 300 | H44: VACIO
A45: 46140 | B45: L. NEGRA | C45: M. DEL PLATA | D45: 320 | F45: 34.9 | H45: 768607
A46: 46141 | B46: M. DEL PLATA | C46: L. NEGRA | D46: 320 | H46: VACIO
D47: 30 A LAS 16
D49: =SUM(D3:D48) -> 5475 | F49: =AVERAGE(F3:F47) -> 35.125 | J49: =SUM(J3:J48) -> 0 | K49: =SUM(K3:K48) -> 1229913
B57: -2000 | C57: adelanto
B58: 2000 | C58: PEAJES | D58: 45152
B59: -2000 | C59: ADELANTO
B60: 800 | C60: PEAJES | D60: 45205
B61: -800 | C61: adelanto
B62: -1000 | C62: ANTEC PENAL | D62: 45373
B63: 3100 | C63: peajes | D63: 45381
B64: -3100 | C64: adelanto | D64: 45381
B65: -1000 | C65: ANTEC PENAL | D65: 45733
B66: 10200 | C66: PEAJES | D66: 45838
B67: -10200 | C67: adelanto | D67: 45838
B68: 2000 | C68: PEAJES | D68: 45987
B69: -18000 | C69: adelanto
B70: =SUM(B56:B69) -> -20000 | C70: 45987

Sheet RUPPEL
D1: NYU 936
A2: DIA | B2: SALE DE | C2: LLEGA A | D2: KM REC | E2: TN COM 29 | F2: TN ESC 35 | G2: TN ESC 37,5 | H2: REMITO Nº | I2: MATERIAL | J2: KM VACIOS | K2: $
A29: 46112 | B29: ALLEN | C29: L. NEGRA | D29: 820 | F29: 34.6 | H29: 189318 | I29: YESO LOMA
A30: 46118 | B30: L. NEGRA | C30: CAMPANA | D30: 420 | F30: 34.71 | H30: 619049 | I30: HOLCIM
A31: 46119 | B31: CAMPANA | C31: IBICUY | D31: 85 | H31: VACIO
A32: 46120 | B32: IBICUY | C32: BAJO DEL TORO | D32: 1560 | H32: 119871 | I32: YPF TORO 5
A33: 46122 | B33: BAJO DEL TORO | C33: L. NEGRA | D33: 1070 | H33: VACIO
A34: 46125 | B34: L. NEGRA | C34: CAMPANA | D34: 430 | H34: 293730 | I34: PIEDRA
A35: 46126 | B35: CAMPANA | C35: IBICUY | D35: 100 | H35: VACIO
A36: 46127 | B36: IBICUY | C36: BAJO DEL TORO | D36: 1560 | H36: 81423 | I36: YPF TORO
A37: 46129 | B37: BAJO DEL TORO | C37: L. NEGRA | D37: 1070 | H37: VACIO
A38: 46132 | B38: L. NEGRA | C38: SAN EFRNANDO | D38: 420 | H38: ???? | I38: FENOMIX
A39: 46133 | B39: SAN FERNANDO | C39: IBICUY | D39: 150 | H39: VACIO
A40: 46133 | B40: IBICUY | C40: SAND POINT | D40: 1430 | H40: 122161 | I40: SAN POINT YPF
A41: 46135 | B41: SAND POINT | C41: ALLEN | D41: 200 | H41: VACIO
A42: 46136 | B42: ALLEN | C42: L. NEGRA | D42: 820 | F42: 34.4 | H42: 189853 | I42: YESO LOMA
A43: 46137 | B43: L. NEGRA | C43: ZAPALA | D43: 1010 | H43: 620324 | I43: CLINKER
A44: 46140 | B44: ZAPALA | C44: ALLEN | D44: 240 | H44: VACIO
A45: 46140 | B45: ALLEN | C45: L. NEGRA | D45: 820 | F45: 34.1 | H45: 190029 | I45: YESO LOMA
A46: 46141 | B46: L. NEGRA | C46: TORCUATO | D46: 400 | H46: ???? | I46: PIEDRA
A47: 46142 | B47: TORCUATO | C47: IBICUY | D47: 150 | H47: VACIO
D48: 30 A LAS 20
D50: =SUM(D3:D49) -> 12755 | F50: =AVERAGE(F3:F48) -> 34.4525 | J50: =SUM(J3:J49) -> 0 | K50: =SUM(K3:K49) -> 0
B58: -2000 | C58: adelanto
B59: 10400 | C59: PEAJES
B60: -20000 | C60: adelanto
B61: 18800 | C61: PEAJES
B62: 8000 | C62: GOMERIA
B63: -35000 | C63: adelanto
B64: 9800 | C64: PEAJES
B65: -10000 | C65: adelanto | D65: 45427
B66: -80000 | C66: adelanto
B67: 9000 | C67: gomeria
B68: 43600 | C68: PEAJES
B69: 48608 | C69: aceite
B70: -13000 | C70: adelanto
B72: =SUM(B57:B70) -> -11792 | C72: 45595

Sheet RUCKERT
D1: NYU 936
A2: DIA | B2: SALE DE | C2: LLEGA A | D2: KM REC | E2: TN COM 29 | F2: TN ESC 35 | G2: TN ESC 37,5 | H2: REMITO Nº | I2: MATERIAL | J2: KM VACIOS | K2: $
A24: 46112 | B24: L. NEGRA | C24: ADELA 6 | D24: 1030 | F24: CARGO | G24: PAREDEZ | H24: 118258 | I24: ADELA YPF | J24: AG821WX
A25: 46113 | B25: ADELA 6 | C25: L. NEGRA | D25: 970 | H25: VACIO
A26: 46118 | B26: L. NEGRA | C26: CAMPANA | D26: 420 | F26: 34.96 | H26: 619086 | I26: CLINKER | J26: AB742XZ
A27: 46120 | B27: CAMPANA | C27: SIDERAR | D27: 150 | H27: VACIO
A28: 46120 | B28: SIDERAR | C28: RAMALLO | D28: 10 | H28: 1063933 | I28: CORTO
A29: 46120 | B29: RAMALLO | C29: SIDERAR | D29: 10 | H29: VACIO
A30: 46120 | B30: SIDERAR | C30: RAMALLO | D30: 10 | H30: 1063961 | I30: CORTO
A31: 46120 | B31: RAMALLO | C31: SIDERAR | D31: 10 | H31: VACIO
A32: 46121 | B32: SIDERAR | C32: L. NEGRA | D32: 500 | F32: 35.29 | H32: 1064169 | I32: LODO
A33: 46122 | B33: L. NEGRA | C33: SAN FERNANDO | D33: 420 | F33: 35.02 | H33: 293676 | I33: FENOMIX | K33: 630360
A34: 46125 | B34: SAN FERNANDO | C34: LOMASER | D34: 150 | H34: VACIO
A35: 46126 | B35: LOMASER | C35: BENAVIDEZ | D35: 140 | H35: 896058
A36: 46126 | B36: BENAVIDEZ | C36: CAMPANA | D36: 50 | H36: VACIO
A37: 46126 | B37: CAMPANA | C37: CATAMARCA | D37: 990 | F37: 35.2 | H37: 153189 | I37: SIDERCA
A38: 46127 | B38: CATAMARCA | C38: ALTA GRACIA | D38: 430 | H38: 504029
A39: 46127 | B39: ALTA GRACIA | C39: PAMPAYASTA | D39: 150 | H39: VACIO
A40: 46128 | B40: PAMPAYASTA | C40: ROSARIO | D40: 340 | F40: 35.08 | H40: TKT 21595
A41: 46129 | B41: ROSARIO | C41: RAMALLO | D41: 80 | H41: VACIO
A42: 46129 | B42: RAMALLO | C42: L. NEGRA | D42: 500 | F42: 35.03 | H42: 1065603 | I42: LODO
A43: 46132 | B43: L. NEGRA | C43: M. DEL PLATA | D43: 320 | H43: 767198
A44: 46133 | B44: M. DEL PLATA | C44: L. NEGRA | D44: 320 | H44: VACIO
A45: 46134 | B45: L. NEGRA | C45: CAMPANA | D45: 430 | F45: 34.72 | H45: 294312 | I45: PIEDRA
A46: 46135 | B46: CAMPANA | C46: IBICUY | D46: 100 | H46: VACIO
A47: 46138 | B47: IBICUY | C47: PRINGLES | D47: 650 | G47: VOLVIO A TALLER | H47: SCANIA
A48: 46138 | B48: PRINGLES | C48: HINOJO | D48: 180 | H48: SCANIA
A49: 46140 | B49: HINOJO | C49: BAJO DEL TORO | D49: 1060 | H49: ???? | I49: YPF TORO
D50: 1 A LAS 10
D52: =SUM(D3:D51) -> 9420 | F52: =AVERAGE(F3:F50) -> 35.042857 | J52: =SUM(J3:J51) -> 0 | K52: =SUM(K3:K50) -> 630360
B60: -2000 | C60: adelanto
B61: 800 | C61: PEAJE | D61: 45175
B62: -800 | C62: ADELANTO
B63: 6100 | C63: PEAJES | D63: 45206 | E63: $600 DE UN PEAJE
B64: -6100 | C64: ADELANTO
B65: -1000 | C65: ANT. PENALES | D65: 45769
B66: =SUM(B59:B65) -> -3000 | C66: 45769

Sheet FERNANDEZ
D1: NYU 936
A2: DIA | B2: SALE DE | C2: LLEGA A | D2: KM REC | E2: TN COM 29 | F2: TN ESC 35 | G2: TN ESC 37,5 | H2: REMITO Nº | I2: MATERIAL | J2: KM VACIOS | K2: $
A3: 46112 | B3: L. NEGRA | C3: M. DEL PLATA | D3: 320 | F3: 35.48 | H3: 764442 | K3: 1257428.9
A4: 46113 | B4: M. DEL PLATA | C4: L. NEGRA | D4: 320 | H4: VACIO
A5: 46116 | B5: L. NEGRA | C5: B. DE ESCOBAR | D5: 430 | F5: 35.48 | H5: 764713 | K5: 1657729.6
A6: 46118 | B6: B. ESCOBAR | C6: LOMASER | D6: 140 | H6: VACIO
A7: 46119 | B7: LOMASER | C7: RAMALLO | D7: 300 | H7: 895125
A8: 46120 | B8: RAMALLO | C8: LOMASER | D8: 300 | H8: 278708 | I8: ESCORIA
A9: 46121 | B9: LOMASER | C9: TORTUGUITAS | D9: 140 | F9: 35.12 | H9: 895440 | K9: 391358.32
A10: 46121 | B10: TORTUGUITAS | C10: L. NEGRA | D10: 410 | H10: VACIO
A11: 46122 | B11: L. NEGRA | C11: M. DEL PLATA | D11: 320 | F11: 35.18 | H11: 765662
A12: 46125 | B12: M. DEL PLATA | C12: L. NEGRA | D12: 320 | H12: VACIO
A13: 46125 | B13: L. NEGRA | C13: OLAVARRIA | D13: 40 | F13: 34.78 | H13: 766135
A14: 46126 | B14: OLAVARRIA | C14: L. NEGRA | D14: 40 | H14: VACIO
A15: 46126 | B15: L. NEGRA | C15: OLAVARRIA | D15: 40 | F15: 34.92 | H15: 766290
A16: 46127 | B16: OLAVARRIA | C16: L. NEGRA | D16: 40 | H16: VACIO
A17: 46127 | B17: L. NEGRA | C17: CERRITO | D17: 900 | F17: 35.22 | H17: 766490
A18: 46128 | B18: CERRITO | C18: RAMALLO | D18: 330 | H18: VACIO
A19: 46129 | B19: RAMALLO | C19: LOMASER | D19: 300 | H19: 766490
A20: 46130 | B20: LOMASER | C20: L. NEGRA | D20: 300 | H20: VACIO
A21: 46134 | B21: L. NEGRA | C21: B. DE ESCOBAR | D21: 430 | F21: 35.32 | H21: 767540
A22: 46135 | B22: B. ESCOBAR | C22: L. NEGRA | D22: 430 | H22: VACIO
A23: 46136 | B23: L. NEGRA | C23: B. JUAREZ | D23: 120 | F23: 35.38 | H23: 767868
A24: 46136 | B24: B. JUAREZ | C24: OLAVARRIA | D24: 120 | F24: DECARGO 5 TN | G24: EN OLAVARRIA | H24: VACIO
A25: 46136 | B25: OLAVARRIA | C25: L. NEGRA | D25: 20 | H25: VACIO
A26: 46139 | B26: L. NEGRA | C26: LA PLATA | D26: 350 | H26: ????
A27: 46140 | B27: LA PLATA | C27: LOMASER | D27: 100 | H27: VACIO
A28: 46140 | B28: LOMASER | C28: RAMALLO | D28: 300 | H28: ????
A29: 46141 | B29: RAMALLO | C29: LOMASER | D29: 300 | H29: ??? | I29: ESCORIA
A30: 46141 | B30: LOMASER | C30: SOLA | D30: 80 | H30: ????
A31: 46142 | B31: SOLA | C31: L. NEGRA | D31: 360 | H31: VACIO
D32: 30 A LAS 23
D34: =SUM(D3:D33) -> 7600 | F34: =AVERAGE(F3:F32) -> 35.208889 | J34: =SUM(J3:J32) -> 0 | K34: =SUM(K3:K33) -> 3306516.8
B42: -2000 | C42: adelanto
B43: 800 | C43: PEAJE | D43: 45175
B44: -800 | C44: ADELANTO
B45: 1200 | C45: peajes | D45: 45182
B46: 2600 | C46: PEAJES
B47: -2600 | C47: adelanto
B48: -100000 | C48: adelanto | D48: 45530
B49: 39400 | C49: PEAJE
B50: -39400 | C50: ADELANTO | D50: 45538
B51: 30300 | C51: peajes | D51: 45545
B52: -30300 | C52: adelanto | D52: 45545
B53: 18000 | C53: PEAJES | D53: 45560
B54: 82500 | C54: DEV. CAJA | D54: 45560
B55: 8000 | C55: PEAJE | D55: 45856
B56: -8000 | C56: ADELANTO
B57: -1000 | C57: ANT. PENALES | D57: 45934
D58: 45934
B59: =SUM(B42:B57) -> -1300 | C59: 45934

Sheet MAZZEI
D1: NYU 936
A2: DIA | B2: SALE DE | C2: LLEGA A | D2: KM REC | E2: TN COM 29 | F2: TN ESC 35 | G2: TN ESC 37,5 | H2: REMITO Nº | I2: MATERIAL | J2: KM VACIOS | K2: $
A3: 46113 | B3: IBICUY | C3: ADELA 6 | D3: 1450 | H3: 812278 | I3: ADELA YPF
A4: 46114 | B4: ADELA 6 | C4: L. NEGRA | D4: 970 | H4: VACIO
A5: 46116 | B5: L. NEGRA | C5: T. SUAREZ | D5: 330 | H5: 764738 | K5: 891828.5
A6: 46118 | B6: T. SUAREZ | C6: LOMASER | D6: 25 | H6: VACIO
A7: 46118 | B7: LOMASER | C7: ESCOBAR | D7: 140 | H7: 894958 | K7: 362310.8
A8: 46119 | B8: ESCOBAR | C8: IBICUY | D8: 120 | H8: VACIO
A9: 46120 | B9: IBICUY | C9: BAJO DEL TORO | D9: 1560 | H9: 119766 | I9: YPF TORO
A10: 46122 | B10: BAJO DEL TORO | C10: L. NEGRA | D10: 1070 | H10: VACIO
A11: 46125 | B11: L. NEGRA | C11: CAMPANA | D11: 430 | H11: 293731 | I11: PIEDRA
A12: 46126 | B12: CAMPANA | C12: IBICUY | D12: 100 | H12: VACIO
A13: 46126 | B13: IBICUY | C13: BAJO DEL TORO | D13: 1560 | H13: 121082 | I13: YPF TORO
A14: 46129 | B14: BAJO DEL TORO | C14: ALLEN | D14: 270 | H14: VACIO
A15: 46129 | B15: ALLEN | C15: L. NEGRA | D15: 820 | F15: 33.9 | H15: 189658 | I15: YESO LOMA
A16: 46130 | B16: L. NEGRA | C16: SAN FERNANDO | D16: 420 | F16: 34.2 | H16: 294152 | I16: FENOMIX
A17: 46132 | B17: S. FERNANDO | C17: IBICUY | D17: 150 | H17: VACIO
A18: 46133 | B18: IBICUY | C18: AÑELO | D18: 1430 | H18: 122155 | I18: YPF
A19: 46136 | B19: AÑELO | C19: L. NEGRA | D19: 940 | H19: VACIO
A20: 46139 | B20: L. NEGRA | C20: B. BLANCA | D20: 310 | H20: 768430
A21: 46140 | B21: B. BLANCA | C21: L. NEGRA | D21: 310 | H21: VACIO
A22: 46140 | B22: L. NEGRA | C22: GUATRACHE | D22: 400 | H22: ????
A23: 46141 | B23: GUATRACHE | C23: L. NEGRA | D23: 400 | H23: VACIO
A24: 46141 | B24: L. NEGRA | C24: GRAL. PICO | D24: 450 | H24: ????
A25: 46142 | B25: GRAL. PICO | C25: L. NEGRA | D25: 450 | H25: VACIO
D26: 30 A LAS 21
D28: =SUM(D3:D27) -> 14105 | F28: =AVERAGE(F3:F26) -> 34.05 | J28: =SUM(J3:J26) -> 0 | K28: =SUM(K3:K26) -> 1254139.3
B36: -2000 | C36: adelanto
B37: 800 | C37: PEAJE
B38: -800 | C38: ADELANTO | D38: 45260
B39: 3800 | C39: PEAJE
B40: -3800 | C40: ADELANTO | D40: 45506
B41: 56800 | C41: PEAJES | D41: 45786
B42: -56800 | C42: ADELANTO
B43: -18000 | C43: CAJA
B44: 10200 | C44: PEAJES
B45: -10200 | C45: adelanto | D45: 45835
B46: -1000 | C46: ANT. PENALES | D46: 45868
B47: 3600 | C47: PEAJES
B48: -4000
B49: 4000 | C49: PEAJES | D49: 45910
B50: -4000 | C50: ADELANTO
B51: =SUM(B36:B50) -> -21400 | C51: 45910

Sheet GUILFOR
D1: NYU 936
A2: DIA | B2: SALE DE | C2: LLEGA A | D2: KM REC | E2: TN COM 29 | F2: TN ESC 35 | G2: TN ESC 37,5 | H2: REMITO Nº | I2: MATERIAL | J2: KM VACIOS | K2: $
A3: 46113 | B3: ZAPALA | C3: L. NEGRA | D3: 1010 | H3: VACIO
A4: 46116 | B4: L. NEGRA | C4: DOCK SUD | D4: 370 | G4: 37.62 | H4: 293338 | I4: PIEDRA | K4: 962813.93
A5: 46120 | B5: DOCK SUD | C5: IBICUY | D5: 180 | H5: VACIO
A6: 46120 | B6: IBICUY | C6: BAJO DEL TORO | D6: 1560 | H6: 120015 | I6: YPF TORO
A7: 46123 | B7: BAJO DEL TORO | C7: L. NEGRA | D7: 1070 | H7: VACIO
A8: 46126 | B8: L. NEGRA | C8: ZAPALA | D8: 1010 | G8: 37 | H8: 619625 | I8: CLINKER
A9: 46127 | B9: ZAPALA | C9: ALLEN | D9: 240 | H9: VACIO
A10: 46128 | B10: ALLEN | C10: L. NEGRA | D10: 820 | G10: 36.5 | H10: 189585 | I10: YESO LOMA
A11: 46132 | B11: L. NEGRA | C11: RIO CUARTO | D11: 750 | H11: 767234
A12: 46133 | B12: RIO CUARTO | C12: PAMPAYASTA | D12: 150 | H12: VACIO
A13: 46133 | B13: PAMPAYASTA | C13: ROSARIO | D13: 340 | G13: 36.26 | H13: TKT 21813
A14: 46134 | B14: ROSARIO | C14: RAMALLO | D14: 80 | H14: VACIO
A15: 46134 | B15: RAMALLO | C15: L. NEGRA | D15: 500 | G15: 37.09 | H15: 1066519 | I15: ESCORIA
A16: 46135 | B16: L. NEGRA | C16: CAMPANA | D16: 430 | G16: 36.82 | H16: 294459 | I16: PIEDRA
A17: 46136 | B17: CAMPANA | C17: RAMALLO | D17: 150 | H17: VACIO
A18: 46137 | B18: RAMALLO | C18: L. NEGRA | D18: 500 | G18: 37.11 | H18: 1067037 | I18: ESCORIA
A19: 46140 | B19: L. NEGRA | C19: RADA TILLY | D19: 1450 | H19: 768546
D20: 30 A LAS 12
D22: =SUM(D3:D21) -> 10610 | G22: =AVERAGE(G3:G20) -> 36.914286 | J22: =SUM(J3:J21) -> 0 | K22: =SUM(K3:K21) -> 962813.93
B30: -20000 | C30: adelanto
B31: 9100 | C31: PEAJES | D31: 45302
B32: -9100 | C32: ADELANTO
B33: -1000 | C33: ANT. PENALES | D33: 45519
B34: 60800 | C34: PEAJES | D34: 45835
B35: -60800 | C35: adelanto | D35: 45835
B36: 5100 | C36: PEAJES | D36: 45846
B37: -5000 | C37: ADELANTO
B38: -1000 | C38: ANT. PENALES | D38: 45868
B39: 1000 | C39: PEAJES | D39: 45905
B40: -1000 | C40: ADELANTO
B41: 4400 | C41: PEAJES | D41: 46091
B42: -4000 | C42: ADELANTO
B43: =SUM(B29:B42) -> -21500 | C43: 46091

Sheet SURRA
D1: NYU 936
A2: DIA | B2: SALE DE | C2: LLEGA A | D2: KM REC | E2: TN COM 29 | F2: TN ESC 35 | G2: TN ESC 37,5 | H2: REMITO Nº | I2: MATERIAL | J2: KM VACIOS | K2: $
D3: VACACIONES | E3: 01/04 AL 05/04
A4: 46119 | B4: L. NEGRA | C4: CAMPANA | D4: 420 | F4: 34.68 | H4: 619112 | I4: CLINKER
A5: 46120 | B5: CAMPANA | C5: SIDERAR | D5: 150 | H5: VACIO
A6: 46120 | B6: SIDERAR | C6: RAMALLO | D6: 10 | H6: 1063937 | I6: CORTO
A7: 46120 | B7: RAMALLO | C7: SIDERAR | D7: 10 | H7: VACIO
A8: 46120 | B8: SIDERAR | C8: RAMALLO | D8: 10 | H8: 1063964 | I8: CORTO
A9: 46120 | B9: RAMALLO | C9: SIDERAR | D9: 10 | H9: VACIO
A10: 46121 | B10: SIDERAR | C10: L. NEGRA | D10: 500 | H10: 1064170 | I10: LODO
A11: 46122 | B11: L. NEGRA | C11: CASEROS | D11: 380 | H11: 619420 | I11: TRAMONTANA | K11: 697000
A12: 46125 | B12: CASEROS | C12: LOMASER | D12: 130 | H12: VACIO
A13: 46125 | B13: LOMASER | C13: J. C. PAZ | D13: 120 | H13: 895892
A14: 46125 | B14: J. C. PAZ | C14: LOMASER | D14: 120 | H14: VACIO
A15: 46125 | B15: LOMASER | C15: ZAPALA | D15: 1300 | H15: 5259 | I15: PALLETS | K15: 1510866.7
A16: 46128 | B16: ZAPALA | C16: ALLEN | D16: 240 | H16: VACIO
A17: 46128 | B17: ALLEN | C17: L. NEGRA | D17: 820 | F17: 34.2 | H17: 189638 | I17: YESO LOMA
A18: 46133 | B18: L. NEGRA | C18: ZAPALA | D18: 1010 | F18: 34.3 | H18: 620074 | I18: CLINKER
A19: 46135 | B19: ZAPALA | C19: ALLEN | D19: 240 | H19: VACIO
A20: 46135 | B20: ALLEN | C20: L. NEGRA | D20: 820 | F20: 34 | H20: 189841 | I20: YESO LOMA
A21: 46136 | B21: L. NEGRA | C21: TORCUATO | D21: 400 | F21: 34.68 | H21: 294500 | I21: PIEDRA
A22: 46139 | B22: TORCUATO | C22: IBICUY | D22: 150 | H22: VACIO
A23: 46140 | B23: IBICUY | C23: BAJO DEL TORO | D23: 1560 | H23: 123426 | I23: YPF TORO
D24: 30 A LAS 15 | H24: VACIO
D26: =SUM(D3:D25) -> 8400 | F26: =AVERAGE(F3:F24) -> 34.372 | J26: =SUM(J3:J25) -> 0 | K26: =SUM(K3:K25) -> 2207866.7
B34: -2000 | C34: adelanto
B35: -30000 | C35: ADELANTO | D35: 45351
B36: 7300 | C36: PEAJES | D36: 45359
B37: 10200 | C37: PEAJES | D37: 45838
B38: -10200 | D38: 45838
B41: =SUM(B33:B40) -> -24700 | C41: 45838

Sheet GRASSI
D1: NYU 936
A2: DIA | B2: SALE DE | C2: LLEGA A | D2: KM REC | E2: TN COM 29 | F2: TN ESC 35 | G2: TN ESC 37,5 | H2: REMITO Nº | I2: MATERIAL | J2: KM VACIOS | K2: $
A3: 46113 | B3: L. NEGRA | C3: M. CENTRAL | D3: 340 | F3: 34.72 | H3: 293228 | I3: FENOMIX | K3: 624960
A4: 46118 | B4: M. CENTRAL | C4: IBICUY | D4: 190 | H4: VACIO
A5: 46118 | B5: IBICUY | C5: BAJO DEL TORO | D5: 1660 | H5: 81420 | I5: YPF TORO
A6: 46121 | B6: BAJO DEL TORO | C6: L. NEGRA | D6: 1070 | H6: VACIO
A7: 46123 | B7: L. NEGRA | C7: ZAPALA | D7: 1010 | F7: 34.78 | H7: 619461 | I7: CLINKER | K7: 2284208.5
A8: 46125 | B8: ZAPALA | C8: ALLEN | D8: 240 | H8: VACIO
A9: 46125 | B9: ALLEN | C9: L. NEGRA | D9: 820 | F9: 34.8 | H9: 189456 | I9: YESO LOMA
A10: 46126 | B10: L. NEGRA | C10: CAMPANA | D10: 420 | F10: 35.25 | H10: 619655 | I10: CLINKER
A11: 46127 | B11: CAMPANA | C11: SIDERAR | D11: 150 | H11: VACIO
A12: 46127 | B12: SIDERAR | C12: L. NEGRA | D12: 500 | F12: 34.91 | H12: 1065174 | I12: ESCORIA
A13: 46128 | B13: L. NEGRA | C13: ZAPALA | D13: 1010 | F13: 34.82 | H13: 619784 | I13: CLINKER
A14: 46129 | B14: ZAPALA | C14: ALLEN | D14: 240 | H14: VACIO
A15: 46129 | B15: ALLEN | C15: L. NEGRA | D15: 820 | F15: 33.5 | H15: 189659 | I15: YESO LOMA
A16: 46130 | B16: L. NEGRA | C16: SAN FERNANDO | D16: 420 | H16: ???? | I16: FENOMIX
A17: 46132 | B17: S. FERNANDO | C17: IBICUY | D17: 150 | H17: VACIO
A18: 46133 | B18: IBICUY | C18: BAJO DEL TORO | D18: 1560 | H18: 122153 | I18: YPF TORO
A19: 46135 | B19: BAJO DEL TORO | C19: L. NEGRA | D19: 1070 | H19: VACIO
A20: 46137 | B20: L. NEGRA | C20: SAN FERNANDO | D20: 420 | F20: 35.06 | H20: 294527 | I20: FENOMIX
A21: 46140 | B21: S. FERNANDO | C21: IBICUY | D21: 150 | H21: VACIO
A22: 46140 | B22: IBICUY | C22: BAJO DEL TORO | D22: 1560 | H22: ???? | I22: YPF TORO
D23: 1 A LAS 6
D25: =SUM(D3:D24) -> 13800 | F25: =AVERAGE(F3:F23) -> 34.73 | J25: =SUM(J3:J24) -> 0 | K25: =SUM(K3:K24) -> 2909168.5
B33: -10000 | C33: adelanto
B34: 2400 | C34: PEAJES
B35: -2500 | C35: ADELANTO | D35: 45408
B36: 12000 | C36: PEAJES | D36: 45434
B37: -12000 | C37: ADELANTO
B38: 21500 | C38: PEAJES
B39: -21500 | C39: ADELANTO
B40: 17500 | C40: PEAJES | D40: 45526
B41: -17500 | C41: adelanto | D41: 45526
B42: -1000 | C42: ant. Penales | D42: 45680
B43: 37700 | C43: PEAJES | D43: 45866
B44: -38000 | C44: adelanto | D44: 45866
B45: =SUM(B32:B44) -> -11400 | C45: 45866

Sheet ORLANDO
D1: NYU 936
A2: DIA | B2: SALE DE | C2: LLEGA A | D2: KM REC | E2: TN COM 29 | F2: TN ESC 35 | G2: TN ESC 37,5 | H2: REMITO Nº | I2: MATERIAL | J2: KM VACIOS | K2: $
A3: 46113 | B3: L. NEGRA | C3: CAMPANA | D3: 420 | F3: 34.37 | H3: 618924 | I3: HOLCIM
A4: 46116 | B4: CAMPANA | C4: IBICUY | D4: 85 | H4: VACIO
A5: 46116 | B5: IBICUY | C5: BAJO DEL TORO | D5: 1460 | H5: 81348 | I5: YPF TORO 5
A6: 46118 | B6: BAJO DEL TORO | C6: L. NEGRA | D6: 1070 | H6: VACIO
A7: 46120 | B7: L. NEGRA | C7: BARKER | D7: 180 | H7: 765183
A8: 46121 | B8: BARKER | C8: L. NEGRA | D8: 220 | H8: 33295 | I8: ARCAMIN
A9: 46121 | B9: L. NEGRA | C9: FATIMA | D9: 390 | H9: 293586 | I9: PIEDRA
A10: 46122 | B10: FATIMA | C10: IBICUY | D10: 130 | H10: VACIO
A11: 46122 | B11: IBICUY | C11: AÑELO | D11: 1430 | H11: 120334 | I11: YPF
A12: 46125 | B12: AÑELO | C12: ALLEN | D12: 160 | H12: VACIO
A13: 46125 | B13: ALLEN | C13: L. NEGRA | D13: 820 | F13: 35.6 | H13: 189435 | I13: YESO LOMA
A14: 46127 | B14: L. NEGRA | C14: M. DEL PLATA | D14: 320 | H14: 766334
A15: 46128 | B15: M. DEL PLATA | C15: L. NEGRA | D15: 320 | H15: PALLETS | I15: 1 CLIENTE
A16: 46129 | B16: L. NEGRA | C16: ZAPALA | D16: 1010 | F16: 34.44 | H16: 619867 | I16: CLINKER
A17: 46132 | B17: ZAPALA | C17: ALLEN | D17: 240 | H17: VACIO
A18: 46132 | B18: ALLEN | C18: ZAPALA | D18: 240 | F18: 34.1 | H18: 189737 | I18: CORTO YESO
A19: 46133 | B19: ZAPALA | C19: ALLEN | D19: 240 | H19: VACIO
A20: 46133 | B20: ALLEN | C20: L. NEGRA | D20: 820 | F20: 33.8 | H20: 189789 | I20: YESO LOMA
A21: 46135 | B21: L. NEGRA | C21: CAMPANA | D21: 430 | F21: 34.96 | H21: 294382 | I21: PIEDRA
A22: 46136 | B22: CAMPANA | C22: RAMALLO | D22: 150 | H22: VACIO
A23: 46137 | B23: RAMALLO | C23: L. NEGRA | D23: 500 | F23: 35.14 | H23: 1067043 | I23: LODO
A24: 46139 | B24: L. NEGRA | C24: CAMPANA | D24: 430 | F24: 34.64 | H24: 294,,, | I24: PIEDRA
A25: 46140 | B25: CAMPANA | C25: IBICUY | D25: 100 | H25: VACIO
A26: 46140 | B26: IBICUY | C26: BAJO DEL TORO | D26: 1560 | H26: ???? | I26: YPF TORO
D27: 1 ALAS 23
D29: =SUM(D3:D28) -> 12725 | F29: =AVERAGE(F3:F27) -> 34.63125 | J29: =SUM(J3:J28) -> 0 | K29: =SUM(K3:K28) -> 0
B37: -10000 | C37: adelanto
B38: 23000 | C38: PEAJES | D38: 45435
B39: -23000 | C39: ADELANTO
B40: 3600 | C40: PEAJE
B41: -3600 | C41: ADELANTO | D41: 45447
B42: 4700 | C42: PEAJE | D42: 45586
B43: -4700 | C43: ADELANTO
B44: 1800 | C44: PASADA X MERC CENTRAL | D44: 45902
B45: -2000 | C45: ADELANTO
B46: 4400 | C46: PEAJE | D46: 46091
B47: -15000 | C47: ADELANTO
B48: =SUM(B36:B47) -> -20800 | C48: 46091

Sheet ALVAREZ
D1: NYU 936
A2: DIA | B2: SALE DE | C2: LLEGA A | D2: KM REC | E2: TN COM 29 | F2: TN ESC 35 | G2: TN ESC 37,5 | H2: REMITO Nº | I2: MATERIAL | J2: KM VACIOS | K2: $
A3: 46113 | B3: ADELA 6 | C3: L. NEGRA | D3: 1080 | H3: VACIO
A4: 46119 | B4: L. NEGRA | C4: BAHIA BLANCA | D4: 340 | F4: CARGO A TRELEW | G4: QUEDO EN TALLER | I4: SIGUIO ARCUBY
A5: 46120 | B5: BAHIA BLANCA | C5: L. NEGRA | D5: 340 | H5: VACIO
A6: 46122 | B6: L. NEGRA | C6: FATIMA | D6: 390 | H6: 293675 | I6: PIEDRA
A7: 46125 | B7: FATIMA | C7: IBICUY | D7: 130 | H7: VACIO
A8: 46125 | B8: IBICUY | C8: BAJO DEL TORO | D8: 1560 | H8: 120844 | I8: YPF TORO
A9: 46128 | B9: BAJO DEL TORO | C9: ALLEN | D9: 270 | H9: VACIO
A10: 46128 | B10: ALLEN | C10: L. NEGRA | D10: 820 | F10: 33.5 | H10: 189562 | I10: YESO LOMA
A11: 46133 | B11: L. NEGRA | C11: ZAPALA | D11: 1010 | F11: 35.51 | H11: 620077 | I11: CLINKER
A12: 46135 | B12: ZAPALA | C12: ALLEN | D12: 240 | H12: VACIO
A13: 46136 | B13: ALLEN | C13: L. NEGRA | D13: 820 | F13: 36 | H13: 189885 | I13: YESO LOMA
A14: 46139 | B14: L. NEGRA | C14: M. DEL PLATA | D14: 320 | H14: 768379
A15: 46140 | B15: M. DEL PLATA | C15: L. NEGRA | D15: 320 | H15: VERRR
A16: 46141 | B16: L. NEGRA | C16: ZAPALA | D16: 1010 | H16: 620513 | I16: CLINKER
A17: 46142 | B17: ZAPALA | C17: ALLEN | D17: 240 | H17: VACIO
D18: 30 A LAS 16
D20: =SUM(D3:D19) -> 8890 | G20: =AVERAGE(G3:G18) -> #DIV/0! | J20: =SUM(J3:J19) -> 0 | K20: =SUM(K3:K19) -> 0
B28: -10000 | C28: adelanto
B29: 3600 | C29: PEAJES
B30: -4000 | C30: adelanto
B31: 10000 | C31: GOMERIA | D31: 45483
B32: -10000 | C32: ADELANTO | D32: 45483
B33: -2400 | C33: ANTEC PENAL | D33: 45488
B34: 37700 | C34: PEAJES
B35: -37700 | C35: ADELANTO
B36: 60800 | C36: peajes | D36: 45829
B37: -60800 | C37: peajes | D37: 45829
B38: 4000 | C38: PEAJES | D38: 45917
B39: -4000 | C39: ADELANTO
B40: 25000 | C40: GOMERIA | D40: 46091
B41: 2200 | C41: PEAJES
B42: -35000 | C42: ADELANTO
B43: =SUM(B27:B42) -> -20600 | C43: 46091

Sheet  MARTINEZ NICO
D1: NYU 936
A2: DIA | B2: SALE DE | C2: LLEGA A | D2: KM REC | E2: TN COM 29 | F2: TN ESC 35 | G2: TN ESC 37,5 | H2: REMITO Nº | I2: MATERIAL | J2: KM VACIOS | K2: $
A3: 46113 | B3: AÑELO | C3: L. NEGRA | D3: 940 | H3: VACIO
A4: 46119 | B4: L. NEGRA | C4: CAMPANA | D4: 420 | F4: 35.36 | H4: 619111 | I4: CLINKER
A5: 46119 | B5: CAMPANA | C5: SIDERAR | D5: 150 | H5: VACIO
A6: 46119 | B6: SIDERAR | C6: RAMALLO | D6: 10 | H6: 1063808 | I6: CORTO
A7: 46119 | B7: RAMALLO | C7: SIDERAR | D7: 10 | H7: VACIO
A8: 46119 | B8: SIDERAR | C8: RAMALLO | D8: 10 | H8: 1063834 | I8: CORTO
A9: 46120 | B9: RAMALLO | C9: SIDERAR | D9: 10 | H9: VACIO
A10: 46120 | B10: SIDERAR | C10: RAMALLO | D10: 10 | H10: 1063900 | I10: CORTO
A11: 46120 | B11: RAMALLO | C11: V. CONSTITUCION | D11: 40 | H11: VACIO
A12: 46120 | B12: V. CONSTITUCION | C12: CATAMARCA | D12: 830 | F12: 35.82 | H12: 924028 | I12: ACINDAR | K12: 1568022.3
A13: 46121 | B13: CATAMARCA | C13: CORDOBA | D13: 380 | H13: 503516 | K13: 1057200.1
A14: 46122 | B14: CORDOBA | C14: MALAGUEÑO | D14: 50 | H14: VACIO
A15: 46122 | B15: MALAGUEÑO | C15: ROSARIO | D15: 430 | F15: 34.82 | H15: 303302 | I15: PIEDRA
A16: 46123 | B16: ROSARIO | C16: RAMALLO | D16: 80 | H16: VACIO
A17: 46123 | B17: RAMALLO | C17: L. NEGRA | D17: 500 | F17: 35.04 | H17: 1064651 | I17: LODO
A18: 46125 | B18: L. NEGRA | C18: CAMPANA | D18: 420 | F18: 35.11 | H18: 619580 | I18: CLINKER
A19: 46126 | B19: CAMPANA | C19: SIDERAR | D19: 150 | H19: VACIO
A20: 46126 | B20: SIDERAR | C20: L. NEGRA | D20: 500 | F20: 35.65 | H20: 1064946 | I20: LODO
A21: 46127 | B21: L. NEGRA | C21: ZAPALA | D21: 1010 | F21: 34.96 | H21: 619694 | I21: CLINKER
A22: 46128 | B22: ZAPALA | C22: ALLEN | D22: 240 | H22: VACIO
A23: 46128 | B23: ALLEN | C23: L. NEGRA | D23: 820 | F23: 34.7 | H23: 189642 | I23: YESO LOMA
A24: 46129 | B24: L. NEGRA | C24: SAN EFRNANDO | D24: 420 | F24: 34.98 | H24: 294162 | I24: FENOMIX
A25: 46132 | B25: SAN FERNANDO | C25: IBICUY | D25: 150 | H25: VACIO
A26: 46133 | B26: IBICUY | C26: AÑELO | D26: 1430 | H26: 122152 | I26: YPF
A27: 46135 | B27: AÑELO | C27: L. NEGRA | D27: 940 | H27: VACIO
A28: 46137 | B28: L. NEGRA | C28: ZAPALA | D28: 1010 | F28: 36.21 | H28: 620320 | I28: CLINKER
A29: 46139 | B29: ZAPALA | C29: ALLEN | D29: 240 | H29: VACIO
A30: 46140 | B30: ALLEN | C30: L. NEGRA | D30: 820 | F30: 35.2 | H30: 189986 | I30: YESO LOMA
A31: 46141 | B31: L. NEGRA | C31: ZAPALA | D31: 1010 | F31: 35.39 | H31: 620535 | I31: CLINKER
A32: 46142 | B32: ZAPALA | C32: ALLEN | D32: 240 | H32: VACIO
D33: 30 A LAS 20
D35: =SUM(D3:D34) -> 13270 | F35: =AVERAGE(F3:F33) -> 35.27 | J35: =SUM(J3:J34) -> 0 | K35: =SUM(K3:K34) -> 2625222.4
B43: -10000 | C43: adelanto
B44: 8100 | C44: PEAJES
B45: -8100 | C45: ADELANTO
B46: -1000 | C46: ANT. PENALES | D46: 45558
B47: 24500 | C47: PEAJES | D47: 45562
B48: -24500 | C48: adelanto | D48: 45562
B49: 5000 | C49: PEAJES
B50: =SUM(B42:B49) -> -6000 | C50: 45836

Sheet URBAN
D1: NYU 936
A2: DIA | B2: SALE DE | C2: LLEGA A | D2: KM REC | E2: TN COM 29 | F2: TN ESC 35 | G2: TN ESC 37,5 | H2: REMITO Nº | I2: MATERIAL | J2: KM VACIOS | K2: $
A3: 46111 | B3: IBICUY | C3: ADELA 6 | D3: 1490 | H3: 118243 | I3: ADELA YPF | J3: NYU938
A4: 46114 | B4: ADELA 6 | C4: L. NEGRA | D4: 970 | H4: VACIO
A5: 46126 | B5: L. NEGRA | C5: ZAPALA | D5: 1030 | F5: 33.15 | H5: 619652 | I5: CLINKER | J5: AE601GF
A6: 46128 | B6: ZAPALA | C6: ALLEN | D6: 240 | H6: VACIO
A7: 46128 | B7: ALLEN | C7: L. NEGRA | D7: 820 | F7: 33.7 | H7: 189639 | I7: YESO LOMA
A8: 46133 | B8: L. NEGRA | C8: ZAPALA | D8: 1030 | F8: 32.21 | H8: 620075 | I8: CLINKER
A9: 46135 | B9: ZAPALA | C9: ALLEN | D9: 240 | H9: VACIO
A10: 46135 | B10: ALLEN | C10: L. NEGRA | D10: 820 | F10: 34.5 | H10: 189845 | I10: YESO LOMA
A11: 46139 | B11: L. NEGRA | C11: BAJO DEL TORO | D11: 1070 | G11: CARGO CARTASSO | H11: ???? | I11: YPF DE TORO | J11: NYU938
A12: 46141 | B12: BAJO DEL TORO | C12: L. NEGRA | D12: 1070 | H12: VACIO
D13: 31 A LAS 17
D15: =SUM(D3:D14) -> 8780 | F15: =AVERAGE(F3:F13) -> 33.39 | J15: =SUM(J3:J14) -> 0 | K15: =SUM(K3:K14) -> 0
B23: -10000 | C23: adelanto
B24: 8750 | C24: peajes
B25: -8750 | C25: adelanto | D25: 45478
B26: 5600 | C26: peajes
B27: -5600 | C27: adelanto | D27: 45831
B28: 15300 | C28: peajes
B29: -26000 | C29: adelanto | D29: 45835
B30: -1000 | C30: ANTEC PENAL | D30: 45835
B31: =SUM(B22:B30) -> -21700 | C31: 45835

Sheet CEJAS DIEGO
A2: DIA | B2: SALE DE | C2: LLEGA A | D2: KM REC | E2: TN COM 29 | F2: TN ESC 35 | G2: TN ESC 37,5 | H2: REMITO Nº | I2: MATERIAL | J2: KM VACIOS | K2: $
A3: 46116 | B3: L. NEGRA | C3: CAMPANA | D3: 420 | F3: 35.42 | H3: 618989 | I3: HOLCIM
A4: 46118 | B4: CAMPANA | C4: IBICUY | D4: 85 | H4: VACIO
A5: 46119 | B5: IBICUY | C5: BAJO DEL TORO | D5: 1460 | H5: 119644 | I5: YPF TORO 5
A6: 46121 | B6: BAJO DEL TORO | C6: L. NEGRA | D6: 1070 | H6: VACIO
A7: 46123 | B7: L. NEGRA | C7: ZAPALA | D7: 1010 | F7: 34.85 | H7: 619512 | I7: CLINKER
A8: 46126 | B8: ZAPALA | C8: ALLEN | D8: 230 | H8: VACIO
A9: 46126 | B9: ALLEN | C9: L. NEGRA | D9: 820 | F9: 35.5 | H9: 189471 | I9: YESO LOMA
A10: 46127 | B10: L. NEGRA | C10: CAMPANA | D10: 430 | H10: 293897 | I10: PIEDRA
A11: 46129 | B11: CAMPANA | C11: SIDERAR | D11: 150 | H11: VACIO
A12: 46129 | B12: SIDERAR | C12: L. NEGRA | D12: 500 | F12: 34.41 | H12: 1065645 | I12: ESCORIA
A13: 46132 | B13: L. NEGRA | C13: SAN FERNANDO | D13: 420 | H13: ???? | I13: FENOMIX
A14: 46133 | B14: S. FERNANDO | C14: IBICUY | D14: 150 | H14: VACIO
A15: 46134 | B15: IBICUY | C15: BAJO DEL TORO | D15: 1560 | H15: 122285 | I15: YPF TORO
A16: 46137 | B16: BAJO DEL TORO | C16: L. NEGRA | D16: 1070 | H16: VACIO
A17: 46139 | B17: L. NEGRA | C17: CAMPANA | D17: 430 | H17: 294,,, | I17: PIEDRA
A18: 46140 | B18: CAMPANA | C18: IBICUY | D18: 100 | H18: VACIO
D19: 29 A LAS 14
D21: =SUM(D3:D20) -> 9905 | F21: =AVERAGE(#REF!) -> #REF! | J21: =SUM(J3:J20) -> 0 | K21: =SUM(K3:K20) -> 0
B29: -10000 | C29: adelanto
B30: 8750 | C30: peajes
B31: -8750 | C31: adelanto | D31: 45478
B32: -1000 | C32: ANTEC PENAL | D32: 45666
B36: =SUM(B28:B35) -> -11000 | C36: 45478

Sheet JUAREZ LUIS
D1: NYU 936
A2: DIA | B2: SALE DE | C2: LLEGA A | D2: KM REC | E2: TN COM 29 | F2: TN ESC 35 | G2: TN ESC 37,5 | H2: REMITO Nº | I2: MATERIAL | J2: KM VACIOS | K2: $
A3: 46113 | B3: L. NEGRA | C3: CAMPANA | D3: 420 | F3: 35.5 | H3: 618927 | I3: HOLCIM
A4: 46116 | B4: CAMPANA | C4: IBICUY | D4: 85 | H4: VACIO
A5: 46116 | B5: IBICUY | C5: BAJO DEL TORO | D5: 1560 | H5: 81352 | I5: YPF TORO
A6: 46119 | B6: BAJO DEL TORO | C6: L. NEGRA | D6: 1070 | H6: VACIO
A7: 46120 | B7: L. NEGRA | C7: CAMPANA | D7: 420 | F7: 35.62 | H7: 619310 | I7: HOLCIM
A8: 46122 | B8: CAMPANA | C8: IBICUY | D8: 85 | H8: VACIO
A9: 46123 | B9: IBICUY | C9: BAJO DEL TORO | D9: 1560 | H9: ????? | I9: YPF TORO
A10: 46125 | B10: BAJO DEL TORO | C10: L. NEGRA | D10: 1070 | H10: VACIO
A11: 46129 | B11: L. NEGRA | C11: CASEROS | D11: 380 | H11: ???? | I11: TRAMONTANA
A12: 46132 | B12: CASEROS | C12: IBICUY | D12: 180 | H12: VACIO
A13: 46132 | B13: IBICUY | C13: BAJO DEL TORO | D13: 1560 | H13: 121972 | I13: YPF TORO
A14: 46135 | B14: BAJO DEL TORO | C14: ALLEN | D14: 270 | H14: VACIO
A15: 46135 | B15: ALLEN | C15: L. NEGRA | D15: 820 | F15: 34.6 | H15: 189838 | I15: YESO LOMA
A16: 46136 | B16: L. NEGRA | C16: TORCUATO | D16: 400 | F16: 35.66 | H16: 294502
A17: 46139 | B17: TORCUATO | C17: IBICUY | D17: 150 | H17: VACIO
A18: 46139 | B18: IBICUY | C18: BAJO DEL TORO | D18: 1560 | H18: 123330 | I18: YPF TORO
D19: 30 A LAS 15
D21: =SUM(D3:D20) -> 11590 | F21: =AVERAGE(F3:F19) -> 35.345 | J21: =SUM(J3:J20) -> 0 | K21: =SUM(K3:K20) -> 0
B29: -10000 | C29: adelanto
B30: 8750 | C30: peajes
B31: -8750 | C31: adelanto | D31: 45478
B32: 4700 | C32: PEAJE | D32: 45608
B33: -5000 | C33: ADELANTO
B34: -50000 | C34: 45660
B35: 33200 | C35: PEAJES | D35: 45686
B36: -33000 | C36: adelanto | D36: 45686
B37: 62100 | C37: peajes
B38: -12000 | C38: adelanto | D38: 45698
B39: 5100 | C39: PEAJES
B40: -5100 | C40: adelanto | D40: 45965
B41: =SUM(B28:B40) -> -10000 | C41: 45965

Sheet ARCUBY 
D1: NYU 936
A2: DIA | B2: SALE DE | C2: LLEGA A | D2: KM REC | E2: TN COM 29 | F2: TN ESC 35 | G2: TN ESC 37,5 | H2: REMITO Nº | I2: MATERIAL | J2: KM VACIOS | K2: $
A3: 46113 | B3: MALAGUEÑO | C3: ROSARIO | D3: 430 | F3: 36.28 | H3: LA ELENA | K3: 725600
A4: 46113 | B4: ROSARIO | C4: IBICUY | D4: 300 | H4: VACIO
A5: 46113 | B5: IBICUY | C5: ADELA 6 | D5: 1490 | H5: 118687 | I5: ADELA YPF
A6: 46115 | B6: ADELA 6 | C6: L. NEGRA | D6: 970 | H6: VACIO
A7: 46119 | B7: L. NEGRA | C7: M. DEL PLATA | D7: 320 | H7: 765027
A8: 46120 | B8: M. DEL PLATA | C8: L. NEGRA | D8: 320 | H8: VACIO
A9: 46120 | B9: L. NEGRA | C9: TRELEW | D9: 1050 | F9: CARGO | G9: ALVAREZ | H9: 765085 | I9: Y QUEDO EN TALLER | J9: BAHIA
A10: 46121 | B10: TRELEW | C10: L. NEGRA | D10: 1050 | H10: VACIO
A11: 46123 | B11: L. NEGRA | C11: B. DE ESCOBAR | D11: 430 | H11: 765857
A12: 46125 | B12: B. ESCOBAR | C12: LOMASER | D12: 140 | H12: VACIO
A13: 46125 | B13: LOMASER | C13: RAMALLO | D13: 300 | H13: 895973 | K13: 525418.2
A14: 46126 | B14: RAMALLO | C14: L. NEGRA | D14: 500 | G14: 36.78 | H14: 1064942 | I14: LODO
A15: 46127 | B15: L. NEGRA | C15: ZAPALA | D15: 1010 | G15: 37.44 | H15: 6196693 | I15: CLINKER
A16: 46128 | B16: ZAPALA | C16: ALLEN | D16: 240 | H16: VACIO
A17: 46128 | B17: ALLEN | C17: L. NEGRA | D17: 820 | G17: 33.1 | H17: 189640 | I17: YESO LOMA
E18: LF
D20: =SUM(D3:D19) -> 9370 | G20: =AVERAGE(G3:G18) -> 35.773333 | J20: =SUM(J3:J19) -> 0 | K20: =SUM(K3:K19) -> 1251018.2
B28: -10000 | C28: adelanto
B29: 8750 | C29: peajes
B30: -8750 | C30: adelanto | D30: 45478
B31: -1000 | C31: ANTEC PENAL | D31: 45579
B35: =SUM(B27:B34) -> -11000 | C35: 45579

Sheet DE LIBANO
D1: AB742XZ
A2: DIA | B2: SALE DE | C2: LLEGA A | D2: KM REC | E2: TN COM 29 | F2: TN ESC 35 | G2: TN ESC 37,5 | H2: REMITO Nº | I2: MATERIAL | J2: KM VACIOS | K2: $
A3: 46112 | B3: L. NEGRA | C3: VICTORIA | D3: 430 | F3: 34.72 | H3: 293156 | I3: PIEDRA
A4: 46113 | B4: VICTORIA | C4: IBICUY | D4: 150 | H4: VACIO
A5: 46114 | B5: IBICUY | C5: AÑELO | D5: 1430 | H5: 112934 | I5: YPF RUTA 5
A6: 46115 | B6: AÑELO | C6: L. NEGRA | D6: 940 | H6: VACIO
A7: 46119 | B7: L. NEGRA | C7: I. WHITE | D7: 320 | F7: 34.82 | H7: 293484 | I7: PIEDRA
A8: 46120 | B8: I. WHITE | C8: BARKER | D8: 350 | H8: VACIO
A9: 46120 | B9: BARKER | C9: L. NEGRA | D9: 200 | H9: 182539 | I9: M. ROJO
A10: 46120 | B10: L. NEGRA | C10: TANDIL | D10: 140 | H10: 619289 | K10: 423455.57
A11: 46274 | B11: TANDIL | C11: BARKER | D11: 70 | H11: VACIO
A12: 46121 | B12: BARKER | C12: L. NEGRA | D12: 200 | H12: 182556 | I12: M. ROJO
A13: 46122 | B13: L. NEGRA | C13: CAMPANA | D13: 430 | F13: 35.66 | H13: 619403 | I13: PIEDRA
A14: 46125 | B14: CAMPANA | C14: SIDERAR | D14: 150 | H14: VACIO
A15: 46126 | B15: SIDERAR | C15: L. NEGRA | D15: 500 | F15: 35.27 | H15: 1064902 | I15: LODO | K15: 579519.61
A16: 46127 | B16: L. NEGRA | C16: ARROYITO | D16: 870 | H16: ????
A17: 46219 | B17: ARROYITO | C17: L. NEGRA | D17: 870 | H17: VACIO
A18: 46130 | B18: L. NEGRA | C18: ZAPALA | D18: 1010 | F18: 35.01 | H18: 619980 | I18: CLINKER
A19: 46133 | B19: ZAPALA | C19: ALLEN | D19: 240 | H19: VACIO
A20: 46134 | B20: ALLEN | C20: L. NEGRA | D20: 820 | F20: 34.6 | H20: 189811 | I20: YESO LOMA
A21: 46136 | B21: L. NEGRA | C21: TORCUATO | D21: 400 | H21: 294465 | I21: PIEDRA
A22: 46139 | B22: TORCUATO | C22: IBICUY | D22: 150 | H22: VACIO
A23: 46139 | B23: IBICUY | C23: BAJO DEL TORO | D23: 1560 | H23: ???? | I23: YPF TORO
D24: 30 A LAS 11
D26: =SUM(D3:D25) -> 11230 | F26: =AVERAGE(F3:F24) -> 35.013333 | J26: =SUM(J3:J25) -> 0 | K26: =SUM(K3:K25) -> 1002975.2
B28: -10000
B29: -150000 | C29: ADELANTO | D29: 45812
B30: 47000 | C30: PEAJES | D30: 45819
B31: 103000 | C31: DEVUELVE
B32: -10000 | C32: ADELANTO | D32: 45819
B33: 8900 | C33: PEAJES | D33: 45860
B34: -8900 | C34: ADELANTO
B35: 8900 | C35: PEAJES | D35: 45866
B36: -10000 | C36: 45866
B37: 5100 | C37: PEAJE | D37: 45954
B38: -5100 | C38: ADELANTO
B39: -1000 | C39: ANTEC | D39: 46091
B40: =SUM(B28:B39) -> -22100 | C40: 46091 | M40: 16486.66
M41: 23766.66
M42: 61333
M43: 61333
M44: 9100
M45: 5999.85
M46: 7200
M47: 15000
M48: 14271.33
M49: =SUM(M29:M48) -> 214490.5

Sheet FERNANDEZ FACUNDO
D1: AB742XZ
A2: DIA | B2: SALE DE | C2: LLEGA A | D2: KM REC | E2: TN COM 29 | F2: TN ESC 35 | G2: TN ESC 37,5 | H2: REMITO Nº | I2: MATERIAL | J2: KM VACIOS | K2: $
A3: 46112 | B3: L. NEGRA | C3: TORCUATO | D3: 400 | F3: 35.26 | H3: 293200 | I3: PIEDRA | K3: 723643.75
A4: 46113 | B4: TORCUATO | C4: IBICUY | D4: 145 | H4: VACIO
A5: 46114 | B5: IBICUY | C5: AÑELO | D5: 1430 | H5: 118784 | I5: YPF
A6: 46117 | B6: AÑELO | C6: ALLEN | D6: 180 | H6: VACIO
A7: 46119 | B7: ALLEN | C7: L. NEGRA | D7: 820 | F7: 33.73 | H7: 189369 | I7: C. AVELLANEDA
A8: 46120 | B8: L. NEGRA | C8: M. DEL PLATA | D8: 320 | H8: 765232 | K8: 857189.3
A9: 46121 | B9: M. DEL PLATA | C9: L. NEGRA | D9: 320 | H9: PALLETS | I9: 1 CLIENTE
A10: 46121 | B10: L. NEGRA | C10: FATIMA | D10: 390 | H10: 29588 | I10: PIEDRA
A11: 46122 | B11: FATIMA | C11: IBICUY | D11: 130 | H11: VACIO
A12: 46122 | B12: IBICUY | C12: AÑELO | D12: 1430 | H12: 120360 | I12: YPF
A13: 46126 | B13: AÑELO | C13: ALLEN | D13: 180 | H13: VACIO
A14: 46127 | B14: ALLEN | C14: L. NEGRA | D14: 820 | F14: 34.8 | H14: 189536 | I14: C. AVELLANEDA | K14: 1503186.9
A15: 46129 | B15: L. NEGRA | C15: ZAPALA | D15: 1010 | F15: 34.66 | H15: 619861 | I15: CLINKER
A16: 46132 | B16: ZAPALA | C16: ALLEN | D16: 230 | H16: VACIO
A17: 46132 | B17: ALLEN | C17: L. NEGRA | D17: 820 | F17: 33.9 | H17: 189743 | I17: YESO LOMA
A18: 46134 | B18: L. NEGRA | C18: CAMPANA | D18: 430 | F18: 34.7 | H18: 294336 | I18: PIEDRA
A19: 46135 | B19: CAMPANA | C19: IBICUY | D19: 100 | H19: VACIO
A20: 46136 | B20: IBICUY | C20: AÑELO | D20: 1430 | H20: 122673 | I20: YPF
A21: 46140 | B21: AÑELO | C21: L. NEGRA | D21: 940 | H21: VACIO
A22: 46141 | B22: L. NEGRA | C22: SOLA | D22: 360 | F22: 34.28 | H22: 294824 | I22: PIEDRA
A23: 46142 | B23: SOLA | C23: IBICUY | D23: 180 | H23: VACIO
D24: 30 A LAS 22
D26: =SUM(D3:D25) -> 12065 | F26: =AVERAGE(F3:F24) -> 34.475714 | J26: =SUM(J3:J25) -> 0 | K26: =SUM(K3:K25) -> 3084020
B28: -10000
B29: 9500 | C29: PEAJES
B30: -9500 | C30: ADELANTO | D30: 45574
B31: 19700 | C31: GOMERIA PEAJE
B32: -19700 | C32: ADELANTO
B33: -1000 | C33: ANTEC PENAL | D33: 45931 | M33: 16486.66
B34: 2200 | C34: PEAJES | D34: 46107
B35: =SUM(B28:B34) -> -8800 | C35: 46107 | M35: 23766.66
M36: 61333
M37: 61333
M38: 9100
M39: 5999.85
M40: 7200
M41: 15000
M42: 14271.33
M43: =SUM(M33:M42) -> 214490.5

Sheet PITTANA
D1: AB742XZ
A2: DIA | B2: SALE DE | C2: LLEGA A | D2: KM REC | E2: TN COM 29 | F2: TN ESC 35 | G2: TN ESC 37,5 | H2: REMITO Nº | I2: MATERIAL | J2: KM VACIOS | K2: $
A3: 46111 | B3: L. NEGRA | C3: G. PACHECO | D3: 430 | F3: 34.38 | H3: 764203
A4: 46116 | B4: G. PACHECO | C4: LOMASER | D4: 120 | H4: VACIO
A5: 46116 | B5: LOMASER | C5: TORCUATO | D5: 140 | H5: 894830 | K5: 471464.24
A6: 46118 | B6: TORCUATO | C6: LOMASER | D6: 140 | H6: VACIO
A7: 46118 | B7: LOMASER | C7: TORTUGUITAS | D7: 140 | F7: 34.71 | H7: 895011 | K7: 386789.5
A8: 46119 | B8: TORTUGUITAS | C8: L. NEGRA | D8: 400 | H8: VACIO
A9: 46119 | B9: L. NEGRA | C9: POLVORINES | D9: 410 | F9: 31.5 | H9: 765124 | K9: 1349171.1
A10: 46120 | B10: POLVORINES | C10: LOMASER | D10: 130 | H10: VACIO
A11: 46120 | B11: LOMASER | C11: RAMALLO | D11: 300 | H11: 895309
A12: 46121 | B12: RAMALLO | C12: TORCUATO | D12: 200 | H12: 278779 | I12: ESCORIA
A13: 46121 | B13: TORCUATO | C13: LOMASER | D13: 140 | H13: VACIO
A14: 46121 | B14: LOMASER | C14: SOLA | D14: 80 | H14: 895496
A15: 46122 | B15: SOLA | C15: LOMASER | D15: 80 | H15: VACIO
A16: 46125 | B16: LOMASER | C16: RAMALLO | D16: 300 | H16: 895860
A17: 46125 | B17: RAMALLO | C17: LOMASER | D17: 300 | H17: 278920 | I17: ESCORIA
A18: 46126 | B18: LOMASER | C18: LUJAN | D18: 90 | F18: 34.98 | H18: 896106
A19: 46127 | B19: LUJAN | C19: LOMASER | D19: 90 | H19: VACIO
A20: 46127 | B20: LOMASER | C20: BOSQUES | D20: 105 | F20: 34.8 | H20: 896275
A21: 46127 | B21: BOSQUES | C21: LOMASER | D21: 105 | H21: VACIO
A22: 46128 | B22: LOMASER | C22: RAMALLO | D22: 300 | H22: 896499
A23: 46128 | B23: RAMALLO | C23: LOMASER | D23: 300 | H23: 279083 | I23: ESCORIA
A24: 46129 | B24: LOMASER | C24: URIBURU | D24: 340 | H24: 896739
A25: 46132 | B25: URIBURU | C25: RAMALLO | D25: 80 | H25: VACIO
A26: 46132 | B26: RAMALLO | C26: LOMASER | D26: 300 | H26: 279194 | I26: ESCORIA
A27: 46133 | B27: LOMASER | C27: TORTUGUITAS | D27: 140 | F27: 34.8 | H27: 897155
A28: 46133 | B28: TORTUGUITAS | C28: LOMASER | D28: 140 | H28: VACIO
A29: 46134 | B29: LOMASER | C29: BOSQUES | D29: 105 | F29: 35.02 | H29: 897344
A30: 46134 | B30: BOSQUES | C30: LOMASER | D30: 105 | H30: VACIO
A31: 46135 | B31: LOMASER | C31: ESCOBAR | D31: 140 | F31: 34.86 | H31: 897640
A32: 46136 | B32: ESCOBAR | C32: LOMASER | D32: 140 | H32: VACIO
A33: 46137 | B33: LOMASER | C33: RAMALLO | D33: 300 | H33: 897935
A34: 46139 | B34: RAMALLO | C34: ESCOBAR | D34: 185 | F34: 35.06 | H34: 279424
A35: 46139 | B35: ESCOBAR | C35: LOMASER | D35: 140 | H35: VACIO
A36: 46139 | B36: LOMASER | C36: RAMALLO | D36: 300 | H36: 898146
A37: 46140 | B37: RAMALLO | C37: DARSENA F | D37: 230 | F37: 34.84 | H37: 279468
A38: 46141 | B38: DARSENA F | C38: LOMASER | D38: 80 | H38: VACIO
A39: 46141 | B39: LOMASER | C39: RAMALLO | D39: 300 | H39: 898524
A40: 46142 | B40: RAMALLO | C40: URIBURU | D40: 80 | H40: 279576
A41: 46142 | B41: URIBURU | C41: RAMALLO | D41: 80 | H41: VACIO
A42: 46142 | B42: RAMALLO | C42: LOMASER | D42: 300 | H42: 279591 | I42: ESCORIA
D43: 30 A LAS 19
D45: =SUM(D3:D44) -> 7785 | F45: =AVERAGE(F3:F43) -> 34.495 | J45: =SUM(J3:J44) -> 0 | K45: =SUM(K3:K44) -> 2207424.9
B47: -20000 | D47: 45566
B50: =SUM(B47:B47) -> -20000 | C50: 45566

Sheet PITTANA EUGENIO
D1: AB742XZ
A2: DIA | B2: SALE DE | C2: LLEGA A | D2: KM REC | E2: TN COM 29 | F2: TN ESC 35 | G2: TN ESC 37,5 | H2: REMITO Nº | I2: MATERIAL | J2: KM VACIOS | K2: $
A3: 45807 | B3: L. NEGRA | C3: TIGRE | D3: 420 | F3: 30.36 | H3: 715948
A4: 45839 | B4: TIGRE | C4: LOMASER | D4: 150 | H4: VACIO
A5: 45839 | B5: LOMASER | C5: TORTUGUITAS | D5: 130 | F5: 34.84 | H5: 850707
A6: 45840 | B6: TORTUGUITAS | C6: LOMASER | D6: 130 | H6: VACIO
A7: 45840 | B7: LOMASER | C7: RAMALLO | D7: 290 | F7: 34.9 | H7: 850885
A8: 45840 | B8: RAMALLO | C8: LOMASER | D8: 290 | F8: 34.86 | H8: 266541 | I8: ESCORIA
A9: 45841 | B9: LOMASER | C9: RAMALLO | D9: 290 | F9: 35.08 | H9: 851101
A10: 45842 | B10: RAMALLO | C10: LOMASER | D10: 290 | F10: 34.42 | H10: 266615 | I10: ESCORIA
A11: 45842 | B11: LOMASER | C11: RAMALLO | D11: 290 | F11: 34.86 | H11: 851383
A12: 45843 | B12: RAMALLO | C12: LOMASER | D12: 290 | F12: 35.18 | H12: 266701 | I12: ESCORIA
A13: 45845 | B13: LOMASER | C13: RAMALLO | D13: 290 | F13: 34.98 | H13: 851611
A14: 45845 | B14: RAMALLO | C14: LOMASER | D14: 290 | F14: 34.72 | H14: 266782 | I14: ESCORIA
A15: 45846 | B15: LOMASER | C15: RAMALLO | D15: 290 | F15: 35.01 | H15: 851891
A16: 45846 | B16: RAMALLO | C16: LOMASER | D16: 290 | F16: 35.3 | H16: 266852 | I16: ESCORIA
A17: 45846 | B17: LOMASER | C17: L. NEGRA | D17: 300 | H17: VACIO
A18: 45848 | B18: L. NEGRA | C18: DARSENA F | D18: 380 | F18: 35.08 | H18: 717682
A19: 45849 | B19: DARSENA F | C19: L. NEGRA | D19: 380 | H19: VACIO
A20: 45849 | B20: L. NEGRA | C20: URIBURU | D20: 550 | F20: 35 | H20: 718081
A21: 45850 | B21: URIBURU | C21: RAMALLO | D21: 80 | H21: VACIO
A22: 45850 | B22: RAMALLO | C22: LOMASER | D22: 290 | F22: 35.02 | H22: 267067 | I22: ESCORIA
A23: 45852 | B23: LOMASER | C23: L. NEGRA | D23: 300 | H23: VACIO
A24: 45852 | B24: L. NEGRA | C24: ESCOBAR | D24: 420 | F24: 35.04 | H24: 718602
A25: 45853 | B25: B. DE ESCOBAR | C25: LOMASER | D25: 130 | H25: VACIO
A26: 45854 | B26: LOMASER | C26: TORTUGUITAS | D26: 130 | F26: 34.58 | H26: 853132
A27: 45854 | B27: TORTUGUITAS | C27: LOMASER | D27: 130 | H27: VACIO
A28: 45855 | B28: LOMASER | C28: BOSQUES | D28: 105 | F28: 34.58 | H28: 853341
A29: 45855 | B29: BOSQUES | C29: LOMASER | D29: 105 | H29: VACIO
A30: 45855 | B30: LOMASER | C30: RAMALLO | D30: 290 | H30: 853434
A31: 45856 | B31: RAMALLO | C31: LOMASER | D31: 290 | F31: 34.86 | H31: 267385 | I31: ESCORIA
A32: 45857 | B32: LOMASER | C32: RAMALLO | D32: 290 | F32: 34.83 | H32: 853689
A33: 45859 | B33: RAMALLO | C33: LOMASER | D33: 290 | F33: 35.18 | H33: 267456 | I33: ESCORIA
A34: 45859 | B34: LOMASER | C34: RAMALLO | D34: 290 | F34: 35.14 | H34: 853919
A35: 45860 | B35: RAMALLO | C35: LOMASER | D35: 290 | F35: 35.14 | H35: 267534 | I35: ESCORIA
A36: 45861 | B36: LOMASER | C36: RAMALLO | D36: 290 | F36: 34.91 | H36: 854162
A37: 45861 | B37: RAMALLO | C37: LOMASER | D37: 290 | F37: 35.12 | H37: 267599 | I37: ESCORIA
A38: 45862 | B38: LOMASER | C38: RAMALLO | D38: 290 | F38: 35.13 | H38: 854435
A39: 45862 | B39: RAMALLO | C39: LOMASER | D39: 290 | F39: 34.94 | H39: 267663 | I39: ESCORIA
A40: 45863 | B40: LOMASER | C40: RAMALLO | D40: 290 | F40: 34.98 | H40: 854645
A41: 45863 | B41: RAMALLO | C41: TORCUATO | D41: 200 | F41: 35.22 | H41: 267723 | I41: ESCORIA
A42: 45864 | B42: TORCUATO | C42: LOMASER | D42: 130 | H42: VACIO
A43: 45864 | B43: LOMASER | C43: TORTUGUITAS | D43: 130 | F43: 35.2 | H43: 854962
A44: 45866 | B44: TORTUGUITAS | C44: RAMALLO | D44: 190 | H44: VACIO
A45: 45866 | B45: RAMALLO | C45: URIBURU | D45: 80 | F45: 35.16 | H45: 267825 | I45: ESCORIA
A46: 45866 | B46: URIBURU | C46: RAMALLO | D46: 80 | H46: VACIO
A47: 45867 | B47: RAMALLO | C47: ESCOBAR | D47: 175 | F47: 35.1 | H47: 267854 | I47: ESCORIA
A48: 45868 | B48: ESCOBAR | C48: LOMASER | D48: 130 | H48: VACIO
A49: 45868 | B49: LOMASER | C49: RAMALLO | D49: 290 | F49: 34.94 | H49: 855542
A50: 45868 | B50: RAMALLO | C50: LOMASER | D50: 290 | F50: 35.22 | H50: 267932 | I50: ESCORIA
A51: 45869 | B51: LOMASER | C51: RAMALLO | D51: 290 | H51: 855761
D54: =SUM(D3:D53) -> 12205 | F54: =AVERAGE(F3:F52) -> 34.849412 | J54: =SUM(J3:J53) -> 0 | K54: =SUM(K3:K53) -> 0
B56: -20000 | D56: 45566
B59: =SUM(B56:B56) -> -20000 | C59: 45566

Sheet EUGENIO PITTA
D1: AB742XZ
A2: DIA | B2: SALE DE | C2: LLEGA A | D2: KM REC | E2: TN COM 29 | F2: TN ESC 35 | G2: TN ESC 37,5 | H2: REMITO Nº | I2: MATERIAL | J2: KM VACIOS | K2: $
A3: 46113 | B3: LOMASER | C3: TORTUGUITAS | D3: 140 | F3: 34.89 | H3: 894639 | K3: 388795.32
A4: 46113 | B4: TORTUGUITAS | C4: L. NEGRA | D4: 410 | H4: VACIO
A5: 46118 | B5: L. NEGRA | C5: B. DE ESCOBAR | D5: 430 | F5: 35.08 | H5: 764985 | K5: 1639040.4
A6: 46119 | B6: ESCOBAR | C6: LOMASER | D6: 140 | H6: VACIO
A7: 46119 | B7: LOMASER | C7: SOLA | D7: 80 | F7: 34.7 | H7: 895134 | K7: 386678.06
A8: 46120 | B8: SOLA | C8: LOMASER | D8: 80 | H8: VACIO
A9: 46120 | B9: LOMASER | C9: RAMALLO | D9: 290 | H9: 895294
A10: 46121 | B10: RAMALLO | C10: LOMASER | D10: 290 | F10: 35.14 | H10: 278785 | I10: ESCORIA
A11: 46122 | B11: LOMASER | C11: TORTUGUITAS | D11: 140 | F11: 35.09 | H11: 895636
A12: 46125 | B12: TORTUGUITAS | C12: LOMASER | D12: 140 | H12: VACIO
A13: 46125 | B13: LOMASER | C13: RAMALLO | D13: 290 | F13: 34.82 | H13: 895954
A14: 46125 | B14: RAMALLO | C14: ESCOBAR | D14: 185 | F14: 34.62 | H14: 278940 | I14: ESCORIA
A15: 46126 | B15: ESCOBAR | C15: LOMASER | D15: 140 | H15: VACIO
A16: 46126 | B16: LOMASER | C16: CAMPANA | D16: 125 | F16: 34.92 | H16: 896194
A17: 46127 | B17: CAMPANA | C17: RAMALLO | D17: 150 | H17: VACIO
A18: 46127 | B18: RAMALLO | C18: LOMASER | D18: 290 | F18: 34.78 | H18: 279010
A19: 46129 | B19: LOMASER | C19: RAMALLO | D19: 290 | F19: 35.16 | H19: 896678
A20: 46129 | B20: RAMALLO | C20: LOMASER | D20: 290 | F20: 35.02 | H20: 279135
A21: 46132 | B21: LOMASER | C21: CAMPANA | D21: 125 | F21: 34.86 | H21: 897000
A22: 46133 | B22: CAMPANA | C22: RAMALLO | D22: 150 | H22: VACIO
A23: 46133 | B23: RAMALLO | C23: LOMASER | D23: 290 | F23: 35.12 | H23: 279240
A24: 46134 | B24: LOMASER | C24: ESCOBAR | D24: 140 | F24: 35.09 | H24: 897387
A25: 46135 | B25: ESCOBAR | C25: LOMASER | D25: 140 | H25: VACIO
A26: 46136 | B26: LOMASER | C26: RAMALLO | D26: 290 | F26: 35.14 | H26: 897775
A27: 46136 | B27: RAMALLO | C27: LOMASER | D27: 290 | F27: 35 | H27: 279386
A28: 46139 | B28: LOMASER | C28: L. NEGRA | D28: 300 | H28: VACIO
A29: 46139 | B29: L. NEGRA | C29: TIGRE | D29: 420 | F29: 34.46 | H29: 768390
A30: 46141 | B30: TIGRE | C30: L. NEGRA | D30: 420 | H30: VACIO
A31: 46141 | B31: L. NEGRA | C31: TIGRE | D31: 420 | F31: 34.54 | H31: 768897
D32: 30 A LAS 17
D34: =SUM(D3:D33) -> 6885 | F34: =AVERAGE(F3:F32) -> 34.912778 | J34: =SUM(J3:J33) -> 0 | K34: =SUM(K3:K33) -> 2414513.8
B36: -20000 | D36: 45566
B39: =SUM(B36:B36) -> -20000 | C39: 45566

Sheet ALBORNOZ
D1: AB742XZ
A2: DIA | B2: SALE DE | C2: LLEGA A | D2: KM REC | E2: TN COM 29 | F2: TN ESC 35 | G2: TN ESC 37,5 | H2: REMITO Nº | I2: MATERIAL | J2: KM VACIOS | K2: $
A3: 46116 | B3: L. NEGRA | C3: CAMPANA | D3: 420 | F3: 33.69 | H3: 618974 | I3: CLINKER
A4: 46118 | B4: CAMPANA | C4: SIDERAR | D4: 150 | H4: VACIO
A5: 46118 | B5: SIDERAR | C5: RAMALLO | D5: 10 | H5: 1063500 | I5: CORTO
A6: 46118 | B6: RAMALLO | C6: SIDERAR | D6: 10 | H6: VACIO
A7: 46119 | B7: SIDERAR | C7: RAMALLO | D7: 10 | H7: 1063590 | I7: CORTO
A8: 46119 | B8: RAMALLO | C8: SIDERAR | D8: 10 | H8: VACIO
A9: 46119 | B9: SIDERAR | C9: L. NEGRA | D9: 500 | F9: 34.58 | H9: 1063676 | I9: ESCORIA
A10: 46120 | B10: L. NEGRA | C10: CAMPANA | D10: 420 | F10: 34.75 | H10: 619237 | I10: CLINKER
A11: 46121 | B11: CAMPANA | C11: SIDERAR | D11: 150 | H11: VACIO
A12: 46121 | B12: SIDERAR | C12: RAMALLO | D12: 10 | H12: 1064311 | I12: CORTO
A13: 46121 | B13: RAMALLO | C13: SIDERAR | D13: 10 | H13: VACIO
A14: 46122 | B14: SIDERAR | C14: RAMALLO | D14: 10 | H14: 1064410 | I14: CORTO
A15: 46122 | B15: RAMALLO | C15: SIDERAR | D15: 10 | H15: VACIO
A16: 46122 | B16: SIDERAR | C16: L. NEGRA | D16: 500 | H16: 1064517 | I16: LODO
A17: 46125 | B17: L. NEGRA | C17: CAMPANA | D17: 420 | F17: 34.97 | H17: 619593 | I17: CLINKER
A18: 46126 | B18: CAMPANA | C18: SIDERAR | D18: 150 | H18: VACIO
A19: 46126 | B19: SIDERAR | C19: L. NEGRA | D19: 500 | F19: 35.11 | H19: 1065000 | I19: LODO
A20: 46127 | B20: L. NEGRA | C20: ZAPALA | D20: 1010 | F20: 34.85 | H20: 619731 | I20: CLINKER
A21: 46129 | B21: ZAPALA | C21: ALLEN | D21: 230 | H21: VACIO
A22: 46129 | B22: ALLEN | C22: L. NEGRA | D22: 820 | F22: 34 | H22: 189651 | I22: YESO LOMA
A23: 46132 | B23: L. NEGRA | C23: S. FERNANDO | D23: 410 | F23: 34.74 | H23: 294207 | I23: FENOMIX
A24: 46133 | B24: SAN FERNANDO | C24: IBICUY | D24: 150 | H24: VACIO
A25: 46134 | B25: IBICUY | C25: AÑELO | D25: 1430 | H25: 122284 | I25: YPF
A26: 46136 | B26: AÑELO | C26: ALLEN | D26: 160 | H26: VACIO
A27: 46136 | B27: ALLEN | C27: L. NEGRA | D27: 820 | F27: 35.1 | H27: 189846 | I27: YESO LOMA
A28: 46139 | B28: L. NEGRA | C28: CAMPANA | D28: 430 | F28: 34.29 | H28: 620391 | I28: PIEDRA
A29: 46140 | B29: CAMPANA | C29: IBICUY | D29: 100 | H29: VACIO
A30: 46140 | B30: IBICUY | C30: CACHARI | D30: 380 | F30: CAMION ROTO | G30: TRASBORDO | H30: Y SIGUIO | I30: NOVILLO
D31: 28 A LAS 19
D33: =SUM(D3:D32) -> 9230 | F33: =AVERAGE(F3:F31) -> 34.608 | J33: =SUM(J3:J32) -> 0 | K33: =SUM(K3:K32) -> 0
B35: -20000
B36: 5100 | C36: PEAJES
B37: -5100 | C37: ADELANTO | D37: 45687
B38: 3400 | C38: PEAJES
B39: -3500 | C39: ADELANTO | D39: 45722
B40: 1800 | C40: PEAJES
B41: -2000 | C41: ADELANTO | D41: 45896
B42: -1000 | C42: ANTEC PENAL | D42: 46098
B43: =SUM(B35:B42) -> -21300 | C43: 46098

Sheet CARTASSO
D1: AB742XZ
A2: DIA | B2: SALE DE | C2: LLEGA A | D2: KM REC | E2: TN COM 29 | F2: TN ESC 35 | G2: TN ESC 37,5 | H2: REMITO Nº | I2: MATERIAL | J2: KM VACIOS | K2: $
A3: 46112 | B3: IBICUY | C3: ADELA 6 | D3: 1490 | H3: 118525 | I3: ADELA YPF 5 | J3: AA696BJ
A4: 46114 | B4: ADELA 6 | C4: L. NEGRA | D4: 970 | H4: VACIO
A5: 46116 | B5: L. NEGRA | C5: CAMPANA | D5: 420 | F5: 34.91 | H5: 619002 | I5: CLINKER
A6: 46118 | B6: CAMPANA | C6: SIDERAR | D6: 150 | H6: VACIO
A7: 46118 | B7: SIDERAR | C7: RAMALLO | D7: 10 | H7: 1063486 | I7: CORTO
A8: 46118 | B8: RAMALLO | C8: SIDERAR | D8: 10 | H8: VACIO
A9: 46119 | B9: SIDERAR | C9: RAMALLO | D9: 10 | H9: 1063591 | I9: CORTO
A10: 46119 | B10: RAMALLO | C10: SIDERAR | D10: 10 | H10: VACIO
A11: 46119 | B11: SIDERAR | C11: L. NEGRA | D11: 500 | H11: 1063661 | I11: ESCORIA
A12: 46121 | B12: L. NEGRA | C12: CAMPANA | D12: 420 | F12: 34.8 | H12: 619298 | I12: HOLCIM | J12: NYU938
A13: 46122 | B13: CAMPANA | C13: IBICUY | D13: 85 | H13: VACIO
A14: 46122 | B14: IBICUY | C14: AÑELO | D14: 1430 | H14: 120308 | I14: YPF
A15: 46125 | B15: AÑELO | C15: ALLEN | D15: 160 | H15: VACIO
A16: 46125 | B16: ALLEN | C16: L. NEGRA | D16: 820 | F16: 35.5 | H16: 189434 | I16: YESO LOMA
A17: 46127 | B17: L. NEGRA | C17: M. DEL PLATA | D17: 320 | H17: 766329
A18: 46128 | B18: M.DEL PLATA | C18: L. NEGRA | D18: 320 | H18: VACIO
A19: 46128 | B19: L. NEGRA | C19: CAMPANA | D19: 430 | H19: 293989 | I19: PIEDRA
A20: 46129 | B20: CAMPANA | C20: IBICUY | D20: 100 | H20: VACIO
A21: 46129 | B21: IBICUY | C21: BAJO DEL TORO | D21: 1560 | H21: 121465 | I21: YPF TORO
A22: 46132 | B22: BAJO DEL TORO | C22: ALLEN | D22: 270 | H22: VACIO
A23: 46133 | B23: ALLEN | C23: L. NEGRA | D23: 820 | F23: 34.5 | H23: 189709 | I23: YESO LOMA
A24: 46135 | B24: L. NEGRA | C24: CAMPANA | D24: 430 | H24: ???? | I24: PIEDRA
A25: 46136 | B25: CAMPANA | C25: IBICUY | D25: 100 | H25: VACIO
A26: 46136 | B26: IBICUY | C26: HINOJO | D26: 480 | G26: SIGUIO | H26: VERRR | I26: URBAN
A27: 46139 | B27: HINOJO | C27: CAMPANA | D27: 420 | F27: 33.7 | H27: 620392 | J27: AA696BJ
A28: 46140 | B28: CAMPANA | C28: IBICUY | D28: 85 | H28: VACIO
A29: 46140 | B29: IBICUY | C29: AÑELO | D29: 1430 | H29: 123586 | I29: YPF
D30: 30 A LA 1
D32: =SUM(D3:D31) -> 13250 | F32: =AVERAGE(F3:F30) -> 34.682 | J32: =SUM(J3:J31) -> 0 | K32: =SUM(K3:K31) -> 0
B34: -20000 | D34: 45566
B35: 5100 | C35: PEAJES | D35: 45838
B36: -5100 | C36: ADELANTO | D36: 45838
B37: -1000 | C37: ANTEC PENAL | D37: 45944
B38: 2200 | C38: PEAJES | D38: 46091
B39: -2000 | C39: ADELANTO
B40: =SUM(B34:B39) -> -20800 | C40: 46091

Sheet ANDRUSZEZEN
D1: AB742XZ
A2: DIA | B2: SALE DE | C2: LLEGA A | D2: KM REC | E2: TN COM 29 | F2: TN ESC 35 | G2: TN ESC 37,5 | H2: REMITO Nº | I2: MATERIAL | J2: KM VACIOS | K2: $
A3: 46112 | B3: ALLEN | C3: L. NEGRA | D3: 820 | H3: 189344 | I3: YESO LOMA
A4: 46116 | B4: L. NEGRA | C4: CAMPANA | D4: 420 | H4: ???? | I4: HOLCIM
A5: 46117 | B5: CAMPANA | C5: IBICUY | D5: 85 | H5: VACIO
A6: 46117 | B6: IBICUY | C6: AÑELO | D6: 1310 | H6: 81380 | I6: YPF RUTA 5
A7: 46119 | B7: AÑELO | C7: L. NEGRA | D7: 940 | H7: VACIO
A8: 46121 | B8: L. NEGRA | C8: CAMPANA | D8: 420 | F8: 34.64 | H8: 619309 | I8: CLINKER
A9: 46122 | B9: CAMPANA | C9: SIDERAR | D9: 150 | H9: VACIO
A10: 46122 | B10: SIDERAR | C10: RAMALLO | D10: 10 | H10: 1064532 | I10: CORTO
A11: 46122 | B11: RAMALLO | C11: SIDERAR | D11: 10 | H11: VACIO
A12: 46123 | B12: SIDERAR | C12: L. NEGRA | D12: 500 | F12: 34.8 | H12: 1064626 | I12: LODO | K12: 573111.54
A13: 46126 | B13: L. NEGRA | C13: CAMPANA | D13: 430 | H13: 293870 | I13: PIEDRA
A14: 46127 | B14: CAMPANA | C14: SIDERCA | D14: 10 | H14: VACIO
A15: 46127 | B15: CAMPANA | C15: CATAMARCA | D15: 990 | F15: 34.06 | H15: 153223 | I15: SIDERCA
A16: 46128 | B16: CATAMARCA | C16: FERREYRA | D16: 400 | H16: 504113
A17: 46129 | B17: FERREYRA | C17: PAMPAYASTA | D17: 120 | H17: VACIO
A18: 46129 | B18: PAMPAYASTA | C18: ROSARIO | D18: 340 | F18: 34.78 | H18: TKT 21655
A19: 46130 | B19: ROSARIO | C19: RAMALLO | D19: 80 | H19: VACIO
A20: 46132 | B20: RAMALLO | C20: ZAPALA | D20: 1470 | F20: 34.45 | H20: 1065913 | I20: LODO
A21: 46134 | B21: ZAPALA | C21: L. NEGRA | D21: 1060 | H21: 16429 | I21: TANDILIA
A22: 46136 | B22: L. NEGRA | C22: ZAPALA | D22: 1010 | F22: 35.12 | H22: 620250 | I22: CLINKER
A23: 46138 | B23: ZAPALA | C23: ALLEN | D23: 240 | H23: VACIO
A24: 46139 | B24: ALLEN | C24: L. NEGRA | D24: 820 | F24: 34.4 | H24: 189969 | I24: YESO LOMA
A25: 46141 | B25: L. NEGRA | C25: ZAPALA | D25: 1010 | H25: ???? | I25: CLINKER
A26: 46142 | B26: ZAPALA | C26: ALLEN | D26: 240 | H26: VACIO
D27: 30 a las 20
D29: =SUM(D3:D28) -> 12885 | F29: =AVERAGE(F3:F27) -> 34.607143 | J29: =SUM(J3:J28) -> 0 | K29: =SUM(K3:K28) -> 573111.54
B31: -20000
B34: =SUM(B31:B31) -> -20000

Sheet PAZ
D1: AB742XZ
A2: DIA | B2: SALE DE | C2: LLEGA A | D2: KM REC | E2: TN COM 29 | F2: TN ESC 35 | G2: TN ESC 37,5 | H2: REMITO Nº | I2: MATERIAL | J2: KM VACIOS | K2: $
A3: 46112 | B3: RAMALLO | C3: LOMASER | D3: 300 | H3: 278564 | I3: ESCORIA
A4: 46118 | B4: LOMASER | C4: CHACHARRAMENDI | D4: 900 | F4: 33.34 | H4: 694945
A5: 46120 | B5: CHACHARRAMENDI | C5: L. NEGRA | D5: 650 | H5: VACIO
A6: 46120 | B6: L. NEGRA | C6: TIGRE | D6: 420 | F6: 33.24 | H6: 765304
A7: 46121 | B7: TIGRE | C7: LOMASER | D7: 120 | H7: VACIO
A8: 46122 | B8: LOMASER | C8: RAMALLO | D8: 300 | H8: 859605
A9: 46122 | B9: RAMALLO | C9: LOMASER | D9: 300 | H9: 278861 | I9: ESCORIA
A10: 46125 | B10: LOMASER | C10: TORTUGUITAS | D10: 140 | F10: 33.62 | H10: 895962
A11: 46126 | B11: TORTUGUITAS | C11: LOMASER | D11: 140 | H11: VACIO
A12: 46127 | B12: LOMASER | C12: RAMALLO | D12: 300 | H12: 896302
A13: 46127 | B13: RAMALLO | C13: LOMASER | D13: 300 | H13: 279019 | I13: ESCORIA
A14: 46128 | B14: LOMASER | C14: L. NEGRA | D14: 300 | H14: VACIO
A15: 46129 | B15: L. NEGRA | C15: ZELAYA | D15: 400 | F15: 29.36 | H15: 766649
A16: 46129 | B16: ZELAYA | C16: LOMASER | D16: 130 | H16: VACIO
A17: 46129 | B17: LOMASER | C17: RAMALLO | D17: 300 | H17: 896755
A18: 46132 | B18: RAMALLO | C18: ESCOBAR | D18: 185 | F18: 34.06 | H18: 279193
A19: 46133 | B19: ESCOBAR | C19: LOMASER | D19: 140 | H19: VACIO
A20: 46133 | B20: LOMASER | C20: TORTUGUITAS | D20: 140 | F20: 33.79 | H20: 897246
A21: 46133 | B21: TORTUGUITAS | C21: LOMASER | D21: 140 | H21: VACIO
A22: 46135 | B22: LOMASER | C22: TORTUGUITAS | D22: 140 | F22: 34.08 | H22: 897610
A23: 46135 | B23: TORTUGUITAS | C23: LOMASER | D23: 140 | H23: VACIO
A24: 46139 | B24: LOMASER | C24: RAMALLO | D24: 300 | H24: 898059
A25: 46139 | B25: RAMALLO | C25: LOMASER | D25: 300 | H25: 279448 | I25: ESCORIA
A26: 46140 | B26: LOMASER | C26: TORTUGUITAS | D26: 140 | F26: 33.75 | H26: 898410
A27: 46141 | B27: TORTUGUITAS | C27: L. NEGRA | D27: 400 | H27: VACIO
A28: 46142 | B28: L. NEGRA | C28: ESCOBAR | D28: 430 | F28: 33.46 | H28: 768902
A29: 46142 | B29: ESCOBAR | C29: LOMASER | D29: 140 | H29: VACIO
D30: 30 A LAS 22
D32: =SUM(D3:D31) -> 7595 | F32: =AVERAGE(F3:F30) -> 33.188889 | J32: =SUM(J3:J31) -> 0 | K32: =SUM(K3:K31) -> 0
B34: -20000 | D34: 45705
B35: -200000 | C35: PARA COMB. | D35: 45705
B36: 183230 | C36: GAS
B37: -400000 | C37: ADELANTO | D37: 45712
B38: 434477.03 | C38: GAS | D38: 45742
B39: 491381 | C39: TARJ DEB DE EL
B40: -900000 | C40: ADELANTO
B41: 410911.97 | C41: GAS EFEC CAJA
B42: 185219.97 | C42: GAS EFEC PAGO EL
B43: 616480 | C43: TARJ DEB DE EL
B44: -780000 | C44: ADELANTO
B45: 1000 | C45: ATEC PENAL | D45: 45974
B46: =SUM(B34:B45) -> 22699.97 | C46: 45974

Sheet LEYENDEKER
D1: AB742XZ
A2: DIA | B2: SALE DE | C2: LLEGA A | D2: KM REC | E2: TN COM 29 | F2: TN ESC 35 | G2: TN ESC 37,5 | H2: REMITO Nº | I2: MATERIAL | J2: KM VACIOS | K2: $
A3: 46118 | B3: L. NEGRA | C3: M. DEL PLATA | D3: 320 | H3: 764998 | K3: 857189.3
A4: 46119 | B4: M.DEL PLATA | C4: L. NEGRA | D4: 320 | H4: PALLETS | I4: 1 CLIENTE
A5: 46120 | B5: L. NEGRA | C5: CAMPANA | D5: 420 | F5: 35.54 | H5: 619229 | I5: CLINKER
A6: 46121 | B6: CAMPANA | C6: SIDERAR | D6: 150 | H6: VACIO
A7: 46121 | B7: SIDERAR | C7: RAMALLO | D7: 10 | H7: 1064287 | I7: CORTO
A8: 46122 | B8: RAMALLO | C8: SIDERAR | D8: 10 | H8: VACIO
A9: 46122 | B9: SIDERAR | C9: RAMALLO | D9: 10 | H9: 1064352 | I9: CORTO
A10: 46122 | B10: RAMALLO | C10: SIDERAR | D10: 10 | H10: VACIO
A11: 46122 | B11: SIDERAR | C11: L. NEGRA | D11: 500 | F11: 35.69 | H11: 1064433 | I11: ESCORIA | K11: 586420.61
A12: 46125 | B12: L. NEGRA | C12: ZAPALA | D12: 1010 | F12: 35.48 | H12: 619565 | I12: CLINKER | K12: 2330181.6
A13: 46127 | B13: ZAPALA | C13: ALLEN | D13: 240 | H13: VACIO
A14: 46127 | B14: ALLEN | C14: L. NEGRA | D14: 820 | F14: 35.8 | H14: 189540 | I14: YESO LOMA | K14: 996974.49
A15: 46129 | B15: L. NEGRA | C15: ZAPALA | D15: 1010 | F15: 35.6 | H15: 619862 | I15: CLINKER
A16: 46133 | B16: ZAPALA | C16: ALLEN | D16: 240 | H16: VACIO
A17: 46133 | B17: ALLEN | C17: L. NEGRA | D17: 820 | F17: 35 | H17: 189802 | I17: YESO LOMA
A18: 46135 | B18: L. NEGRA | C18: CAMPANA | D18: 430 | F18: 35.9 | H18: 294379 | I18: PIEDRA
A19: 46136 | B19: CAMPANA | C19: SIDERAR | D19: 150 | H19: VACIO
A20: 46136 | B20: SIDERAR | C20: L. NEGRA | D20: 500 | F20: 32.8 | G20: DESCONTAR | H20: 1066972 | I20: LODO
A21: 46137 | B21: L. NEGRA | C21: CAMPANA | D21: 420 | H21: ???? | I21: HOLCIM
A22: 46140 | B22: CAMPANA | C22: IBICUY | D22: 85 | H22: VACIO
A23: 46141 | B23: IBICUY | C23: BAJO DEL TORO | D23: 1560 | H23: 123728 | I23: YPF TORO
D24: 1 a las 12
D26: =SUM(D3:D25) -> 9035 | F26: =AVERAGE(F3:F24) -> 35.22625 | J26: =SUM(J3:J25) -> 0 | K26: =SUM(K3:K25) -> 4770766
B28: -20000
B29: 5100 | C29: PEAJES
B30: -5100 | C30: ADELANTO | D30: 45930
B31: -1000 | C31: ANT PENALES
B35: =SUM(B28:B34) -> -21000 | C35: 45930

Sheet FRANCO
D1: AB742XZ
A2: DIA | B2: SALE DE | C2: LLEGA A | D2: KM REC | E2: TN COM 29 | F2: TN ESC 35 | G2: TN ESC 37,5 | H2: REMITO Nº | I2: MATERIAL | J2: KM VACIOS | K2: $
A3: 46113 | B3: L. NEGRA | C3: M. CENTRAL | D3: 340 | F3: 34.16 | H3: 293323 | K3: 614880
A4: 46118 | B4: M. CENTRAL | C4: IBICUY | D4: 190 | H4: VACIO
A5: 46119 | B5: IBICUY | C5: AÑELO | D5: 1310 | H5: 119616 | I5: YPF RUTA 5
A6: 46121 | B6: AÑELO | C6: L. NEGRA | D6: 940 | H6: VACIO
A7: 46122 | B7: L. NEGRA | C7: CASEROS | D7: 380 | H7: 61940 | I7: TRAMONTANA
A8: 46125 | B8: CASEROS | C8: LOMASER | D8: 120 | H8: VACIO
A9: 46125 | B9: LOMASER | C9: RAMALLO | D9: 300 | H9: 895979
A10: 46126 | B10: RAMALLO | C10: L. NEGRA | D10: 500 | F10: 35.15 | H10: 1064985 | I10: LODO
A11: 46127 | B11: L. NEGRA | C11: ZAPALA | D11: 1010 | F11: 34.42 | H11: 619732 | I11: CLINKER
A12: 46129 | B12: ZAPALA | C12: ALLEN | D12: 230 | H12: VACIO
A13: 46129 | B13: ALLEN | C13: L. NEGRA | D13: 820 | F13: 34.4 | H13: 189652 | I13: YESO LOMA
A14: 46132 | B14: L. NEGRA | C14: SAN FERNANDO | D14: 420 | F14: 34.96 | H14: 294209 | I14: FENOMIX
A15: 46133 | B15: SAN FERNANDO | C15: IBICUY | D15: 150 | H15: VACIO
A16: 46134 | B16: IBICUY | C16: AÑELO | D16: 1430 | H16: 122283 | I16: YPF
A17: 46136 | B17: AÑELO | C17: L. NEGRA | D17: 940 | H17: VACIO
A18: 46140 | B18: L. NEGRA | C18: CAMPANA | D18: 420 | F18: 35.27 | H18: 620419 | I18: CLINKER
A19: 46140 | B19: CAMPANA | C19: SIDERAR | D19: 150 | H19: VACIO
A20: 46140 | B20: SIDERAR | C20: RAMALLO | D20: 10 | H20: 1067564 | I20: CORTO
A21: 46141 | B21: RAMALLO | C21: SIDERAR | D21: 10 | H21: VACIO
A22: 46141 | B22: SIDERAR | C22: RAMALLO | D22: 10 | H22: 1067583 | I22: CORTO
A23: 46141 | B23: RAMALLO | C23: SIDERAR | D23: 10 | H23: VACIO
A24: 46141 | B24: SIDERAR | C24: L. NEGRA | D24: 500 | F24: 35.35 | H24: 1067679 | I24: ESCORIA
D25: 30 A LAS 12
D27: =SUM(D3:D26) -> 10190 | F27: =AVERAGE(F3:F25) -> 34.815714 | J27: =SUM(J3:J26) -> 0 | K27: =SUM(K3:K26) -> 614880
B29: -20000
B30: -1000 | C30: ANTEC PENAL | D30: 45826
B36: =SUM(B29:B35) -> -21000 | C36: 45826

Sheet LARRECOCHEA J.
D1: AB742XZ
A2: DIA | B2: SALE DE | C2: LLEGA A | D2: KM REC | E2: TN COM 29 | F2: TN ESC 35 | G2: TN ESC 37,5 | H2: REMITO Nº | I2: MATERIAL | J2: KM VACIOS | K2: $
A3: 46113 | B3: L. NEGRA | C3: M. CENTRAL | D3: 340 | F3: 35.02 | H3: 293226 | K3: 630360
A4: 46118 | B4: M. CENTRAL | C4: IBICUY | D4: 190 | H4: VACIO
A5: 46118 | B5: IBICUY | C5: AÑELO | D5: 1430 | H5: 119479 | I5: YPF
A6: 46120 | B6: AÑELO | C6: L. NEGRA | D6: 940 | H6: VACIO
A7: 46121 | B7: L. NEGRA | C7: M. DEL PLATA | D7: 320 | H7: 765444
A8: 46122 | B8: M. DEL PLATA | C8: BARKER | D8: 230 | H8: VACIO
A9: 46122 | B9: BARKER | C9: L. NEGRA | D9: 220 | H9: 182578 | I9: M. ROJO
A10: 46123 | B10: L. NEGRA | C10: ESCOBAR | D10: 430 | H10: 765824
A11: 46125 | B11: ESCOBAR | C11: LOMASER | D11: 140 | H11: VACIO
A12: 46125 | B12: LOMASER | C12: BENAVIDEZ | D12: 140 | H12: 895961
A13: 46126 | B13: BENAVIDEZ | C13: RAMALLO | D13: 210 | H13: VACIO
A14: 46127 | B14: RAMALLO | C14: L. NEGRA | D14: 500 | F14: 34.17 | H14: 1065198 | I14: ESCORIA
A15: 46128 | B15: L. NEGRA | C15: CAMPANA | D15: 420 | F15: 34.04 | H15: 619801 | I15: HOLCIM
A16: 46129 | B16: CAMPANA | C16: RAMALLO | D16: 150 | H16: VACIO
A17: 46130 | B17: RAMALLO | C17: ZAPALA | D17: 1470 | F17: 34.12 | H17: 1065756 | I17: LODO
A18: 46134 | B18: ZAPALA | C18: L. NEGRA | D18: 1060 | H18: 16427 | I18: TANDILIA
A19: 46135 | B19: L. NEGRA | C19: ZAPALA | D19: 1010 | F19: 34.62 | H19: 620199 | I19: CLINKER
A20: 46136 | B20: ZAPALA | C20: ALLEN | D20: 240 | H20: VACIO
A21: 46136 | B21: ALLEN | C21: L. NEGRA | D21: 820 | F21: 34.2 | H21: 189910 | I21: YESO LOMA
A22: 46139 | B22: L. NEGRA | C22: TORCUATO | D22: 400 | H22: 294622
A23: 46140 | B23: TORCUATO | C23: IBICUY | D23: 150 | H23: VACIO
A24: 46141 | B24: IBICUY | C24: BAJO DEL TORO | D24: 1560 | H24: 123726 | I24: YPF TORO
D25: 1 A LAS 10
D27: =SUM(D3:D26) -> 12370 | F27: =AVERAGE(F3:F25) -> 34.361667 | J27: =SUM(J3:J26) -> 0 | K27: =SUM(K3:K26) -> 630360
B29: -20000
B36: =SUM(B29:B35) -> -20000

Sheet LARRECOCHEA MARCELO
D1: AB742XZ
A2: DIA | B2: SALE DE | C2: LLEGA A | D2: KM REC | E2: TN COM 29 | F2: TN ESC 35 | G2: TN ESC 37,5 | H2: REMITO Nº | I2: MATERIAL | J2: KM VACIOS | K2: $
A3: 46113 | B3: L. NEGRA | C3: M. CENTRAL | D3: 340 | F3: 34.68 | H3: 293225 | K3: 624240
A4: 46118 | B4: M. CENTRAL | C4: IBICUY | D4: 190 | H4: VACIO
A5: 46118 | B5: IBICUY | C5: AÑELO | D5: 1430 | H5: 119478 | I5: YPF
A6: 46120 | B6: AÑELO | C6: L. NEGRA | D6: 940 | H6: VACIO
A7: 46121 | B7: L. NEGRA | C7: M. DEL PLATA | D7: 320 | H7: 765443
A8: 46122 | B8: M. DEL PLATA | C8: BARKER | D8: 230 | H8: VACIO
A9: 46122 | B9: BARKER | C9: L. NEGRA | D9: 200 | H9: 182577 | I9: M. ROJO
A10: 46123 | B10: L. NEGRA | C10: TORCUATO | D10: 400 | H10: 765826
A11: 46125 | B11: TORCUATO | C11: LOMASER | D11: 140 | H11: VACIO
A12: 46125 | B12: LOMASER | C12: BENAVIDEZ | D12: 140 | H12: 895957
A13: 46126 | B13: BENAVIDEZ | C13: CAMPANA | D13: 50 | H13: VACIO
A14: 46126 | B14: CAMPANA | C14: CATAMARCA | D14: 990 | F14: 34.12 | H14: 153191 | I14: SIDERCA
A15: 46127 | B15: CATAMARCA | C15: FERREYRA | D15: 390 | H15: 504113
A16: 46128 | B16: FERREYRA | C16: PAMPAYASTA | D16: 120 | H16: VACIO
A17: 46129 | B17: PAMPAYASTA | C17: ROSARIO | D17: 340 | F17: 36.88 | H17: TKT 21594
A18: 46129 | B18: ROSARIO | C18: RAMALLO | D18: 80 | H18: VACIO
A19: 46129 | B19: RAMALLO | C19: L. NEGRA | D19: 500 | F19: 34.25 | H19: 1065643 | I19: ESCORIA
A20: 46133 | B20: L. NEGRA | C20: CAMPANA | D20: 430 | F20: 34.42 | H20: 294288 | I20: PIEDRA
A21: 46134 | B21: CAMPANA | C21: IBICUY | D21: 100 | H21: VACIO
A22: 46134 | B22: IBICUY | C22: BAJO DEL TORO | D22: 1560 | H22: 122403 | I22: YPF TORO
A23: 46136 | B23: BAJO DEL TORO | C23: L. NEGRA | D23: 1070 | H23: VACIO
A24: 46139 | B24: L. NEGRA | C24: TORCUATO | D24: 400 | F24: 34.34 | H24: 294623
A25: 46140 | B25: TORCUATO | C25: IBICUY | D25: 150 | H25: VACIO
A26: 46141 | B26: IBICUY | C26: BAJO DEL TORO | D26: 1560 | H26: 123725 | I26: YPF TORO
D27: 1 A LAS 10
D29: =SUM(D3:D28) -> 12070 | F29: =AVERAGE(F3:F27) -> 34.781667 | J29: =SUM(J3:J28) -> 0 | K29: =SUM(K3:K28) -> 624240
B31: -20000
B38: =SUM(B31:B37) -> -20000

Sheet PITANA MAXI
D1: AB742XZ
A2: DIA | B2: SALE DE | C2: LLEGA A | D2: KM REC | E2: TN COM 29 | F2: TN ESC 35 | G2: TN ESC 37,5 | H2: REMITO Nº | I2: MATERIAL | J2: KM VACIOS | K2: $
A3: 46112 | B3: RAMALLO | C3: LOMASER | D3: 300 | H3: 278559 | I3: ESCORIA
A4: 46116 | B4: LOMASER | C4: TORTUGUITAS | D4: 140 | F4: 34.76 | H4: 894839 | K4: 387346.67
A5: 46118 | B5: TORTUGUITAS | C5: LOMASER | D5: 140 | H5: VACIO
A6: 46119 | B6: LOMASER | C6: TORTUGUITAS | D6: 140 | H6: 895079 | K6: 386232.32
A7: 46119 | B7: TORTUGUITAS | C7: LOMASER | D7: 140 | H7: VACIO
A8: 46120 | B8: LOMASER | C8: RAMALLO | D8: 300 | H8: 895236
A9: 46120 | B9: RAMALLO | C9: LOMASER | D9: 300 | H9: 278750 | I9: ESCORIA
A10: 46121 | B10: LOMASER | C10: TORCUATO | D10: 140 | F10: 34.34 | H10: 895518
A11: 46122 | B11: TORCUATO | C11: L. NEGRA | D11: 400 | H11: VACIO
A12: 46125 | B12: L. NEGRA | C12: LEZAMA | D12: 380 | F12: 34.44 | H12: 766173
A13: 46127 | B13: LEZAMA | C13: LOMASER | D13: 190 | H13: VACIO
A14: 46128 | B14: LOMASER | C14: TORTUGUITAS | D14: 140 | F14: 34.48 | H14: 896482
A15: 46128 | B15: TORTUGUITAS | C15: LOMASER | D15: 140 | H15: VACIO
A16: 46129 | B16: LOMASER | C16: RAMALLO | D16: 300 | H16: 896701
A17: 46129 | B17: RAMALLO | C17: LOMASER | D17: 300 | H17: 279148 | I17: ESCORIA
A18: 46132 | B18: LOMASER | C18: URIBURU | D18: 340 | F18: 34.75 | H18: 897021
A19: 46134 | B19: URIBURU | C19: RAMALLO | D19: 80 | H19: VACIO
A20: 46134 | B20: RAMALLO | C20: LOMASER | D20: 300 | H20: 279293 | I20: ESCORIA
A21: 46136 | B21: LOMASER | C21: TORTUGUITAS | D21: 140 | F21: 34.75 | H21: 897834
A22: 46139 | B22: TORTUGUITAS | C22: LOMASER | D22: 140 | H22: VACIO
A23: 46140 | B23: LOMASER | C23: RAMALLO | D23: 300 | H23: 898274
A24: 46140 | B24: RAMALLO | C24: LOMASER | D24: 300 | H24: 279499 | I24: ESCORIA
A25: 46141 | B25: LOMASER | C25: RAMALLO | D25: 300 | H25: 898502
A26: 46141 | B26: RAMALLO | C26: LOMASER | D26: 300 | H26: 279566 | I26: ESCORIA
D27: 30 A LAS 9
D29: =SUM(D3:D28) -> 5650 | F29: =AVERAGE(F3:F27) -> 34.586667 | J29: =SUM(J3:J28) -> 0 | K29: =SUM(K3:K28) -> 773578.99
B31: -20000
B32: 10200 | C32: 45835
B33: -10200 | C33: 45835
B34: -200000 | C34: PARA PEAJES XQ NO TIENE DISP | D34: 46161
B38: =SUM(B31:B37) -> -220000 | C38: 46161

Sheet GARMENDIA L.
D1: AB742XZ
A2: DIA | B2: SALE DE | C2: LLEGA A | D2: KM REC | E2: TN COM 29 | F2: TN ESC 35 | G2: TN ESC 37,5 | H2: REMITO Nº | I2: MATERIAL | J2: KM VACIOS | K2: $
A3: 46116 | B3: L. NEGRA | C3: CAMPANA | D3: 420 | G3: 36.84 | H3: 618967 | I3: CLINKER
A4: 46118 | B4: CAMPANA | C4: SIDERCA | D4: 10 | H4: VACIO
A5: 46119 | B5: CAMPANA | C5: CATAMARCA | D5: 990 | H5: 153048 | I5: SIDERCA | K5: 1762572.9
A6: 46120 | B6: CATAMARCA | C6: CORDOBA | D6: 380 | H6: 503423 | K6: 1119388.3
A7: 46121 | B7: CORDOBA | C7: MALAGUEÑO | D7: 50 | H7: VACIO
A8: 46121 | B8: MALAGUEÑO | C8: ROSARIO | D8: 430 | G8: 36.2 | H8: 303244 | I8: PIEDRA
A9: 46122 | B9: ROSARIO | C9: RAMALLO | D9: 80 | H9: VACIO
A10: 46123 | B10: RAMALLO | C10: L. NEGRA | D10: 500 | G10: 35.82 | H10: 1064646 | I10: LODO
A11: 46126 | B11: L. NEGRA | C11: ZAPALA | D11: 1030 | G11: 36.64 | H11: 619630 | I11: CLINKER
A12: 46127 | B12: ZAPALA | C12: ALLEN | D12: 240 | H12: VACIO
A13: 46128 | B13: ALLEN | C13: L. NEGRA | D13: 820 | G13: 32.4 | H13: 189633 | I13: YESO LOMA
A14: 46130 | B14: L. NEGRA | C14: ZAPALA | D14: 1030 | G14: 36.5 | H14: 619976 | I14: CLINKER
A15: 46132 | B15: ZAPALA | C15: ALLEN | D15: 240 | H15: VACIO
A16: 46133 | B16: ALLEN | C16: L. NEGRA | D16: 820 | G16: 35.4 | H16: 189787 | I16: YESO LOMA
A17: 46135 | B17: L. NEGRA | C17: ZAPALA | D17: 1030 | G17: 36.53 | H17: 620184 | I17: CLINKER
A18: 46136 | B18: ZAPALA | C18: ALLEN | D18: 240 | H18: VACIO
A19: 46136 | B19: ALLEN | C19: L. NEGRA | D19: 820 | G19: 35.4 | H19: 189915 | I19: YESO LOMA
A20: 46139 | B20: L. NEGRA | C20: CAMPANA | D20: 430 | G20: 36.1 | H20: 294624 | I20: PIEDRA
A21: 46140 | B21: CAMPANA | C21: SIDERAR | D21: 150 | H21: VACIO
A22: 46140 | B22: SIDERAR | C22: RAMALLO | D22: 10 | H22: 1067468 | I22: CORTO
A23: 46140 | B23: RAMALLO | C23: SIDERAR | D23: 10 | H23: VACIO
A24: 46140 | B24: SIDERAR | C24: RAMALLO | D24: 10 | H24: 1067528 | I24: CORTO
A25: 46141 | B25: RAMALLO | C25: SIDERAR | D25: 10 | H25: VACIO
A26: 46141 | B26: SIDERAR | C26: L. NEGRA | D26: 500 | G26: 35.2 | H26: 1067618 | I26: ESCORIA
A27: 46141 | B27: L. NEGRA | C27: SOLA | D27: 380 | F27: 35.84 | H27: 294825 | I27: PIEDRA
A28: 46142 | B28: SOLA | C28: IBICUY | D28: 180 | H28: VACIO
D29: 30 A LAS 22
D31: =SUM(D3:D30) -> 10810 | F31: =AVERAGE(F3:F29) -> 35.84 | G31: =AVERAGE(G3:G29) -> 35.73 | J31: =SUM(J3:J30) -> 0 | K31: =SUM(K3:K30) -> 2881961.2
B33: -20000
B34: -1000 | C34: ANT. PENALES | D34: 45866
B40: =SUM(B33:B39) -> -21000 | C40: 45866

Sheet GOMEZ M.
D1: AB742XZ
A2: DIA | B2: SALE DE | C2: LLEGA A | D2: KM REC | E2: TN COM 29 | F2: TN ESC 35 | G2: TN ESC 37,5 | H2: REMITO Nº | I2: MATERIAL | J2: KM VACIOS | K2: $
D3: SUSPENSION | E3: 3 DIAS
A4: 46125 | B4: L. NEGRA | C4: ZAPALA | D4: 1030 | F4: 36.04 | H4: 619532 | I4: CLINKER | K4: 2366960.2
A5: 46127 | B5: ZAPALA | C5: ALLEN | D5: 240 | H5: VACIO
A6: 46127 | B6: ALLEN | C6: L. NEGRA | D6: 820 | F6: 35.5 | H6: 189539 | I6: YESO LOMA | K6: 992006.18
A7: 46129 | B7: L. NEGRA | C7: ZAPALA | D7: 1030 | H7: 619895 | I7: CLINKER
A8: 46131 | B8: ZAPALA | C8: ALLEN | D8: 240 | H8: VACIO
A9: 46132 | B9: ALLEN | C9: L. NEGRA | D9: 820 | F9: 35.3 | H9: 189672 | I9: YESO LOMA
A10: 46134 | B10: L. NEGRA | C10: CAMPANA | D10: 430 | F10: 35.9 | H10: 294323 | I10: PIEDRA
A11: 46135 | B11: CAMPANA | C11: IBICUY | D11: 100 | H11: VACIO
A12: 46136 | B12: IBICUY | C12: BAJO DEL TORO | D12: 1560 | H12: 122665 | I12: YPF TORO
A13: 46139 | B13: BAJO DEL TORO | C13: ALLEN | D13: 270 | H13: VACIO
A14: 46139 | B14: ALLEN | C14: L. NEGRA | D14: 820 | F14: 35.4 | H14: 189976 | I14: YESO LOMA
A15: 46141 | B15: L. NEGRA | C15: ZAPALA | D15: 1030 | H15: ???? | I15: CLINKER | J15: AD916TF
A16: 46142 | B16: ZAPALA | C16: ALLEN | D16: 240 | H16: VACIO
D17: 28 A LAS 23
D19: =SUM(D3:D18) -> 8630 | F19: =AVERAGE(F3:F17) -> 35.628 | G19: =AVERAGE(G3:G17) -> #DIV/0! | J19: =SUM(J3:J18) -> 0 | K19: =SUM(K3:K18) -> 3358966.3
B21: -20000
B22: -1000 | C22: ANT. PENALES | D22: 46055
B28: =SUM(B21:B27) -> -21000 | C28: 45866

Sheet PAREDEZ
D1: AB742XZ
A2: DIA | B2: SALE DE | C2: LLEGA A | D2: KM REC | E2: TN COM 29 | F2: TN ESC 35 | G2: TN ESC 37,5 | H2: REMITO Nº | I2: MATERIAL | J2: KM VACIOS | K2: $
A3: 46113 | B3: HINOJO | C3: CAMPANA | D3: 420 | G3: 36.6 | H3: 618936 | I3: CLINKER | J3: AD916TF
A4: 46116 | B4: CAMPANA | C4: IBICUY | D4: 85 | H4: VACIO
A5: 46116 | B5: IBICUY | C5: BAJO DEL TORO | D5: 1560 | H5: 81365 | I5: YPF TORO
A6: 46119 | B6: BAJO DEL TORO | C6: ALLEN | D6: 270 | H6: VACIO
A7: 46120 | B7: ALLEN | C7: L. NEGRA | D7: 820 | G7: 35.7 | H7: 189319 | I7: YESO LOMA | K7: 1563002.3
A8: 46122 | B8: L. NEGRA | C8: CAMPANA | D8: 420 | G8: 36.8 | H8: 619373 | I8: CLINKER
A9: 46125 | B9: CAMPANA | C9: IBICUY | D9: 85 | H9: VACIO
A10: 46125 | B10: IBICUY | C10: BAJO DEL TORO | D10: 1560 | H10: 120810 | I10: YPF TORO
A11: 46127 | B11: BAJO DEL TORO | C11: ALLEN | D11: 270 | H11: VACIO
A12: 46128 | B12: ALLEN | C12: L. NEGRA | D12: 820 | G12: 35.4 | H12: 189558 | I12: YESO LOMA
A13: 46130 | B13: L. NEGRA | C13: CASEROS | D13: 380 | H13: 2702680 | I13: TRAMONTANA
A14: 46132 | B14: CASEROS | C14: IBICUY | D14: 180 | H14: VACIO
A15: 46132 | B15: IBICUY | C15: AÑELO | D15: 1430 | H15: 121959 | I15: YPF
A16: 46134 | B16: AÑELO | C16: ALLEN | D16: 160 | H16: VACIO
A17: 46134 | B17: ALLEN | C17: L. NEGRA | D17: 820 | G17: 36.3 | H17: 189818 | I17: YESO LOMA
A18: 46136 | B18: L. NEGRA | C18: CAMPANA | D18: 430 | G18: 35.38 | H18: 294496 | I18: PIEDRA | J18: AE169ZO
A19: 46139 | B19: CAMPANA | C19: IBICUY | D19: 100 | H19: VACIO
A20: 46139 | B20: IBICUY | C20: BAJO DEL TORO | D20: 1560 | H20: 81576 | I20: YPF TORO
A21: 46142 | B21: BAJO DEL TORO | C21: L. NEGRA | D21: 1070 | H21: VACIO
D22: 1 A LAS 9
D24: =SUM(D3:D23) -> 12440 | F24: =AVERAGE(F3:F22) -> #DIV/0! | G24: =AVERAGE(G3:G22) -> 36.03 | J24: =SUM(J3:J23) -> 0 | K24: =SUM(K3:K23) -> 1563002.3
B26: -20000
B33: =SUM(B26:B32) -> -20000

Sheet ASTEAZARAN  AGUSTIN
A2: DIA | B2: SALE DE | C2: LLEGA A | D2: KM REC | E2: TN COM 29 | F2: TN ESC 35 | G2: TN ESC 37,5 | H2: REMITO Nº | I2: MATERIAL | J2: KM VACIOS | K2: $
A3: 46113 | B3: ADELA 6 | C3: L. NEGRA | D3: 970 | H3: VACIO
A4: 46116 | B4: L. NEGRA | C4: CAMPANA | D4: 420 | F4: 34.94 | H4: 618988 | I4: CLINKER
A5: 46118 | B5: CAMPANA | C5: SIDERAR | D5: 150 | H5: VACIO
A6: 46118 | B6: SIDERAR | C6: RAMALLO | D6: 10 | H6: 1063440 | I6: CORTO
A7: 46118 | B7: RAMALLO | C7: SIDERAR | D7: 10 | H7: VACIO
A8: 46118 | B8: SIDERAR | C8: RAMALLO | D8: 10 | H8: 1063515 | I8: CORTO
A9: 46119 | B9: RAMALLO | C9: SIDERAR | D9: 10 | H9: VACIO
A10: 46119 | B10: SIDERAR | C10: L. NEGRA | D10: 500 | F10: 35.34 | H10: 1063616 | I10: LODO
A11: 46120 | B11: L. NEGRA | C11: JUNIN | D11: 350 | H11: 619285 | K11: 1017135.2
A12: 46121 | B12: JUNIN | C12: L. NEGRA | D12: 350 | H12: VACIO
A13: 46122 | B13: L. NEGRA | C13: CAMPANA | D13: 420 | F13: 34.97 | H13: 619378 | I13: CLINKER
A14: 46125 | B14: CAMPANA | C14: SIDERAR | D14: 150 | H14: VACIO
A15: 46125 | B15: SIDERAR | C15: L. NEGRA | D15: 500 | F15: 34.61 | H15: 1064809 | I15: LODO
A16: 46126 | B16: L. NEGRA | C16: NAVARRO | D16: 320 | H16: 766271
A17: 46127 | B17: NAVARRO | C17: LOMASER | D17: 100 | H17: VACIO
A18: 46127 | B18: LOMASER | C18: ROSARIO | D18: 340 | H18: 896370
A19: 46128 | B19: ROSARIO | C19: L. NEGRA | D19: 550 | H19: PALLETS 300
A20: 46129 | B20: L. NEGRA | C20: ZAPALA | D20: 1030 | F20: 34.78 | H20: 619863 | I20: CLINKER
A21: 46132 | B21: ZAPALA | C21: ALLEN | D21: 240 | H21: VACIO
A22: 46132 | B22: ALLEN | C22: L. NEGRA | D22: 820 | F22: 33.7 | H22: 189778 | I22: YESO LOMA
A23: 46135 | B23: L. NEGRA | C23: CAMPANA | D23: 430 | H23: 294353 | I23: piedra
A24: 46136 | B24: CAMPANA | C24: IBICUY | D24: 100 | H24: VACIO
A25: 46136 | B25: IBICUY | C25: BAJO DEL TORO | D25: 1560 | H25: 122781 | I25: YPF TORO
A26: 46139 | B26: BAJO DEL TORO | C26: ALLEN | D26: 270 | H26: VACIO
A27: 46139 | B27: ALLEN | C27: L. NEGRA | D27: 820 | F27: 34.4 | H27: 189968 | I27: YESO LOMA
A28: 46141 | B28: L. NEGRA | C28: ZAPALA | D28: 1030 | H28: 620528 | I28: CLINKER
A29: 46142 | B29: ZAPALA | C29: ALLEN | D29: 240 | H29: VACIO
D32: =SUM(D3:D31) -> 11700 | F32: =AVERAGE(F3:F30) -> 34.677143 | G32: =AVERAGE(G3:G30) -> #DIV/0! | J32: =SUM(J3:J31) -> 0 | K32: =SUM(K3:K31) -> 1017135.2
B34: -20000
B41: =SUM(B34:B40) -> -20000

Sheet VALENZA
D1: AB742XZ
A2: DIA | B2: SALE DE | C2: LLEGA A | D2: KM REC | E2: TN COM 29 | F2: TN ESC 35 | G2: TN ESC 37,5 | H2: REMITO Nº | I2: MATERIAL | J2: KM VACIOS | K2: $
A3: 46113 | B3: IBICUY | C3: AÑELO | D3: 1430 | H3: 80713 | I3: YPF
A4: 46116 | B4: AÑELO | C4: L. NEGRA | D4: 940 | H4: VACIO
A5: 46118 | B5: L. NEGRA | C5: BAHIA BLANCA | D5: 320 | H5: 764968 | K5: 843834.1
A6: 46119 | B6: BAHIA BLANCA | C6: L. NEGRA | D6: 320 | H6: VACIO
A7: 46120 | B7: L. NEGRA | C7: CAMPANA | D7: 420 | F7: 34.71 | H7: 619196 | I7: CLINKER
A8: 46121 | B8: CAMPANA | C8: SIDERCA | D8: 10 | H8: VACIO
A9: 46122 | B9: SIDERCA | C9: CATAMARCA | D9: 990 | F9: 34.72 | H9: 153128 | I9: SIDERCA | K9: 1701794.6
A10: 46123 | B10: CATAMARCA | C10: CORDOBA | D10: 380 | H10: 503728 | K10: 1057200.1
A11: 46123 | B11: CORDOBA | C11: MALAGUEÑO | D11: 60 | H11: VACIO
A12: 46125 | B12: MALAGUEÑO | C12: ROSARIO | D12: 430 | F12: 34.94 | H12: 303446 | I12: PIEDRA
A13: 46126 | B13: ROSARIO | C13: RAMALLO | D13: 80 | H13: VACIO
A14: 46126 | B14: RAMALLO | C14: L. NEGRA | D14: 500 | F14: 35.37 | H14: 1064945 | I14: LODO
A15: 46128 | B15: L. NEGRA | C15: CAMPANA | D15: 420 | F15: 35.06 | H15: 619771 | I15: CLINKER
A16: 46129 | B16: CAMPANA | C16: IBICUY | D16: 85 | H16: VACIO
A17: 46129 | B17: IBICUY | C17: BAJO DEL TORO | D17: 1470 | H17: 121451 | I17: YPF TORO 5
A18: 46132 | B18: BAJO DEL TORO | C18: ZAPALA | D18: 300 | H18: VACIO
A19: 46133 | B19: ZAPALA | C19: L. NEGRA | D19: 1030 | H19: 162561 | I19: PALLETS
A20: 46135 | B20: L. NEGRA | C20: ZAPALA | D20: 1030 | F20: 34.4 | H20: 620201 | I20: CLINKER
A21: 46136 | B21: ZAPALA | C21: ALLEN | D21: 240 | H21: VACIO
A22: 46136 | B22: ALLEN | C22: L. NEGRA | D22: 820 | F22: 34.2 | H22: 189914 | I22: YESO LOMA
A23: 46139 | B23: L. NEGRA | C23: PIGUE | D23: 260 | H23: 768378 | J23: AE228WV
A24: 46140 | B24: PIGUE | C24: L. NEGRA | D24: 260 | H24: VACIO
A25: 46142 | B25: L. NEGRA | C25: C. FEDERAL | D25: 390 | H25: ???? | I25: PIEDRA
A26: 46142 | B26: C. FEDERAL | C26: IBICUY | D26: 170 | H26: VACIO
D27: 30 A LAS 19
D29: =SUM(D3:D28) -> 12355 | F29: =AVERAGE(F3:F27) -> 34.771429 | G29: =AVERAGE(G3:G27) -> #DIV/0! | J29: =SUM(J3:J28) -> 0 | K29: =SUM(K3:K28) -> 3602828.7
B31: -20000
B32: 20000 | C32: PEAJES
B33: -20000 | C33: ADELANTO | D33: 46115
B38: =SUM(B31:B37) -> -20000 | C38: 46115

Sheet JUAREZ N
D1: AB742XZ
A2: DIA | B2: SALE DE | C2: LLEGA A | D2: KM REC | E2: TN COM 29 | F2: TN ESC 35 | G2: TN ESC 37,5 | H2: REMITO Nº | I2: MATERIAL | J2: KM VACIOS | K2: $
A3: 46120 | B3: HINOJO | C3: CAMPANA | D3: 420 | F3: 35.29 | H3: 619254 | I3: CLINKER | J3: PFN849
A4: 46121 | B4: CAMPANA | C4: IBICUY | D4: 85 | H4: VACIO
A5: 46122 | B5: IBICUY | C5: BAJO DEL TORO | D5: 1560 | H5: 1020309 | I5: YPF TORO
A6: 46125 | B6: BAJO DEL TORO | C6: ALLEN | D6: 270 | H6: VACIO
A7: 46126 | B7: ALLEN | C7: L. NEGRA | D7: 820 | F7: 36.3 | H7: 189436 | I7: YESO LOMA
A8: 46127 | B8: L. NEGRA | C8: CAMPANA | D8: 420 | F8: 35.41 | H8: 619717 | I8: HOLCIM
A9: 46128 | B9: CAMPANA | C9: RAMALLO | D9: 150 | H9: VACIO
A10: 46128 | B10: RAMALLO | C10: L. NEGRA | D10: 500 | F10: 35.26 | H10: 1065466 | I10: ESCORIA
A11: 46129 | B11: L. NEGRA | C11: ZAPALA | D11: 1010 | H11: 619906 | I11: CLINKER
A12: 46132 | B12: ZAPALA | C12: ALLEN | D12: 240 | H12: VACIO
A13: 46132 | B13: ALLEN | C13: L. NEGRA | D13: 820 | F13: 35.4 | H13: 189734 | I13: YESO LOMA
A14: 46134 | B14: L. NEGRA | C14: CAMPANA | D14: 430 | F14: 35.7 | H14: 294328 | I14: PIEDRA
A15: 46135 | B15: CAMPANA | C15: IBICUY | D15: 100 | H15: VACIO
A16: 46136 | B16: IBICUY | C16: AÑELO | D16: 1430 | H16: 122812 | I16: YPF
A17: 46140 | B17: AÑELO | C17: L. NEGRA | D17: 940 | H17: VACIO
A18: 46141 | B18: L. NEGRA | C18: SOLA | D18: 360 | F18: 35.78 | H18: 294823 | I18: PIEDRA
A19: 46142 | B19: SOLA | C19: IBICUY | D19: 180 | H19: VACIO
D20: 30 A LAS 23
D22: =SUM(D3:D21) -> 9735 | F22: =AVERAGE(F3:F20) -> 35.591429 | G22: =AVERAGE(G3:G20) -> #DIV/0! | J22: =SUM(J3:J21) -> 0 | K22: =SUM(K3:K21) -> 0
B24: -20000
B31: =SUM(B24:B30) -> -20000

Sheet TOTALES
A1: CHOFER | B1: FACT. X EQUIPO | C1: KM | D1: TONE COM 29 | E1: TONE ESCAL 35 | F1: TONE ESCAL 37,5 | G1: KM VACIOS | I1: CHOFER | J1: FACTURACION | K1: SUELDO | L1: % | N1: CHOFER | O1: CONSUMO MENSUAL | P1: KM VACIO | R1: CHOFER
A2: GALLASTEGUI | B2: =+GALLASTEGUI!K51 -> 2885882.4 | C2: =+GALLASTEGUI!D51 -> 11020 | D2: =+GALLASTEGUI!E51 -> 0 | E2: =+GALLASTEGUI!F51 -> 0 | F2: =+GALLASTEGUI!G51 -> 35.695714 | G2: =+GALLASTEGUI!J51 -> 0 | I2: GALLASTEGUI | J2: =+B2 -> 2885882.4 | K2: 45163.21 | L2: =+K2/J2*100 -> 1.5649705 | N2: GALLASTEGUI | O2: 33.36 | P2: 1730 | R2: GALLASTEGUI | S2: 154244.69 | T2: =+S2*1.05 -> 161956.92
A3: SCHWINDT | B3: =+SCHWINDT!K52 -> 2758994.6 | C3: =+SCHWINDT!D52 -> 15200 | D3: =+SCHWINDT!E52 -> 0 | E3: =+SCHWINDT!F52 -> 34.497333 | F3: =+SCHWINDT!G52 -> 0 | G3: =+SCHWINDT!J52 -> 0 | I3: SCHWINDT | J3: =+B3 -> 2758994.6 | K3: 43639.78 | L3: =+K3/J3*100 -> 1.5817276 | N3: SCHWINDT | O3: 31.91 | P3: 2580 | R3: SCHWINDT | S3: 167317.68 | T3: =+S3*1.05 -> 175683.56
A4: MARTINEZ | B4: =+#REF! -> #REF! | C4: =+#REF! -> #REF! | D4: =+#REF! -> #REF! | E4: =+#REF! -> #REF! | F4: =+#REF! -> #REF! | G4: =+#REF! -> #REF! | I4: MARTINEZ | J4: =+#REF! -> #REF! | K4: 47674.86 | L4: =+K4/J4*100 -> #REF! | N4: MARTINEZ | O4: 31.25 | P4: 760 | R4: MARTINEZ | S4: 201532.83 | T4: =+S4*1.05 -> 211609.47
A5: SAENZ | B5: =+'SAENZ BURUAGA'!K63 -> 4826475 | C5: =+'SAENZ BURUAGA'!D63 -> 12285 | D5: =+'SAENZ BURUAGA'!E63 -> 0 | E5: =+'SAENZ BURUAGA'!F63 -> 34.838 | F5: =+'SAENZ BURUAGA'!G63 -> 0 | G5: =+'SAENZ BURUAGA'!J63 -> 0 | I5: SAENZ | J5: =+B5 -> 4826475 | K5: 53281.79 | L5: =+K5/J5*100 -> 1.1039483 | N5: SAENZ | O5: 34.22 | P5: 490 | R5: GONZALEZ | S5: 154894.65 | T5: =+S5*1.05 -> 162639.38
A6: SCHMIDT | B6: =+SCHMIDT!K63 -> 0 | C6: =+SCHMIDT!D63 -> 22290 | D6: =+SCHMIDT!E63 -> 0 | E6: =+SCHMIDT!F63 -> 34.173636 | F6: =+SCHMIDT!G63 -> 0 | G6: =+SCHMIDT!J63 -> 0 | I6: SCHWINDT | J6: =+B6 -> 0 | K6: 45111.55 | L6: =+K6/J6*100 -> #DIV/0! | N6: SCHMIDT | O6: 34.59 | P6: 910 | R6: CHIARELLI | S6: 138220.55 | T6: =+S6*1.05 -> 145131.58
A7: PULLOL | B7: =+#REF! -> #REF! | C7: =+#REF! -> #REF! | D7: =+#REF! -> #REF! | E7: =+#REF! -> #REF! | F7: =+#REF! -> #REF! | G7: =+#REF! -> #REF! | I7: PULLOL | J7: =+#REF! -> #REF! | K7: 40232.49 | L7: =+K7/J7*100 -> #REF! | N7: PULLOL | O7: 34.13 | P7: 1230 | R7: SCHMIDT | S7: 157469.82 | T7: =+S7*1.05 -> 165343.31
A8: CEJAS | B8: =+CEJAS!K58 -> 0 | C8: =+CEJAS!D58 -> 17150 | D8: =+CEJAS!E58 -> 0 | E8: =+CEJAS!F58 -> 34.05 | F8: =+CEJAS!G58 -> 0 | G8: =+CEJAS!J58 -> 0 | I8: CEJAS | J8: =+CEJAS!K58 -> 0 | K8: 39527.61 | L8: =+K8/J8*100 -> #DIV/0! | N8: CEJAS | O8: 37.24 | P8: 485 | R8: FACUNDO G. | S8: 137470.69 | T8: =+S8*1.05 -> 144344.22
A9: VALERGA | B9: =+VALERGA!K47 -> 949499.51 | C9: =+VALERGA!D47 -> 18285 | D9: =+VALERGA!E47 -> 0 | E9: =+VALERGA!F47 -> #REF! | F9: =+VALERGA!G47 -> 36.07 | G9: =+VALERGA!J47 -> 0 | I9: VALERGA | J9: =+VALERGA!K47 -> 949499.51 | K9: 39458.22 | L9: =+K9/J9*100 -> 4.1556862 | N9: VALERGA | O9: 34.78 | P9: 2665 | R9: CANTERO | S9: 139161.56 | T9: =+S9*1.05 -> 146119.64
A10: PUCHETA | B10: =+PUCHETA!K49 -> 0 | C10: =+PUCHETA!D49 -> 18655 | D10: =+PUCHETA!E49 -> 0 | E10: =+PUCHETA!F49 -> 34.904615 | F10: =+PUCHETA!G49 -> 0 | G10: =+PUCHETA!J49 -> 0 | I10: PUCHETA | J10: =+PUCHETA!K49 -> 0 | K10: 41120.3 | L10: =+K10/J10*100 -> #DIV/0! | N10: PUCHETA | O10: 35.02 | P10: 225
A11: DIORIO | B11: =+#REF! -> #REF! | C11: =+#REF! -> #REF! | D11: =+#REF! -> #REF! | E11: =+#REF! -> #REF! | F11: =+#REF! -> #REF! | G11: =+#REF! -> #REF!
A12: CAVIA | B12: =+#REF! -> #REF! | C12: =+#REF! -> #REF! | D12: =+#REF! -> #REF! | E12: =+#REF! -> #REF! | F12: =+#REF! -> #REF! | G12: =+#REF! -> #REF!
A13: CALIGIURI | B13: =+CALIGIURI!K49 -> 907612.2 | C13: =+CALIGIURI!D49 -> 5380 | D13: =+CALIGIURI!E49 -> 0 | E13: =+CALIGIURI!F49 -> 0 | F13: =+CALIGIURI!G49 -> 35.8075 | G13: =+CALIGIURI!J49 -> 0
A14: SAGANIAS | B14: =+#REF! -> #REF! | C14: =+#REF! -> #REF! | D14: =+#REF! -> #REF! | E14: =+#REF! -> #REF! | F14: =+#REF! -> #REF! | G14: =+#REF! -> #REF!
A15: HERLEIN | B15: =GALLASTEGUI!#REF! -> #REF! | C15: =+#REF! -> #REF! | D15: =+#REF! -> #REF! | E15: =+#REF! -> #REF! | F15: =+#REF! -> #REF! | G15: =+#REF! -> #REF!
